Workbook
Name _Order1: 255
Name _Regression_Int: 1
Name \a: #N/A
Name Countries: [1]List!$A$1:$A$31
Name CUAD.0: #N/A
Name CUAD.0CONT: #N/A
Name CUAD.1: #N/A
Name CUAD.1CONT: #N/A
Name CUAD.2: #N/A
Name CUAD.2CONT: #N/A
Name fech_cambi: #REF!
Name fech_cambi: #REF!
Name fech_cambi: #REF!
Name fech_cambi: #REF!
Name fech_cambi: #REF!
Name fech_cambi: #REF!
Name fech_cambi: #REF!
Name gv: #REF!
Name gv: #REF!
Name gv: #REF!
Name gv: #REF!
Name gv: #REF!
Name gv: #REF!
Name gv: #REF!
Name ip: #REF!
Name ip: #REF!
Name ip: #REF!
Name ip: #REF!
Name ip: #REF!
Name ip: #REF!
Name ip: #REF!
Name iq: #REF!
Name iq: #REF!
Name iq: #REF!
Name iq: #REF!
Name iq: #REF!
Name iq: #REF!
Name iq: #REF!
Name PPP_: '[2]10. Mobility Matrices'!$N$60
Name PPP_: '[3]10. Mobility Matrices'!$N$60
Name PPP_: '[4]10. Mobility Matrices'!$N$60
Name Títulos_a_imprimir_IM: '[5]SAN LUIS'!$A$102:$IV$107,'[5]SAN LUIS'!$A$1:$A$65536
Name Títulos_a_imprimir_IM: '[6]SAN LUIS'!$A$102:$IV$107,'[6]SAN LUIS'!$A$1:$A$65536
Name Variables: [1]List!$B$1:$B$45

Sheet Title
B10: CEQ DATA CENTER ON FISCAL REDISTRIBUTION
B11: CEQ Standard indicators web version 4.0
B12: May 15, 2020
B14: The Commitment to Equity (CEQ) Institute works to reduce inequality and poverty through comprehensive and rigorous tax and benefit incidence analysis, and active engagement with the policy community. Building on the seven years of achievements of the CEQ project, the Institute was founded in May 2015 with Nora Lustig as its Director. The CEQ Data Center on Fiscal Redistribution consists of an information and monitoring system with key indicators and a harmonized micro-fiscal database to assess the impact of fiscal systems on inequality and poverty. Among the key questions that the Data Center will allow users to address are: (i) What is the impact of taxes and transfers on inequality and poverty? (ii) How progressive is public spending on education and health? (iii) What is the contribution of specific taxes and transfers to the overall impact? (iv) How effective is the fiscal system in reducing inequality and poverty? (v) How much additional fiscal and redistributive effort is required to end extreme poverty and equalize opportunities? (vi) What is the impact of fiscal policy reforms on inequality and the poverty? The application of the common analytical framework described in the CEQ Handbook (Lustig, editor, 2018) allows for cross-country comparison and benchmarking, both of which can be influential in the context of in-country policy dialogue. http://www.commitmentoequity.org/publications-ceq-handbook/ The indicators presented here are for the United States and 46 low and middle income countries in the CEQ Data Center: Albania, Argentina, Armenia, Bolivia, Belarus, Brazil, Burkina Faso, Chile, Colombia, Comoros, Costa Rica, Croatia, Dominican Republic, Ecuador, Egypt, El Salvador, Ethiopia, Georgia, Ghana, Guatemala, Guinea, Honduras, Indonesia, Iran, Jordan, Kenya, Mali, Mexico, Mongolia, Namibia, Nicaragua, Niger, Panama, Paraguay, Peru, Poland, Romania, Russia, South Africa,Spain, Sri Lanka, Tanzania, Tunisia, Uganda, Ukraine, United States, Uruguay and Venezuela. The CEQ Data Center has been made possible thanks to the generous support of the Bill & Melinda Gates Foundation.
B16: For all Data Center inquiries and data requests: datacenter@ceqinstitute.org

Sheet Contents
C2: Contents
B3: 1 | C3: CEQ methodology
B4: 2 | C4: CEQ Core income concepts
B5: 3 | C5: General information
B6: 4 | C6: Taxes and transfers as a share of GDP
B7: 5 | C7: Inequality gini coefficient
B8: 6 | C8: Inequality Theil Index
B9: 7 | C9: Inequality 90/10 ratio
B10: 8 | C10: Inequality Absolute Gini
B11: 9 | C11: Poverty headcount ratio 2005PPP
B12: 10 | C12: Poverty headcount ratio 2011PPP
B13: 11 | C13: Poverty gap and squared poverty gap PDI 2005PPP
B14: 12 | C14: Poverty gap and squared poverty gap PDI 2011PPP
... B29: 27 | C29: Household surveys

Sheet 1. CEQ Methodology
A1: Go to Contents
B8: CEQ Methodology
B10: Lustig, Nora, editor. 2018. Commitment to Equity Handbook. Estimating the Impact of Fiscal Policy on Inequality and Poverty (Brookings Institution Press and CEQ Institute, Tulane University).
B11: Online version available by clicking here.
B13: The Commitment to Equity Handbook. Estimating the Impact of Fiscal Policy on Inequality and Poverty is a unique manual with a step-by-step guide to apply fiscal incidence analysis as well as country studies to illustrate the impact. The handbook is open access under a CC-BY-NC-ND 4.0 International Public License thanks to the generous support of the Bill & Melinda Gates Foundation.

Sheet 2. CEQ Core income concepts 
A1: Go to Contents
B5: CEQ Core income concepts
B60: Lustig, Nora, editor. 2018. Commitment to Equity Handbook. Estimating the Impact of Fiscal Policy on Inequality and Poverty (Brookings Institution Press and CEQ Institute, Tulane University).

Sheet 3. General information
A1: Go to Contents
B3: General information on the CEQ assessments
B4: NOTE: FOR SOURCES AND CITATIONS SEE BOTTOM OF PAGE
B6: Country | C6: Year of survey | D6: Year of budgetary data and fiscal system | E6: Methodology based on CEQ Handbook *** | F6: Welfare aggregate | I6: Imputed rent calculated for owner's occupied housing | J6: Indirect effects of indirect taxes | K6: Indirect effects of subsidies | L6: Method for health expenditure allocation**** | M6: GNI per capita for fiscal year in 2005ppp | N6: GNI per capita for fiscal year in 2011ppp | O6: Population | P6: GDP (current LCU) | Q6: Household Survey Name
F7: Consumption -or income- based | G7: Variable observed in survey | H7: Consumption of own production
A8: =A7+1 -> 1 | B8: *,** Albania (2015) | C8: 2015 | D8: 2015 | E8: CEQHB 2018 | F8: C | G8: Disposable Income | I8: No | J8: Yes (excise taxes on intermediate goods) | N8: 11800 | O8: 2880703 | P8: 1434307000000 | Q8: Household Budget Survey
A9: =A8+1 -> 2 | B9: Argentina (2012) | C9: 2012-13 | D9: 2012 | E9: CEQHB 2013 | F9: I | G9: Net Market Income | H9: Yes | I9: Yes | J9: Yes | K9: No | L9: Insurance value - Intermediate | M9: 7402.6 | N9: 19130 | O9: 36138213 | P9: 2.6379138e+12 | Q9: Encuesta Nacional de Gasto de los Hogares 2012-2013
A10: =A9+1 -> 3 | B10: Armenia (2011) | C10: 2011 | D10: 2011 | E10: CEQHB 2018 | F10: I | G10: Disposable Income | H10: Yes | I10: Yes | J10: No | K10: No | L10: Actual Use | M10: 2156.7 | N10: 7270 | O10: 2965466.5 | P10: 3777945600000 | Q10: Integrated Living Conditions Survey 2011
A11: =A10+1 -> 4 | B11: *,** Belarus (2015) | C11: 2015 | D11: 2016 | F11: C | G11: Disposable Income | J11: Yes | K11: Yes | N11: 16450.216 | O11: 9489616 | P11: 89909810000 | Q11: Household Budget Survey
A12: =A11+1 -> 5 | B12: Bolivia (2009) | C12: 2009 | D12: 2009 | E12: CEQHB 2011 | F12: I | G12: Net Market Income | H12: No | I12: Yes | J12: No | K12: No | L12: Insurance value - Intermediate | M12: 1130.5 | N12: 4910 | O12: 10232625 | P12: 1.2172675e+11 | Q12: Encuesta de Hogares 2009
A13: =A12+1 -> 6 | B13: Brazil (2008) | C13: 2008-09 | D13: 2009 | E13: CEQHB 2018 | F13: I | G13: Market Income | H13: Yes | I13: Yes | J13: No | K13: No | L13: Insurance value - Access | M13: 4994.1 | N13: 12920 | O13: 1.905193e+08 | P13: 3333039000000 | Q13: Pesquisa de Orçamentos Familiares 2008-2009
A14: =A13+1 -> 7 | B14: *,** Burkina Faso (2014) | C14: 2014 | D14: 2014 | E14: CEQHB 2018 | F14: C | G14: Disposable Income | H14: Yes | I14: Yes | N14: 1620 | O14: 17586017 | P14: 6119568000000 | Q14: Enquête Multisectorielle Continue
A15: =A14+1 -> 8 | B15: Chile (2013) | C15: 2013 | D15: 2013 | E15: CEQHB 2013 | F15: I | G15: Net Market Income | H15: Yes | I15: Yes | J15: Yes (fuel tax) | K15: No | L15: Insurance value - Intermediate | M15: 9354.6 | N15: 21600 | O15: 17256219 | P15: 137212064000000 | Q15: Encuesta de Caracterización Socioeconómica Nacional 2013
A16: =A15+1 -> 9 | B16: Colombia (2010) | C16: 2010 | D16: 2010 | E16: CEQHB 2018 | F16: I | G16: Market Income | H16: Yes | I16: Yes | J16: No | K16: No | L16: Insurance value - Intermediate | M16: 3821 | N16: 10160 | O16: 45062798 | P16: 544924000000000 | Q16: Encuesta Nacional de Calidad de Vida 2010
B17: Colombia (2014) | C17: 2014 | D17: 2014 | E17: CEQHB 2018 | F17: I | G17: Market Income | H17: Yes | I17: Yes | J17: No | K17: No | L17: Insurance value - Intermediate | N17: 12940 | O17: 47203862 | P17: 756152000000000 | Q17: Encuesta Nacional de Calidad de Vida 2014
A18: =A16+1 -> 10 | B18: *,** Comoros (2014) | C18: 2014 | E18: CEQHB 2013 | F18: C | G18: Disposable Income | H18: Yes | I18: Yes | N18: 2529 | O18: 747155 | P18: 425713000000 | Q18: Enquête sur l’emploi, le secteur informel et la consommation des ménages aux Comores 2014
A19: =A18+1 -> 11 | B19: Costa Rica (2010) | C19: 2010 | D19: 2010 | E19: CEQHB 2011 | F19: I | G19: Market Income | H19: No | J19: No | K19: No | L19: Insurance value - Access | M19: 5393.6 | N19: 12320 | O19: 4551553 | P19: 19086721000000 | Q19: Encuesta Nacional de Hogares 2010
A20: =A19+1 -> 12 | B20: *,** Croatia (2014) | C20: 2014 | D20: 2014 | E20: CEQHB 2018 | F20: I | G20: Net Market Income | H20: No | J20: No | K20: No | L20: Insurance value - Access | N20: 21640 | O20: 4238389 | P20: 3.3156965e+11 | Q20: Croatian Household Budget Survey
A21: =A20+1 -> 13 | B21: Dominican Republic (2006) | C21: 2006-07 | D21: 2013 | E21: CEQHB 2018 | F21: I | G21: Market Income | H21: Yes | I21: Yes | J21: No | K21: No | L21: Insurance value - Access & Intermediate | N21: 11770 | O21: 9234446 | P21: 2590678302100 | Q21: Encuesta Nacional de Ingresos y Gastos de los Hogares 2006-2007
A22: =A21+1 -> 14 | B22: Ecuador (2011) | C22: 2011-12 | D22: 2011 | E22: CEQHB 2013 | F22: I | G22: Market Income | H22: No | I22: Yes | J22: No | K22: No | L22: Insurance value - Intermediate | M22: 3421.4 | N22: 9770 | O22: 15223535 | P22: 79276664000 | Q22: Encuesta Nacional de Ingresos y Gastos de los Hogares Urbanos y Rurales 2011-2012
A23: =A22+1 -> 15 | B23: *,** Egypt (2015) | C23: 2015 | D23: 2015 | E23: CEQHB 2018 | F23: C | G23: Disposable Income | H23: Yes | I23: Yes | J23: Yes | K23: Yes | N23: 10068.822 | O23: 92442547 | P23: 2443900000000 | Q23: Household Income, Expenditure, and Consumption Survey
A24: =A23+1 -> 16 | B24: El Salvador (2011) | C24: 2011 | D24: 2011 | E24: CEQHB 2018 | F24: I | G24: Market Income | H24: Yes | I24: Yes | J24: No | K24: No | L24: Insurance value - Intermediate | M24: 3016.3 | N24: 6310 | O24: 6213730 | P24: 20283780000 | Q24: Encuesta de Hogares de Propositos Multiples 2011
A25: =A24+1 -> 17 | B25: Ethiopia (2010) | C25: 2010-11 | D25: 2011 | E25: CEQHB 2013 | F25: C | G25: Disposable Income | H25: Yes | I25: Yes | J25: Yes | K25: No | L25: Insurance value - Access | N25: 1160 | O25: 76073949 | P25: 505646000000 | Q25: Household Consumption Expediture Survey 2010 -2011 and Welfare Monitoring Survey 2010-2011
A26: =A25+1 -> 18 | B26: Georgia (2013) | C26: 2013 | D26: 2013 | E26: CEQHB 2013 | F26: I | G26: Net Market Income | H26: Yes | I26: Yes | J26: No | K26: No | L26: Insurance value - Intermediate | M26: 2119.1 | N26: 8530 | O26: 3675078 | P26: 2.6847354e+10 | Q26: Integrated Household Survey 2013
A27: =A26+1 -> 19 | B27: Ghana (2012) | C27: 2012-13 | D27: 2013 | E27: CEQHB 2018 | F27: C | G27: Disposable Income | H27: Yes | I27: No | J27: Yes (import duties and fuel excises on petrol and diesel) | K27: Yes (electricity subsidy) | L27: Actual Use | N27: 3860 | O27: 26347424 | P27: 93415886300 | Q27: Living Standards Survey, Round 6 2012-2013
A28: =A27+1 -> 20 | B28: Guatemala (2011) | C28: 2011 | D28: 2011 | E28: CEQHB 2013 | F28: I | G28: Net Market Income | H28: Yes | I28: Yes | J28: No | K28: No | L28: Insurance value - Access | M28: 2174.1 | N28: 6630 | O28: 14636886 | P28: 371278000000 | Q28: Encuesta Nacional de Condiciones de Vida 2011
A29: =A28+1 -> 21 | B29: *,** Guinea (2012) | C29: 2012 | D29: 2016 | E29: CEQHB 2018 | N29: 1620 | O29: 10652029 | P29: 5.3358078e+13 | Q29: Enquête Légère pour l’Evaluation de la Pauvreté 2012
A30: =A29+1 -> 22 | B30: Honduras (2011) | C30: 2011 | D30: 2011 | E30: CEQHB 2013 | F30: I | G30: Market Income | H30: No | I30: Yes | J30: No | K30: No | L30: Insurance value - Basic | M30: 1490.7 | N30: 3820 | O30: 8171770 | P30: 335027800000 | Q30: Encuesta Permanente de Hogares de Propositos Multiples 2011
A31: =A30+1 -> 23 | B31: Indonesia (2012) | C31: 2012 | D31: 2012 | E31: CEQHB 2013 | F31: C | G31: Disposable Income | H31: Yes | I31: Yes | J31: Yes | K31: Yes | L31: Insurance value - Access | M31: 1668.6 | N31: 9160 | O31: 245265690 | P31: 8.2418643e+15 | Q31: Survei Sosial-Ekonomi Nasional 2012
A32: =A31+1 -> 24 | B32: Iran (2011) | C32: 2011-12 | D32: 2011-12 | E32: CEQHB 2013 | F32: I | G32: Market Income | H32: No | I32: Yes | J32: No | K32: No | L32: Insurance value - Access | N32: 17625 | O32: 79511694 | P32: 6.2457657e+15 | Q32: Iranian Urban and Rural Household Income and Expenditure Survey 2011-2012
A33: =A32+1 -> 25 | B33: Jordan (2010) | C33: 2010-11 | D33: 2010 | E33: CEQHB 2013 | F33: C | G33: Disposable Income | H33: Yes | I33: Yes | J33: No | K33: Yes | L33: Insurance value - Access | M33: 2807.8 | N33: 9200 | O33: 5961481.8 | P33: 1.8762019e+10 | Q33: Household Expenditure and Income Survey 2010-2011
A34: =A33+1 -> 26 | B34: *,** Kenya (2015) | C34: 2015-16 | D34: 2015-16 | E34: CEQHB 2013 | F34: C | G34: Disposable Income | K34: No | N34: 3065 | O34: 48465011 | P34: 6653574007897 | Q34: Integrated Household Budget Survey 2015-2016
A35: =A34+1 -> 27 | B35: *,** Mali (2014) | C35: 2014 | D35: 2014 | F35: C | G35: Disposable Income | J35: Yes | N35: 1920 | O35: 16934220 | P35: 7092793041100 | Q35: Enquête Agricole de Conjoncture Intégrée
A36: =A35+1 -> 28 | B36: Mexico (2010) | C36: 2010 | D36: 2010 | E36: CEQHB 2011 | F36: I | G36: Net Market Income | H36: Yes | I36: Yes | J36: No | K36: Yes (fuel subsidy) | L36: Insurance value - Intermediate | M36: 7942.5 | N36: 14660 | O36: 112600583 | P36: 13075798000000 | Q36: Encuesta Nacional de Ingresos y Gastos de los Hogares 2010
B37: Mexico (2012) | C37: 2012 | D37: 2012 | E37: CEQHB 2018 | F37: I | G37: Net Market Income | H37: Yes | I37: Yes | J37: No | K37: Yes (fuel subsidy) | L37: Insurance value - Intermediate | M37: 8534.3402 | N37: 16340 | O37: 117284429 | P37: 15626906634000 | Q37: Encuesta Nacional de Ingresos y Gastos de los Hogares 2012
B38: Mexico (2014) | C38: 2014 | D38: 2014 | E38: CEQHB 2018 | F38: I | G38: Net Market Income | H38: Yes | I38: Yes | J38: No | K38: Yes (fuel subsidy) | L38: Insurance value - Intermediate | N38: 17080 | O38: 119906312 | P38: 17259799421000 | Q38: Encuesta Nacional de Ingresos y Gastos de los Hogares 2014
A39: =A36+1 -> 29 | B39: *,** Mongolia (2016) | C39: 2016 | D39: 2016 | E39: CEQHB 2013 | F39: I | G39: Net Market Income | J39: No | K39: No | N39: 11250 | O39: 3056359 | P39: 2.3942866e+13 | Q39: Mongolia’s Household Socio Economic Survey 2016
A40: =A39+1 -> 30 | B40: *,** Namibia (2009) | C40: 2009 | D40: 2009 -10 | E40: CEQHB 2013 | N40: 7970 | O40: 2118874 | P40: 8.2599189e+10 | Q40: Household Income and Expenditure Survey
A41: =A40+1 -> 31 | B41: Nicaragua (2009) | C41: 2009 | D41: 2009 | E41: CEQHB 2013 | F41: I | G41: Net Market Income | H41: Yes | I41: Yes | J41: No | K41: No | L41: Insurance value - Access | M41: 3876.2756 | N41: 3660 | O41: 5765733 | P41: 1.9088798e+11 | Q41: Encuesta Nacional de Medicion de Nivel de Vida 2009
A42: =A41+1 -> 32 | B42: *,** Niger (2014) | C42: 2014 -15 | D42: 2014 | N42: 800 | O42: 17114761 | P42: 3024277000000 | Q42: Enquête nationale sur les Conditions de Vie des Ménages et Agriculture
A43: =A42+1 -> 33 | B43: Panama (2016) | C43: 2016 | D43: 2015 | E43: CEQHB 2018 | F43: I | G43: Net Market Income | H43: Yes | I43: Yes | J43: No | K43: No | L43: Insurance value - Intermediate | N43: 20900 | O43: 3941606 | P43: 55187800000 | Q43: ﻿Encuesta de Propósitos Múltiples 2016
A44: =A43+1 -> 34 | B44: Paraguay (2014) | C44: 2014 | D44: 2014 | E44: CEQHB 2013 | F44: I | G44: Net Market Income | H44: Yes | I44: Yes | J44: No | K44: No | L44: Insurance value - Intermediate | N44: 11170 | O44: 6780504 | P44: 138259884742000 | Q44: Encuesta Permanente de Hogares 2014
A45: =A44+1 -> 35 | B45: Peru (2009) | C45: 2009 | D45: 2009 | E45: CEQHB 2011 | F45: I | G45: Market Income | H45: Yes | I45: No | J45: No | K45: No | L45: Insurance value - Intermediate | M45: 3087.8 | N45: 8450 | O45: 29553339 | P45: 392565000000 | Q45: Encuesta Nacional de Hogares sobre Condiciones de Vida y Pobreza 2009
B46: Peru (2011) | C46: 2011 | D46: 2011 | E46: CEQHB 2018 | F46: I | G46: Market Income | H46: Yes | I46: No | J46: No | K46: No | L46: Insurance value - Intermediate | N46: 9680 | O46: 29700727 | P46: 473049000000 | Q46: Encuesta Nacional de Hogares sobre Condiciones de Vida y Pobreza 2011
A47: =A45+1 -> 36 | B47: *,** Poland (2014) | C47: 2014 | D47: 2014 | E47: CEQHB 2013 | F47: I | G47: Market Income | J47: Yes | L47: Insurance value - Access | N47: 24740 | O47: 38011735 | P47: 1720430000000 | Q47: Polish Household Budget Survey
A48: =A47+1 -> 37 | B48: *,** Romania (2016) | C48: 2016 | D48: 2016 | E48: CEQHB 2018 | K48: No | N48: 17608.152 | O48: 19702332 | P48: 765135400000 | Q48: Romanian Household Budget Survey
A49: =A48+1 -> 38 | B49: Russia (2010) | C49: 2010 | D49: 2010 | E49: CEQHB 2018 | F49: I | G49: Net Market Income | H49: Yes | I49: No | J49: No | K49: No | L49: Insurance value - Access | M49: 6151.6 | N49: 19860 | O49: 1.3584556e+08 | P49: 46308500000000 | Q49: Russian Longitudinal Monitoring Survey of Higher School of Economics 2010
A50: =A49+1 -> 39 | B50: South Africa (2010) | C50: 2010-11 | D50: 2010 | E50: CEQHB 2013 | F50: I | G50: Net Market Income | H50: No | I50: Yes | J50: Yes | K50: Yes | L50: Insurance value - Intermediate | M50: 5778.3 | N50: 11400 | O50: 50423022 | P50: 2659366000000 | Q50: Income and Expenditure Survey 2010-2011
A51: =A50+1 -> 40 | B51: Sri Lanka (2009) | C51: 2009-10 | D51: 2010 | E51: CEQHB 2018 | F51: C | G51: Disposable Income | H51: Yes | I51: Yes | J51: No | K51: No | L51: Insurance value - Access | M51: 25823.6 | N51: 8260 | O51: 20337761 | P51: 6413668000000 | Q51: Household Income and Expenditure Survey 2009-2010
A52: =A51+1 -> 41 | B52: Tanzania (2011) | C52: 2011-12 | D52: 2011-12 | E52: CEQHB 2018 | F52: C | G52: Disposable Income | H52: No | I52: No | J52: Yes (fuel and import duties tax) | K52: Yes (electricity subsidy) | L52: Actual Use | N52: 2235 | O52: 42270137 | P52: 41120400000000 | Q52: Household Budget Survey 2011-2012
A53: =A52+1 -> 42 | B53: Tunisia (2010) | C53: 2010 | D53: 2010 | E53: CEQHB 2013 | F53: C | G53: Disposable Income | H53: Yes | I53: Yes | J53: No | K53: No | L53: Actual Use | M53: 3624.8 | N53: 9740 | O53: 9706340 | P53: 6.3440855e+10 | Q53: National Survey on Household Budget, Consumption and Standard of Living 2010
A54: =A53+1 -> 43 | B54: Uganda (2012) | C54: 2012-13 | D54: 2012-13 | E54: CEQHB 2013 | F54: C | G54: Disposable Income | H54: Yes | I54: Yes | J54: No | K54: No | L54: Actual Use | N54: 1625 | O54: 32250627 | P54: 63740291673900 | Q54: Uganda National Household Survey 2012- 2013
A55: =A54+1 -> 44 | B55: *,** Ukraine (2016) | C55: 2016 | D55: 2016 | E55: CEQHB 2018 | J55: Yes | K55: Yes | N55: 8210 | O55: 45004645 | P55: 2385367000000 | Q55: Household Living Conditions Survey
A56: =A55+1 -> 45 | B56: United States (2011) | C56: 2011 | D56: 2011 | E56: CEQHB 2013 | F56: I | G56: Net Market Income | J56: No | K56: No | N56: 50710 | O56: 311718857 | P56: 15517926000000 | Q56: Current Population Survey 2011
A57: =A56+1 -> 46 | B57: Uruguay (2009) | C57: 2009 | D57: 2009 | E57: CEQHB 2018 | F57: I | G57: Market Income | H57: Yes | I57: Yes | J57: No | K57: No | L57: Insurance value - Intermediate | M57: 6606.3 | N57: 14880 | O57: 3010285 | P57: 714523446000 | Q57: Encuesta Continua de Hogares 2009
A58: =A57+1 -> 47 | B58: Venezuela (2013) | C58: 2013 | D58: 2013 | E58: CEQHB 2013 | F58: I | G58: Disposable Income | H58: No | I58: Yes | J58: No | K58: No | L58: Insurance value - Basic | N58: 17740 | O58: 29790689 | P58: 2245843966000 | Q58: Encuesta Nacional de Hogares por Muestreo (ENHM), Sistema de Indicadores de Coyuntura (SIC). Tercer trimestre 2013
C61: not applicable; means that the indicator should not be calculated due to methodological reasons or characteristics of the fiscal system.
C63: not calculated; means that the indicator was not calculated by the author/s.
C65: not available; means that the indicator was calculated but it is not publicly available, requests should be put directly to author/s.
C67: not available; means that the indicator is no longer published on the World Bank's Data Bank.
C69: not available; means that the indicator is no published on the World Bank's report
B72: * The information published here is from World Bank led CEQ assessments and has not undergone comprehensive quality control by the CEQ Institute.
B73: ** At least some information for this CEQ Assessment was extracted directly from World Bank Policy Research Working Papers, Reports, Working Papers (numbered series) and Poverty Assessment.
B74: *** The characteristics of each Handbook versions are:
B75: CEQHB 2011:The 2011 Handbook describes the original CEQ methodology. It includes 5 income concepts (market, net market, disposable, consumable and final incomes). The income variables are constructed separately for the two standard scenarios of the CEQ methodology, namely contributory pensions as deferred income (PDI) and contributory pensions as a government transfer (PGT). In this version of the methodology the survey totals are scaled up to match the budgetary totals.
B76: CEQHB 2013: The 2013 Handbook describes the second version of the CEQ methodology. It includes 7 income concepts, adding gross and taxable income to the 5 original income concepts. As previously, the income variables are constructed separately for the two standard scenarios of the CEQ methodology, PDI, and PGT. This version of the methodology does not scale up survey’s totals, but it does scale down indirect taxes and transfers in kind. See page 259 of Lustig ed (2018) for more information on scaling down.
B77: CEQHB 2018: The 2018 Handbook describes the third, and current, version of the CEQ methodology. It includes 8 income concepts, adding market income plus pensions to the 2013 income concepts. The income variables are constructed only once for both scenarios of the CEQ methodology, but the scenarios are analyzed separately using a different reference income, namely Market Income plus Pensions for the PDI scenario, and Market Income for the PGT scenario. Similarly to Handbook 2013, this version of the CEQ methodology scales down indirect taxes and transfers in kind.
B78: **** The definition of the health expenditure allocation is the following:
B79: Actual use: refers to the case in which the public health expenditure is allocated to the individuals who report using the service.
B80: Insurance Value:
B81: Basic: the same per capita health benefit is allocated to the whole population. This method is generally used when the whole population is eligible to use the public health service and there is no information for further disaggregation available.
B82: Access: a different per capita health benefit is allocated according to the system accessed. This method generally is used when there is more than one health system, and information on access is available.
B83: Intermediate: a different per capita health benefit is allocated according to the level of care accessed. This method is generally used when the health system provides at least two levels of care, within the public health system.
... B118: Source: CEQ Institute’s Data Center on Fiscal Redistribution. Based on the following Master Workbooks of Results, for United States the source is the publication of Higgins, et al. (2016):
A119: =A8 -> 1 | B119: =(CONCATENATE(B8,": ",'26. Source - CEQ MWBs'!C11)) -> *,** Albania (2015): n.a.
A120: =A9 -> 2 | B120: =(CONCATENATE(B9,": ",'26. Source - CEQ MWBs'!C12)) -> Argentina (2012): Rossignolo, Dario. 2017. “CEQ Master Workbook: Argentina (2012-2013),” CEQ Data Center on Fiscal Redistribution (CEQ Institute, Tulane University). Jun 8, 2018.
A121: =A10 -> 3 | B121: =(CONCATENATE(B10,": ",'26. Source - CEQ MWBs'!C13)) -> Armenia (2011): Younger, Stephen D., Artsvi Khachatryan, Gohar Gyulumyan, Nistha Sinha, and Ulrich Bartsch. 2019. “CEQ Master Workbook: Armenia (2011),” CEQ Data Center on Fiscal Redistribution (CEQ Institute, Tulane University and the World Bank). June 8, 2019.
A122: =A11 -> 4 | B122: =(CONCATENATE(B11,": ",'26. Source - CEQ MWBs'!C14)) -> *,** Belarus (2015): n.a.
A123: =A12 -> 5 | B123: =(CONCATENATE(B12,": ",'26. Source - CEQ MWBs'!C15)) -> Bolivia (2009): Paz Arauco, Veronica, George Gray-Molina, Wilson Jimenez and Ernesto Yañez. 2014. “CEQ Master Workbook: Bolivia (2009),” CEQ Data Center on Fiscal Redistribution (CEQ Institute, Tulane University). September 22, 2014.
A124: =A13 -> 6 | B124: =(CONCATENATE(B13,": ",'26. Source - CEQ MWBs'!C16)) -> Brazil (2008): Higgins, Sean, Claudiney Pereira, and, Maynor Cabrera. 2019. “CEQ Master Workbook: Brazil (2008-2009),” CEQ Data Center on Fiscal Redistribution (CEQ Institute, Tulane University). May 3, 2019.
A125: =A14 -> 7 | B125: =(CONCATENATE(B14,": ",'26. Source - CEQ MWBs'!C17)) -> *,** Burkina Faso (2014): n.a.
A126: =A15 -> 8 | B126: =(CONCATENATE(B15,": ",'26. Source - CEQ MWBs'!C18)) -> Chile (2013): Martinez-Aguilar, Sandra and Eduardo Ortiz-Juarez. 2016. “CEQ Master Workbook: Chile (2013),” CEQ Data Center on Fiscal Redistribution (CEQ Institute, Tulane University and the World Bank). October 7, 2016.
A127: =A16 -> 9 | B127: =(CONCATENATE(B16,": ",'26. Source - CEQ MWBs'!C19)) -> Colombia (2010): Melendez, Marcela and Valentina Martinez. 2019. “CEQ Master Workbook: Colombia (2010),” CEQ Data Center on Fiscal Redistribution (CEQ Institute, Tulane University and Inter-American Development Bank). February 20, 2019.
A128: =A17 -> 0 | B128: =(CONCATENATE(B17,": ",'26. Source - CEQ MWBs'!C20)) -> Colombia (2014): Melendez, Marcela and Valentina Martinez. 2019. “CEQ Master Workbook: Colombia (2014),” CEQ Data Center on Fiscal Redistribution (CEQ Institute, Tulane University and Inter-American Development Bank). February 28, 2019.
A129: =A18 -> 10 | B129: =(CONCATENATE(B18,": ",'26. Source - CEQ MWBs'!C21)) -> *,** Comoros (2014): n.a.
A130: =A19 -> 11 | B130: =(CONCATENATE(B19,": ",'26. Source - CEQ MWBs'!C22)) -> Costa Rica (2010): Sauma, Pablo and Juan Diego Trejos. 2014. “CEQ Master Workbook: Costa Rica (2010),” CEQ Data Center on Fiscal Redistribution (CEQ Institute, Tulane University). February 14, 2014.
... A147: =A36 -> 28 | B147: =(CONCATENATE(B36,": ",'26. Source - CEQ MWBs'!C39)) -> Mexico (2010): Scott, John. 2013. “CEQ Master Workbook: Mexico (2010),” CEQ Data Center on Fiscal Redistribution (CEQ Institute, Tulane University). September 2, 2013.
B148: =(CONCATENATE(B37,": ",'26. Source - CEQ MWBs'!C40)) -> Mexico (2012): Scott, John, Sandra Martinez-Aguilar, Enrique de la Rosa, and Rodrigo Aranda. 2017. “CEQ Master Workbook: Mexico (2012),” CEQ Data Center on Fiscal Redistribution (CEQ Institute, Tulane University). June 15, 2019
B149: =(CONCATENATE(B38,": ",'26. Source - CEQ MWBs'!C41)) -> Mexico (2014): Scott, John, Sandra Martinez-Aguilar, Enrique de la Rosa, and Rodrigo Aranda. 2017. “CEQ Master Workbook: Mexico (2014),” CEQ Data Center on Fiscal Redistribution (CEQ Institute, Tulane University). June 15, 2019.
A150: =A39 -> 29 | B150: =(CONCATENATE(B39,": ",'26. Source - CEQ MWBs'!C42)) -> *,** Mongolia (2016): n.a.
A151: =A40 -> 30 | B151: =(CONCATENATE(B40,": ",'26. Source - CEQ MWBs'!C43)) -> *,** Namibia (2009): n.a.
A152: =A41 -> 31 | B152: =(CONCATENATE(B41,": ",'26. Source - CEQ MWBs'!C44)) -> Nicaragua (2009): Cabrera, Maynor and Hilcias E. Moran. 2015. “CEQ Master Workbook: Nicaragua (2009),” CEQ Data Center on Fiscal Redistribution (CEQ Institute, Tulane University, Instituto Centroamericano de Estudios Fiscales (Icefi) and International Fund for Agricultural Development (IFAD)). October 14, 2015.
A153: =A42 -> 32 | B153: =(CONCATENATE(B42,": ",'26. Source - CEQ MWBs'!C45)) -> *,** Niger (2014): n.a.
A154: =A43 -> 33 | B154: =(CONCATENATE(B43,": ",'26. Source - CEQ MWBs'!C46)) -> Panama (2016): Martinez-Aguilar, Sandra. 2019. “CEQ Master Workbook: Panama (2016),” CEQ Data Center on Fiscal Redistribution (CEQ Institute, Tulane University and the Economic Co-operation and Development). January 16, 2019.
A155: =A44 -> 34 | B155: =(CONCATENATE(B44,": ",'26. Source - CEQ MWBs'!C47)) -> Paraguay (2014) : Gimenez, Lea, Maria Ana Lugo, Sandra Martinez-Aguilar, Humberto Colman, Juan Jose Galeano and Gabriela Farfan. 2017. “CEQ Master Workbook: Paraguay (2014) ,” CEQ Data Center (CEQ Institute, Tulane University). February 12, 2017.
A156: =A45 -> 35 | B156: =(CONCATENATE(B45,": ",'26. Source - CEQ MWBs'!C48)) -> Peru (2009): Jaramillo, Miguel. 2015. “CEQ Master Workbook: Peru (2009),” CEQ Data Center on Fiscal Redistribution (CEQ Institute, Tulane University). August 7, 2015.
B157: =(CONCATENATE(B46,": ",'26. Source - CEQ MWBs'!C49)) -> Peru (2011): Jaramillo, Miguel. 2019. “CEQ Master Workbook: Peru (2011),” CEQ Data Center on Fiscal Redistribution (CEQ Institute, Tulane University). February 11, 2019.
A158: =A47 -> 36 | B158: =(CONCATENATE(B47,": ",'26. Source - CEQ MWBs'!C50)) -> *,** Poland (2014): n.a.
A159: =A48 -> 37 | B159: =(CONCATENATE(B48,": ",'26. Source - CEQ MWBs'!C51)) -> *,** Romania (2016): n.a.
A160: =A49 -> 38 | B160: =(CONCATENATE(B49,": ",'26. Source - CEQ MWBs'!C52)) -> Russia (2010): Popova, Daria. 2019. “CEQ Master Workbook: Russia (2010),” CEQ Data Center on Fiscal Redistribution (CEQ Institute, Tulane University and the World Bank). March 21, 2019.
...

Sheet 4.Taxes and transfers- ShareGDP
A1: Go to Contents
B3: Taxes and transfers as a share of GDP
B4: NOTE: FOR SOURCES AND CITATIONS SEE BOTTOM OF PAGE
B6: Country | C6: Year of survey | D6: Year of budgetary data and fiscal system | F6: Population | G6: GDP (current LCU) | I6: Revenues as a share of GDP | AA6: Spending as a share of GDP
I7: Total revenues | J7: Taxes | AA7: Total spending | AB7: Primary spending | AC7: Social spending | AI7: Social insurance | AK7: Non social spending
J8: Total taxes | K8: Total tax burden on households *** | L8: Direct taxes | Q8: Indirect taxes | V8: Other taxes | X8: Social security contributions | Y8: Other revenues | AC8: Total social spending | AD8: Direct transfers | AE8: Education | AF8: Health | AG8: Other | AI8: Contributory pensions | AK8: Subsidies | AM8: Social spending plus contributory pensions | AN8: Social spending plus subsidies | AO8: Social spending plus contributory pensions plus subsidies
L9: Total direct taxes | M9: Personal and payroll taxes | N9: Corporate taxes | O9: Other direct taxes | Q9: Total indirect taxes | R9: VAT | S9: Excises | T9: Other indirect taxes
A10: =A9+1 -> 1 | B10: *,** Albania (2015) | C10: 2015 | D10: 2015 | F10: 2880703 | G10: 1434307000000 | I10: 0.276 | J10: 0.247 | K10: =M10+R10+S10+X10 -> 0.144 | L10: =SUM(M10:O10) -> 0.042 | M10: 0.022 | N10: 0.017 | O10: 0.003 | Q10: =SUM(R10:T10) -> 0.126 | R10: 0.091 | S10: 0.031 | T10: 0.004 | V10: 0.079 | Y10: 0.029 | AA10: 0.3279 | AC10: 0.0912 | AE10: 0.028 | AF10: 0.0284 | AG10: 0.035 | AM10: 0.0912 | AN10: 0.0912 | AO10: 0.0912
A11: =A10+1 -> 2 | B11: Argentina (2012) | C11: 2012-13 | D11: 2012 | F11: 36138213 | G11: 2.6379138e+12 | I11: 0.33183965 | J11: 0.23902206 | K11: 0.19606944 | L11: 0.083566774 | M11: 0.020575947 | N11: 0.030511307 | O11: 0.03247952 | Q11: 0.15274806 | R11: 0.072214807 | S11: 0.015466867 | T11: 0.065066382 | V11: 0.002707233 | X11: 0.087811817 | Y11: 0.0050057738 | AA11: 0.44137635 | AB11: 0.42086625 | AC11: 0.20900823 | AD11: 0.057963499 | AE11: 0.074759746 | AF11: 0.05648677 | AG11: 0.019798213 | AI11: 0.071007071 | AK11: 0.059338458 | AM11: 0.2800153 | AN11: 0.26834669 | AO11: 0.33935376
A12: =A11+1 -> 3 | B12: Armenia (2011) | C12: 2011 | D12: 2011 | F12: 2965466.5 | G12: 3777945600000 | I12: 0.23983188 | J12: 0.17147102 | K12: 0.15154995 | L12: 0.051675043 | M12: 0.021495969 | N12: 0.025898282 | O12: 0.0042807922 | Q12: 0.11570275 | R12: 0.086947467 | S12: 0.010430135 | T12: 0.018325145 | V12: 0.0040932299 | X12: 0.032676384 | Y12: 0.035684474 | AA12: 0.26826747 | AB12: 0.25886082 | AC12: 0.077759821 | AD12: 0.025206301 | AE12: 0.035747613 | AF12: 0.016805907 | AI12: 0.042096953 | AM12: 0.11985677 | AN12: 0.077759821 | AO12: 0.11985677
A13: =A12+1 -> 4 | B13: *,** Belarus (2015) | C13: 2015 | D13: 2016 | F13: 9489616 | G13: 89909810000 | I13: 0.433 | J13: 0.368 | K13: =M13+R13+S13+X13 -> 0.261 | L13: 0.084 | M13: 0.043 | N13: 0.027 | O13: 0.014 | Q13: 0.171 | R13: 0.084 | S13: 0.022 | T13: 0.065 | V13: 0.001 | X13: 0.112 | Y13: 0.065 | AA13: 0.41 | AE13: 0.048 | AF13: 0.045 | AI13: 0.096 | AK13: 0.03
A14: =A13+1 -> 5 | B14: Bolivia (2009) | C14: 2009 | D14: 2009 | F14: 10232625 | G14: 1.2172675e+11 | I14: 0.31495206 | J14: 0.26795206 | K14: 0.11333558 | L14: 0.056528133 | M14: 0.00236595 | N14: 0.044558726 | O14: 0.0096034569 | Q14: 0.11096963 | V14: 0.1004543 | Y14: 0.047 | AA14: 0.34836223 | AB14: 0.333 | AC14: 0.14691085 | AD14: 0.020460335 | AE14: 0.082706475 | AF14: 0.036005303 | AG14: 0.0077387386 | AI14: 0.035431819 | AK14: 0.006 | AM14: 0.18234267 | AN14: 0.15291085 | AO14: 0.18834267
A15: =A14+1 -> 6 | B15: Brazil (2008) | C15: 2008-09 | D15: 2009 | F15: 1.905193e+08 | G15: 3333039000000 | I15: 0.36886192 | J15: 0.23974637 | K15: 0.18403052 | L15: 0.094748356 | M15: 0.020131776 | N15: 0.037383297 | O15: 0.037233284 | Q15: 0.14499801 | R15: 0.073231683 | S15: 0.0062696169 | T15: 0.065496712 | X15: 0.084397443 | Y15: 0.044718107 | AA15: 0.48899915 | AB15: 0.39548573 | AC15: 0.16629822 | AD15: 0.05397476 | AE15: 0.050764477 | AF15: 0.049808056 | AG15: 0.011750924 | AI15: 0.086588521 | AM15: 0.25288674 | AN15: 0.16629822 | AO15: 0.25288674
A16: =A15+1 -> 7 | B16: *,** Burkina Faso (2014) | C16: 2014 | D16: 2014 | F16: 17586017 | G16: 6119568000000 | I16: 0.21588779 | J16: 0.15371673 | K16: 0.084486356 | L16: 0.04412403 | M16: 0.0012108698 | N16: 0.042914794 | Q16: 0.10676407 | R16: 0.063221783 | S16: 0.020055337 | T16: 0.023488586 | V16: 0.002828631 | Y16: 0.062171055 | AA16: 0.26815128 | AC16: 0.074 | AD16: 0.006 | AE16: 0.033708262 | AF16: 0.015327879 | AI16: 0.0083 | AK16: 0.010409232 | AM16: 0.0823 | AN16: 0.084409232 | AO16: 0.092709232
A17: =A16+1 -> 8 | B17: Chile (2013) | C17: 2013 | D17: 2013 | F17: 17256219 | G17: 137212064000000 | I17: 0.21034972 | J17: 0.16748223 | K17: 0.12347426 | L17: 0.066221678 | M17: 0.013207501 | N17: 0.036917096 | O17: 0.016097081 | Q17: 0.09812806 | R17: 0.079452679 | S17: 0.016464227 | T17: 0.0022111543 | V17: 0.0031324968 | X17: 0.014349852 | Y17: 0.028517638 | AA17: 0.21648451 | AB17: 0.21065616 | AC17: 0.1106064 | AD17: 0.016424406 | AE17: 0.042867771 | AF17: 0.038077731 | AG17: 0.013240527 | AI17: 0.029256727 | AK17: 0.0048933879 | AM17: 0.13986716 | AN17: 0.11549979 | AO17: 0.14475652
A18: =A17+1 -> 9 | B18: Colombia (2010) | C18: 2010 | D18: 2010 | F18: 45062798 | G18: 544924000000000 | I18: 0.16965836 | J18: 0.13362241 | K18: 0.07529767 | L18: 0.063456993 | M18: 0.0013613385 | N18: 0.014312979 | O18: 0.047782676 | Q18: 0.069933091 | R18: 0.052872844 | T18: 0.017060248 | V18: 0.00023233041 | X18: 0.021063488 | Y18: 0.014972462 | AA18: 0.17196597 | AB18: 0.14588398 | AC18: 0.088423655 | AD18: 0.0049552121 | AE18: 0.032952355 | AF18: 0.049756533 | AG18: 0.00075955546 | AI18: 0.031398874 | AK18: 0.0053972115 | AM18: 0.11982253 | AN18: 0.093820867 | AO18: 0.12521974
B19: Colombia (2014) | C19: 2014 | D19: 2014 | F19: 47203862 | G19: 756152000000000 | I19: 0.20776858 | J19: 0.15905738 | K19: 0.087992527 | L19: 0.087552398 | M19: 0.011259451 | N19: 0.053164876 | O19: 0.023128071 | Q19: 0.07116018 | R19: 0.051246137 | T19: 0.019914043 | V19: 0.00034480014 | X19: 0.025486939 | Y19: 0.023224265 | AA19: 0.1919356 | AB19: 0.17131307 | AC19: 0.092717176 | AD19: 0.0058538098 | AE19: 0.030500739 | AF19: 0.0535464 | AG19: 0.0028162274 | AI19: 0.03632984 | AK19: 0.0046313229 | AM19: 0.12904702 | AN19: 0.097348499 | AO19: 0.13367834
A20: =A18+1 -> 10 | B20: *,** Comoros (2014) | C20: 2014 | F20: 747155 | G20: 425713000000
A21: =A20+1 -> 11 | B21: Costa Rica (2010) | C21: 2010 | D21: 2010 | F21: 4551553 | G21: 19086721000000 | I21: 0.23368647 | J21: 0.14046305 | K21: 0.15769792 | L21: 0.048158545 | M21: 0.010627735 | N21: 0.023574219 | O21: 0.013956591 | Q21: 0.092304502 | R21: 0.075212501 | T21: 0.017092 | X21: 0.07185768 | Y21: 0.021365742 | AA21: 0.27765008 | AB21: 0.25634264 | AC21: 0.16037463 | AD21: 0.011797009 | AE21: 0.065894428 | AF21: 0.062137089 | AG21: 0.020546107 | AI21: 0.04387608 | AM21: 0.20425071 | AN21: 0.16037463 | AO21: 0.20425071
A22: =A21+1 -> 12 | B22: *,** Croatia (2014) | C22: 2014 | D22: 2014 | F22: 4238389 | G22: 3.3156965e+11 | I22: 0.427 | J22: 0.249 | K22: 0.324 | L22: 0.054 | M22: 0.036 | N22: 0.017 | Q22: 0.17 | R22: 0.125 | S22: 0.036 | T22: 0.009 | V22: 0.025 | X22: 0.127 | Y22: 0.051 | AA22: 0.481 | AC22: =SUM(AD22:AG22) -> 0.173 | AD22: 0.029 | AE22: 0.043 | AF22: 0.056 | AG22: 0.045 | AI22: 0.11 | AM22: 0.283 | AN22: =AC22+AK22 -> 0.173 | AO22: =AM22+AK22 -> 0.283
A23: =A22+1 -> 13 | B23: Dominican Republic (2006) | C23: 2006-07 | D23: 2013 | F23: 9234446 | G23: 2590678302100 | I23: 0.14480645 | J23: 0.13655464 | K23: 0.082500844 | L23: 0.050502142 | M23: 0.012832755 | N23: 0.022528919 | O23: 0.015140469 | Q23: 0.086052497 | R23: 0.043745878 | S23: 0.025322957 | T23: 0.016983662 | X23: 0.00059925356 | Y23: 0.0076525532 | AA23: 0.1706616 | AB23: 0.15098328 | AC23: 0.079413113 | AD23: 0.0079258299 | AE23: 0.037122297 | AF23: 0.018129651 | AG23: 0.016235336 | AI23: 0.0083618282 | AK23: 0.013295175 | AM23: 0.087774942 | AN23: 0.092708288 | AO23: 0.10107012
A24: =A23+1 -> 14 | B24: Ecuador (2011) | C24: 2011-12 | D24: 2011 | F24: 15223535 | G24: 79276664000 | I24: 0.25446898 | J24: 0.12399653 | K24: 0.11397067 | L24: 0.048896526 | M24: 0.0037982127 | N24: 0.034183914 | O24: 0.010914399 | Q24: 0.0751 | R24: 0.0527 | S24: 0.0077 | T24: 0.0147 | X24: 0.049772455 | Y24: 0.0807 | AA24: 0.2311 | AB24: 0.22263474 | AC24: 0.092582468 | AD24: 0.012237798 | AE24: 0.045 | AF24: 0.032786788 | AG24: 0.0025578826 | AI24: 0.031087962 | AK24: 0.03983085 | AM24: 0.12367043 | AN24: 0.13241332 | AO24: 0.16350128
A25: =A24+1 -> 15 | B25: *,** Egypt (2015) | C25: 2015 | D25: 2015 | F25: 92442547 | G25: 2443900000000 | I25: 0.19 | J25: 0.125 | K25: =M25+R25+S25+X25 -> 0.06 | L25: 0.062 | M25: 0.016 | N25: 0.037 | O25: 0.009 | Q25: 0.063 | R25: 0.027 | S25: 0.017 | T25: 0.02 | Y25: 0.065 | AA25: 0.3 | AC25: 0.0751 | AD25: 0.0221 | AE25: 0.038 | AF25: 0.015 | AI25: 0.014 | AK25: 0.041 | AM25: =AC25+AI25 -> 0.0891 | AN25: =AC25+AK25 -> 0.1161 | AO25: =AM25+AK25 -> 0.1301
A26: =A25+1 -> 16 | B26: El Salvador (2011) | C26: 2011 | D26: 2011 | F26: 6209818 | G26: 20283780000 | I26: =J26+X26+Y26 -> 0.20805673 | J26: =L26+Q26+V26 -> 0.15810549 | K26: =M26+R26+S26 -> 0.11795484 | L26: =SUM(M26:O26) -> 0.056357691 | M26: 0.024469798 | N26: 0.031084295 | O26: 0.00080359775 | Q26: =SUM(R26:T26) -> 0.1017478 | R26: 0.077605358 | S26: 0.015879683 | T26: 0.0082627597 | X26: 0.01899005 | Y26: =2.04187779595322%+1.05424136921225% -> 0.030961192 | AA26: 0.25275466 | AB26: 0.22722244 | AC26: =SUM(AD26:AF26) -> 0.090136594 | AD26: 0.0078379013 | AE26: 0.033407411 | AF26: 0.048891282 | AI26: 0.01999578 | AK26: 0.020877371 | AM26: =AC26+AI26 -> 0.11013237 | AN26: =AC26+AK26 -> 0.11101396 | AO26: =AM26+AK26 -> 0.13100974
A27: =A26+1 -> 17 | B27: Ethiopia (2010) | C27: 2010-11 | D27: 2011 | F27: 76073949 | G27: 505646000000 | I27: 0.16932157 | J27: 0.1166554 | K27: 0.089322684 | L27: 0.038671459 | M27: 0.011338741 | N27: 0.019885857 | O27: 0.0074468603 | Q27: 0.077983943 | R27: 0.030206104 | S27: 0.047777839 | Y27: 0.052666166 | AA27: 0.18556739 | AB27: 0.18178411 | AC27: 0.079777884 | AD27: 0.013454729 | AE27: 0.046168663 | AF27: 0.012473056 | AG27: 0.0076814358 | AI27: 0.0047464036 | AK27: 0.0054247438 | AM27: 0.084524288 | AN27: 0.085202628 | AO27: 0.089949032
A28: =A27+1 -> 18 | B28: Georgia (2013) | C28: 2013 | D28: 2013 | F28: 3675078 | G28: 2.6847354e+10 | I28: 0.27691958 | J28: 0.24805268 | K28: 0.2050299 | L28: 0.11069304 | M28: 0.072049661 | N28: 0.030041892 | O28: 0.0086014876 | Q28: 0.13630925 | R28: 0.10607628 | S28: 0.026903955 | T28: 0.0033290175 | V28: 0.0010503828 | Y28: 0.028866904 | AA28: 0.28809073 | AB28: 0.27913642 | AC28: 0.12170954 | AD28: 0.061067293 | AE28: 0.027956584 | AF28: 0.018260767 | AG28: 0.014424894 | AK28: 0.020396911 | AM28: 0.12170954 | AN28: 0.14210645 | AO28: 0.14210645
A29: =A28+1 -> 19 | B29: Ghana (2012) | C29: 2012-13 | D29: 2013 | F29: 26347424 | G29: 93415886300 | I29: 0.20863963 | J29: 0.14572741 | K29: 0.081423958 | L29: 0.067451054 | M29: 0.027286579 | N29: 0.029266971 | O29: 0.010897504 | Q29: 0.07827636 | R29: 0.035508553 | S29: 0.0092942244 | T29: 0.033473582 | X29: 0.0093346007 | Y29: 0.053577611 | AA29: 0.286 | AB29: 0.23905998 | AC29: 0.074538173 | AD29: 0.00074933721 | AE29: 0.056542845 | AF29: 0.016645991 | AG29: 0.0006 | AI29: 0.013209745 | AK29: 0.0132 | AM29: 0.087747918 | AN29: 0.087738173 | AO29: 0.10094792
A30: =A29+1 -> 20 | B30: Guatemala (2011) | C30: 2011 | D30: 2011 | F30: 14636886 | G30: 371278000000 | I30: 0.12854547 | J30: 0.10852295 | K30: 0.074114754 | L30: 0.034234414 | M30: 0.0039395163 | N30: 0.023164909 | O30: 0.0071299886 | Q30: 0.074288539 | R30: 0.052446415 | S30: 0.0021089319 | T30: 0.019733192 | X30: 0.015619891 | Y30: 0.0044026309 | AA30: 0.16257745 | AB30: 0.14782921 | AC30: 0.068681462 | AD30: 0.0040469002 | AE30: 0.027104971 | AF30: 0.021374604 | AG30: 0.016154987 | AI30: 0.0029679892 | AK30: 0.003885091 | AM30: 0.071649452 | AN30: 0.072566553 | AO30: 0.075534543
A31: =A30+1 -> 21 | B31: *,** Guinea (2012) | C31: 2012 | D31: 2016 | F31: 10652029 | G31: 5.3358078e+13 | I31: 0.178 | J31: 0.17 | L31: 0.027 | Q31: 0.112 | R31: 0.076 | T31: 0.036 | V31: 0.031 | Y31: 0.008
A32: =A31+1 -> 22 | B32: Honduras (2011) | C32: 2011 | D32: 2011 | F32: 8171770 | G32: 335027800000 | I32: 0.14988099 | J32: 0.14723883 | K32: 0.063854999 | L32: 0.051541693 | M32: 0.00097126268 | N32: 0.0076363812 | O32: 0.042934049 | Q32: 0.095697133 | R32: 0.056543666 | S32: 0.0057359419 | T32: 0.033417525 | X32: 0.00060412897 | Y32: 0.0020380398 | AA32: 0.216 | AB32: 0.202 | AC32: 0.10018874 | AD32: 0.0039602684 | AE32: 0.060844413 | AF32: 0.03533093 | AG32: 5.3129919e-05 | AI32: 0.00060412897 | AK32: 0.0038784841 | AM32: 0.10079287 | AN32: 0.10406723 | AO32: 0.10467135
A33: =A32+1 -> 23 | B33: Indonesia (2012) | C33: 2012 | D33: 2012 | F33: 245265690 | G33: 8.2418643e+15 | I33: 0.16237989 | J33: 0.11896738 | K33: 0.065274244 | L33: 0.059942386 | M33: 0.011896697 | N33: 0.044530949 | O33: 0.00351474 | Q33: 0.058514188 | R33: 0.040959665 | S33: 0.011529794 | T33: 0.0060247291 | V33: 0.00051080676 | X33: 0.00088808766 | Y33: 0.04252442 | AA33: 0.17471775 | AB33: 0.162 | AC33: 0.048579322 | AD33: 0.0038806972 | AE33: 0.033997163 | AF33: 0.0088450862 | AG33: 0.0018563761 | AI33: 0.0075851552 | AK33: 0.040774755 | AM33: 0.056164477 | AN33: 0.089354077 | AO33: 0.096939233
A34: =A33+1 -> 24 | B34: Iran (2011) | C34: 2011-12 | D34: 2011-12 | F34: 79511694 | G34: 6.2457657e+15 | I34: 0.27040783 | J34: 0.065407834 | K34: 0.01518946 | L34: 0.038609378 | M34: 0.0085370579 | N34: 0.027874842 | O34: 0.0021974784 | Q34: 0.026798456 | R34: 0.0066323883 | S34: 2.0013559e-05 | T34: 0.020146054 | Y34: 0.205 | AA34: 0.27 | AB34: 0.26867645 | AC34: 0.1154 | AD34: 0.0399 | AE34: 0.0448 | AF34: 0.025 | AG34: 0.0057 | AI34: 0.0216 | AM34: 0.137 | AN34: 0.1154 | AO34: 0.137
A35: =A34+1 -> 25 | B35: Jordan (2010) | C35: 2010-11 | D35: 2010 | F35: 5961481.8 | G35: 1.8762019e+10 | I35: 0.24796382 | J35: 0.15748849 | K35: 0.1151423 | L35: 0.03329066 | M35: 0.0081174631 | N35: 0.025173197 | Q35: 0.10592154 | R35: 0.10592154 | V35: 0.018276284 | X35: 0.0011032928 | Y35: 0.08937204 | AA35: 0.30423164 | AB35: 0.283 | AC35: 0.091066264 | AD35: 0.0072486867 | AE35: 0.031833194 | AF35: 0.030977476 | AG35: 0.021006907 | AI35: 0.039707879 | AK35: 0.010190801 | AM35: 0.13077414 | AN35: 0.10125706 | AO35: 0.14096494
A36: =A35+1 -> 26 | B36: *,** Kenya (2015) | C36: 2015-16 | D36: 2015-16 | F36: 48465011 | G36: 6653574007897 | J36: 0.17 | K36: 0.107 | L36: 0.086 | M36: 0.043 | N36: 0.042 | O36: 0.001 | Q36: 0.084 | R36: 0.043 | S36: 0.021 | T36: 0.02 | AE36: 0.176 | AF36: 0.019
A37: =A36+1 -> 27 | B37: *,** Mali (2014) | C37: 2014 | D37: 2014 | F37: 16934220 | G37: 7092793041100 | I37: 0.171 | J37: 0.126 | AA37: 0.211 | AF37: 0.012 | AK37: 0.012
A38: =A37+1 -> 28 | B38: Mexico (2010) | C38: 2010 | D38: 2010 | F38: 112600583 | G38: 13075798000000 | I38: 0.1694897 | J38: 0.098499272 | K38: 0.087555216 | L38: 0.05084564 | M38: 0.02227552 | N38: 0.02857012 | Q38: 0.044114984 | R38: 0.037744652 | S38: 0.0045350441 | T38: 0.0018352878 | V38: 0.0035386477 | X38: 0.023 | Y38: 0.047990423 | AC38: 0.098174209 | AD38: 0.009645581 | AE38: 0.045435319 | AF38: 0.030575475 | AG38: 0.012517834 | AI38: 0.0258 | AK38: 0.014 | AM38: 0.12397421 | AN38: 0.11217421 | AO38: 0.13797421
B39: Mexico (2012) | C39: 2012 | D39: 2012 | F39: 117284429 | G39: 15626906634000 | I39: 0.17671517 | J39: 0.095937962 | K39: 0.087538612 | L39: 0.050822381 | M39: 0.023852625 | N39: 0.026969755 | Q39: 0.043043175 | R39: 0.036666862 | S39: 0.0046120892 | T39: 0.0017642236 | V39: 0.0020724053 | X39: 0.022407035 | Y39: 0.058370172 | AA39: 0.18116591 | AB39: 0.16492192 | AC39: 0.087542544 | AD39: 0.009573814 | AE39: 0.045266749 | AF39: 0.032701981 | AI39: 0.021376147 | AK39: 0.019315175 | AM39: 0.10891869 | AN39: 0.10709361 | AO39: 0.12846976
B40: Mexico (2014) | C40: 2014 | D40: 2014 | F40: 119906312 | G40: 17259799421000 | I40: 0.17258429 | J40: 0.10420764 | K40: 0.096092994 | L40: 0.054937399 | M40: 0.027077347 | N40: 0.027860052 | Q40: 0.047248833 | R40: 0.038181397 | S40: 0.0071255377 | T40: 0.0019418975 | V40: 0.00202141 | X40: 0.023708712 | Y40: 0.044667937 | AA40: 0.1931913 | AB40: 0.17648707 | AC40: 0.08846437 | AD40: 0.0097817568 | AE40: 0.047786005 | AF40: 0.030896609 | AI40: 0.023734616 | AK40: 0.0068935177 | AM40: 0.11219899 | AN40: 0.095357888 | AO40: 0.1190925
A41: =A38+1 -> 29 | B41: *,** Mongolia (2016) | C41: 2016 | D41: 2016 | F41: 3056359 | G41: 2.3942866e+13 | I41: =J41+X41 -> 0.243 | J41: 0.194 | K41: =M41+R41+S41 -> 0.097 | L41: 0.046 | M41: 0.023 | N41: 0.021 | O41: 0.004 | Q41: 0.088 | R41: 0.048 | S41: 0.026 | T41: 0.014 | V41: 0.06 | X41: 0.049 | AC41: =SUM(AD41:AF41) -> 0.173 | AD41: 0.089 | AE41: 0.056 | AF41: 0.028 | AM41: =AC41+AI41 -> 0.173 | AN41: =AC41+AK41 -> 0.173 | AO41: =AM41+AK41 -> 0.173
A42: =A41+1 -> 30 | B42: *,** Namibia (2009) | C42: 2009 | D42: 2009 -10 | F42: 2118874 | G42: 8.2599189e+10 | I42: 0.32 | J42: 0.295 | K42: =M42+R42+S42 -> 0.134 | L42: 0.112 | M42: 0.068 | N42: 0.038 | O42: 0.006 | Q42: 0.067 | R42: 0.066 | T42: 0.001 | V42: 0.116 | Y42: 0.025 | AA42: 0.147 | AB42: 0.147 | AC42: =SUM(AD42:AG42) -> 0.127 | AD42: 0.016 | AE42: 0.075 | AF42: 0.033 | AG42: 0.003 | AK42: 0.006 | AM42: =AC42+AI42 -> 0.127 | AN42: =AC42+AK42 -> 0.133 | AO42: =AM42+AK42 -> 0.133
A43: =A42+1 -> 31 | B43: Nicaragua (2009) | C43: 2009 | D43: 2009 | F43: 5765733 | G43: 1.9088798e+11 | I43: 0.23093917 | J43: 0.14220018 | K43: 0.13643099 | L43: 0.044428151 | M43: 0.010786457 | N43: 0.032960143 | O43: 0.00068155155 | Q43: 0.089607135 | R43: 0.054233462 | S43: 0.029029114 | T43: 0.0063445587 | V43: 0.0081648933 | X43: 0.042381962 | Y43: 0.046357031 | AA43: 0.27066508 | AB43: 0.2368709 | AC43: 0.080653669 | AD43: 0.00069784907 | AE43: 0.038019183 | AF43: 0.041936637 | AI43: 0.018805969 | AK43: 0.0036304014 | AM43: 0.099459638 | AN43: 0.08428407 | AO43: 0.10309004
A44: =A43+1 -> 32 | B44: *,** Niger (2014) | C44: 2014 -15 | D44: 2014 | F44: 17114761 | G44: 3024277000000 | I44: 0.23 | J44: 0.156 | AA44: 0.3336 | AC44: =SUM(AD44:AG44) -> 0.089 | AD44: 0.0031 | AE44: 0.0684 | AF44: 0.0175 | AM44: =AC44+AI44 -> 0.089 | AN44: =AC44+AK44 -> 0.089 | AO44: =AM44+AK44 -> 0.089
A45: =A44+1 -> 33 | B45: Panama (2016) | C45: 2016 | D45: 2015 | F45: 3941606 | G45: 55187800000 | I45: 0.19235951 | J45: 0.096831768 | K45: 0.090056537 | L45: 0.050898551 | M45: 0.00046263548 | N45: 0.019031181 | O45: 0.031404734 | Q45: 0.045933218 | R45: 0.026106477 | S45: 0.0048408102 | T45: 0.014985931 | X45: 0.058646614 | Y45: 0.036881128 | AA45: 0.21964549 | AB45: 0.15456176 | AC45: 0.13161514 | AD45: 0.0058024002 | AE45: 0.030414711 | AF45: 0.047699015 | AI45: 0.022901038 | AK45: 0.0040556269 | AM45: 0.15451618 | AN45: 0.13567077 | AO45: 0.15857181
A46: =A45+1 -> 34 | B46: Paraguay (2014) | C46: 2014 | D46: 2014 | F46: 6780504 | G46: 138259884742000 | I46: 0.17898943 | J46: 0.12683655 | K46: 0.1032979 | L46: 0.027 | M46: 0.001 | N46: 0.024 | O46: 0.002 | Q46: 0.098499538 | R46: 0.067503488 | S46: 0.018065999 | T46: 0.012930051 | V46: 0.0013370129 | X46: 0.01672841 | Y46: 0.035424469 | AA46: 0.21512158 | AB46: 0.20219841 | AC46: 0.12660762 | AD46: 0.009678988 | AE46: 0.040420798 | AF46: 0.025406609 | AG46: 0.051101227 | AI46: 0.016594876 | AK46: 0.0026185092 | AM46: 0.1432025 | AN46: 0.12922613 | AO46: 0.14582101
A47: =A46+1 -> 35 | B47: Peru (2009) | C47: 2009 | D47: 2009 | F47: 29553339 | G47: 392565000000 | I47: 0.1917 | J47: 0.141 | K47: 0.102 | L47: 0.050235898 | M47: 0.015 | N47: 0.028943946 | O47: 0.0062919517 | Q47: 0.075563704 | R47: 0.068 | T47: 0.0075637045 | V47: 0.015200398 | X47: 0.019 | Y47: 0.0317 | AA47: 0.2151 | AB47: 0.2016
B48: Peru (2011) | C48: 2011 | D48: 2011 | F48: 29700727 | G48: 473049000000 | I48: 0.21669495 | J48: 0.16345945 | K48: 0.12992832 | L48: 0.065114073 | M48: 0.01551848 | N48: 0.049595593 | Q48: 0.098345379 | R48: 0.085453938 | S48: 0.0099741955 | T48: 0.0029172454 | X48: 0.018981704 | Y48: 0.034253796 | AA48: 0.19180777 | AB48: 0.18052564 | AC48: 0.06484579 | AD48: 0.0058767696 | AE48: 0.026389098 | AF48: 0.031205857 | AG48: 0.0013740648 | AI48: 0.010394272 | AM48: 0.075240062 | AN48: 0.06484579 | AO48: 0.075240062
A49: =A47+1 -> 36 | B49: *,** Poland (2014) | C49: 2014 | D49: 2014 | F49: 38011735 | G49: 1720430000000 | I49: 0.387 | J49: 0.197 | K49: 0.286 | L49: 0.063 | M49: 0.046 | N49: 0.017 | Q49: 0.108 | R49: 0.072 | S49: 0.036 | V49: 0.026 | X49: 0.132 | Y49: 0.058 | AA49: 0.421 | AC49: 0.174 | AD49: 0.009 | AE49: 0.053 | AF49: 0.046 | AG49: 0.066 | AI49: 0.087 | AM49: 0.261 | AN49: =AC49+AK49 -> 0.174 | AO49: =AM49+AK49 -> 0.261
A50: =A49+1 -> 37 | B50: *,** Romania (2016) | C50: 2016 | D50: 2016 | F50: 19702332 | G50: 765135400000 | I50: 0.293 | J50: 0.18 | M50: 0.036 | N50: 0.02 | R50: 0.068 | S50: 0.035 | V50: 0.019 | X50: 0.08 | Y50: 0.034 | AA50: 0.317 | AE50: 0.028 | AF50: 0.04 | AG50: 0.016 | AI50: 0.078 | AK50: 0.009
A51: =A50+1 -> 38 | B51: Russia (2010) | C51: 2010 | D51: 2010 | F51: 1.3584556e+08 | G51: 46308500000000 | I51: 0.34568448 | J51: 0.20998704 | K51: 0.1557695 | L51: 0.090550743 | M51: 0.038664565 | N51: 0.038320634 | O51: 0.013565544 | Q51: 0.076814943 | R51: 0.053948278 | S51: 0.01017995 | T51: 0.012686715 | V51: 0.042621358 | X51: 0.052976711 | Y51: 0.082720727 | AA51: 0.38041948 | AB51: 0.37478974 | AC51: 0.15370587 | AD51: 0.052772685 | AE51: 0.040896592 | AF51: 0.036900453 | AG51: 0.023136141 | AI51: 0.082480374 | AM51: 0.23618625 | AN51: 0.15370587 | AO51: 0.23618625
A52: =A51+1 -> 39 | B52: South Africa (2010) | C52: 2010-11 | D52: 2010 | F52: 50423022 | G52: 2659366000000 | I52: 0.30688022 | J52: 0.2645707 | K52: 0.16725813 | L52: 0.14954537 | M52: 0.085330498 | N52: 0.056434454 | O52: 0.007780418 | Q52: 0.10395993 | R52: 0.069028272 | S52: 0.0086364998 | T52: 0.026295159 | V52: 0.011065397 | X52: 0.0042628581 | Y52: 0.038046662 | AA52: 0.34775731 | AB52: 0.32287528 | AC52: 0.17568085 | AD52: 0.038075731 | AE52: 0.069996083 | AF52: 0.041139551 | AG52: 0.026469483 | AI52: 0.009698257 | AM52: 0.18537911 | AN52: 0.17568085 | AO52: 0.18537911
A53: =A52+1 -> 40 | B53: Sri Lanka (2009) | C53: 2009-10 | D53: 2010 | F53: 20337761 | G53: 6413668000000 | I53: 0.13006286 | J53: 0.11300055 | K53: 0.059668659 | L53: 0.021145931 | M53: 0.0033866689 | N53: 0.0089122137 | O53: 0.0088470482 | Q53: 0.054548193 | R53: 0.034300185 | S53: 0.020248008 | V53: 0.037306421 | X53: 0.0017337973 | Y53: 0.015328514 | AA53: 0.19960575 | AB53: 0.14463065 | AC53: 0.046878479 | AD53: 0.01825648 | AE53: 0.016254037 | AF53: 0.011512133 | AG53: 0.00085582852 | AI53: 0.014187669 | AK53: 0.0052885494 | AM53: 0.061066148 | AN53: 0.052167028 | AO53: 0.066354697
A54: =A53+1 -> 41 | B54: Tanzania (2011) | C54: 2011-12 | D54: 2011-12 | F54: 42270137 | G54: 41120400000000 | I54: 0.24425029 | J54: 0.16112561 | K54: 0.142803 | L54: 0.059099809 | M54: 0.027467358 | N54: 0.018280148 | O54: 0.013352302 | Q54: 0.097987856 | R54: 0.048042939 | S54: 0.034517732 | T54: 0.015427185 | V54: 0.0040379471 | X54: 0.032774973 | Y54: 0.050349705 | AA54: 0.31378012 | AB54: 0.27543419 | AC54: 0.062717629 | AD54: 0.00093238393 | AE54: 0.045989144 | AF54: 0.015640655 | AG54: 0.00015544596 | AI54: 0.023288806 | AK54: 0.011505141 | AM54: 0.086006435 | AN54: 0.07422277 | AO54: 0.097511576
A55: =A54+1 -> 42 | B55: Tunisia (2010) | C55: 2010 | D55: 2010 | F55: 9706340 | G55: 6.3440855e+10 | I55: 0.23280266 | J55: 0.20016597 | L55: 0.079329007 | M55: 0.040984631 | N55: 0.038344376 | Q55: 0.12083696 | Y55: 0.032636698 | AA55: 0.282272 | AB55: 0.224887 | AC55: 0.086961312 | AD55: 0.0082754244 | AE55: 0.062622107 | AF55: 0.015898273 | AG55: 0.00016550849 | AI55: 0.087030668 | AK55: 0.02364407 | AM55: 0.17399198 | AN55: 0.11060538 | AO55: 0.19763605
A56: =A55+1 -> 43 | B56: Uganda (2012) | C56: 2012-13 | D56: 2012-13 | F56: 32250627 | G56: 63740291673900 | I56: 0.133 | J56: 0.115 | K56: 0.081 | L56: 0.039 | M56: 0.019 | N56: 0.0106 | O56: 0.0094 | Q56: 0.076 | R56: 0.038 | S56: 0.024 | T56: 0.014 | Y56: 0.018 | AA56: 0.121 | AB56: 0.10655759 | AC56: 0.0458 | AD56: 0.0054 | AE56: 0.024 | AF56: 0.016 | AG56: 0.0004 | AK56: 0.0021 | AM56: 0.0458 | AN56: 0.0479 | AO56: 0.0479
A57: =A56+1 -> 44 | B57: *,** Ukraine (2016) | C57: 2016 | D57: 2016 | F57: 45004645 | G57: 2385367000000 | I57: 0.33 | J57: 0.27 | M57: 0.06 | R57: 0.1 | S57: 0.03 | AA57: 0.35 | AC57: =SUM(AD57:AG57) -> 0.146 | AD57: 0.06 | AE57: 0.054 | AF57: 0.032 | AI57: 0.062 | AM57: =AC57+AI57 -> 0.208 | AN57: =AC57+AK57 -> 0.146 | AO57: =AM57+AK57 -> 0.208
A58: =A57+1 -> 45 | B58: United States (2011) | C58: 2011 | D58: 2011 | F58: 311718857 | G58: 15517926000000
A59: =A58+1 -> 46 | B59: Uruguay (2009) | C59: 2009 | D59: 2009 | F59: 3010285 | G59: 714523446000 | I59: 0.27694076 | J59: 0.1836419 | K59: 0.21668127 | L59: 0.067239087 | M59: 0.022631082 | N59: 0.031480585 | O59: 0.013127419 | Q59: 0.11640282 | R59: 0.098414664 | S59: 0.017988153 | X59: 0.077647373 | Y59: 0.015651478 | AA59: 0.29704289 | AB59: 0.26926217 | AC59: 0.12476217 | AD59: 0.021811679 | AE59: 0.035642321 | AF59: 0.045089596 | AG59: 0.022218569 | AI59: 0.083504117 | AM59: 0.20826628 | AN59: 0.12476217 | AO59: 0.20826628
A60: =A59+1 -> 47 | B60: Venezuela (2013) | C60: 2013 | D60: 2013 | F60: 29790689 | G60: 2245843966000 | I60: 0.28553639 | J60: 0.13416209 | K60: 0.10169975 | L60: 0.041977289 | M60: 0.0067076679 | N60: 0.035033759 | O60: 0.00023586189 | Q60: 0.092184798 | R60: 0.073644798 | S60: 0.00862 | T60: 0.00992 | X60: 0.012727285 | Y60: 0.13864702 | AA60: 0.32188003 | AB60: 0.30428313 | AC60: 0.12603699 | AD60: 0.0096968441 | AE60: 0.047441666 | AF60: 0.027504149 | AG60: 0.041394333 | AI60: 0.03150167 | AK60: 0.046843204 | AM60: 0.15753866 | AN60: 0.1728802 | AO60: 0.20438187
C63: not applicable; means that the indicator should not be calculated due to methodological reasons or characteristics of the fiscal system.
C65: not calculated; means that the indicator was not calculated by the author/s.
C67: not available; means that the indicator was calculated but it is not publicly available, requests should be put directly to author/s.
C69: not available; means that the indicator is no published on the World Bank's report
B72: * The information published here is from World Bank led CEQ assessments and has not undergone quality control by the CEQ Institute. The information is taken from World Bank Policy Research Working Papers. See References for further detail.
B73: ** At least some information for this CEQ Assessment was extracted directly from World Bank Policy Research Working Papers, Reports, Working Papers (numbered series) and Poverty Assessment.
B75: Notes
B76: *** The total tax burden on households is the sum of individual tax burden as a share of GDP allocated to households
B77: 1. The year represented by the data in parentheses.
B78: 2. Because national and international agencies often update their data series, the information included here may be subject to change.
B79: 3. Data shown here is administrative data as reported by the studies cited and the number not necessarily coincide with the data bases in multilateral or other organizations (e.g., World Bank's WDI).
B80: 4. Other social spending includes expenditures in housing and community amenities; environmental protection; and recreation, culture and religion.
B81: 5. In Armenia, Costa Rica, Iran, Peru, South Africa and Uruguay there are no indirect subsidies.
B82: 6. Bolivia does not have personal income taxes.
B83: 7. In Iran, contributions to pensions are treated as direct taxes.
B84: 8. For Tanzania, fiscal year runs from July 2011 - June 2012.
... B102: Source: CEQ Institute’s Data Center on Fiscal Redistribution. Based on the following Master Workbooks of Results, for United States the source is the publication of Higgins, et al. (2016):
A103: =A10 -> 1 | B103: ='5.Inequality - Gini coefficient'!B101 -> *,** Albania (2015): n.a.
A104: =A11 -> 2 | B104: ='5.Inequality - Gini coefficient'!B102 -> Argentina (2012): Rossignolo, Dario. 2017. “CEQ Master Workbook: Argentina (2012-2013),” CEQ Data Center on Fiscal Redistribution (CEQ Institute, Tulane University). Jun 8, 2018.
A105: =A12 -> 3 | B105: ='5.Inequality - Gini coefficient'!B103 -> Armenia (2011): Younger, Stephen D., Artsvi Khachatryan, Gohar Gyulumyan, Nistha Sinha, and Ulrich Bartsch. 2019. “CEQ Master Workbook: Armenia (2011),” CEQ Data Center on Fiscal Redistribution (CEQ Institute, Tulane University and the World Bank). June 8, 2019.
A106: =A13 -> 4 | B106: ='5.Inequality - Gini coefficient'!B104 -> *,** Belarus (2015): n.a.
A107: =A14 -> 5 | B107: ='5.Inequality - Gini coefficient'!B105 -> Bolivia (2009): Paz Arauco, Veronica, George Gray-Molina, Wilson Jimenez and Ernesto Yañez. 2014. “CEQ Master Workbook: Bolivia (2009),” CEQ Data Center on Fiscal Redistribution (CEQ Institute, Tulane University). September 22, 2014.
A108: =A15 -> 6 | B108: ='5.Inequality - Gini coefficient'!B106 -> Brazil (2008): Higgins, Sean, Claudiney Pereira, and, Maynor Cabrera. 2019. “CEQ Master Workbook: Brazil (2008-2009),” CEQ Data Center on Fiscal Redistribution (CEQ Institute, Tulane University). May 3, 2019.
A109: =A16 -> 7 | B109: ='5.Inequality - Gini coefficient'!B107 -> *,** Burkina Faso (2014): n.a.
A110: =A17 -> 8 | B110: ='5.Inequality - Gini coefficient'!B108 -> Chile (2013): Martinez-Aguilar, Sandra and Eduardo Ortiz-Juarez. 2016. “CEQ Master Workbook: Chile (2013),” CEQ Data Center on Fiscal Redistribution (CEQ Institute, Tulane University and the World Bank). October 7, 2016.
A111: =A18 -> 9 | B111: ='5.Inequality - Gini coefficient'!B109 -> Colombia (2010): Melendez, Marcela and Valentina Martinez. 2019. “CEQ Master Workbook: Colombia (2010),” CEQ Data Center on Fiscal Redistribution (CEQ Institute, Tulane University and Inter-American Development Bank). February 20, 2019.
A112: =A19 -> 0 | B112: ='5.Inequality - Gini coefficient'!B110 -> Colombia (2014): Melendez, Marcela and Valentina Martinez. 2019. “CEQ Master Workbook: Colombia (2014),” CEQ Data Center on Fiscal Redistribution (CEQ Institute, Tulane University and Inter-American Development Bank). February 28, 2019.
A113: =A20 -> 10 | B113: ='5.Inequality - Gini coefficient'!B111 -> *,** Comoros (2014): n.a.
A114: =A21 -> 11 | B114: ='5.Inequality - Gini coefficient'!B112 -> Costa Rica (2010): Sauma, Pablo and Juan Diego Trejos. 2014. “CEQ Master Workbook: Costa Rica (2010),” CEQ Data Center on Fiscal Redistribution (CEQ Institute, Tulane University). February 14, 2014.
... A153: =A60 -> 47 | B153: ='5.Inequality - Gini coefficient'!B151 -> Venezuela (2013): Molina, Emiro. 2016. “CEQ Master Workbook: Venezuela (2012),” CEQ Data Center on Fiscal Redistribution (CEQ Institute, Tulane University). April 5, 2018.

Sheet 5.Inequality - Gini coefficient
A1: Go to Contents
B3: Inequality - Gini coefficient
B4: NOTE: FOR SOURCES AND CITATIONS SEE BOTTOM OF PAGE
B6: Country | C6: Year of survey | D6: Year of budgetary data and fiscal system | F6: Contributory pensions as deferred income | K6: Contributory pensions as government transfer
F7: Market income plus pensions | G7: Disposable income | H7: Consumable income | I7: Final income | K7: Market income | L7: Disposable income | M7: Consumable income | N7: Final income
A8: =A7+1 -> 1 | B8: *,** Albania (2015) | C8: 2015 | D8: 2015 | F8: 0.3693 | G8: 0.3452 | H8: 0.3453 | I8: 0.317 | K8: 0.4742 | L8: 0.3452 | M8: 0.3453 | N8: 0.317
A9: =A8+1 -> 2 | B9: Argentina (2012) | C9: 2012-13 | D9: 2012 | F9: 0.4749556 | G9: 0.4046247 | H9: 0.4105455 | I9: 0.2986643 | K9: 0.501804 | L9: 0.4037833 | M9: 0.4097137 | N9: 0.2975485
A10: =A9+1 -> 3 | B10: Armenia (2011) | C10: 2011 | D10: 2011 | F10: 0.4044213 | G10: 0.37525667 | H10: 0.37675151 | I10: 0.35813615 | K10: 0.4700838 | L10: 0.37525667 | M10: 0.37675151 | N10: 0.35813615
A11: =A10+1 -> 4 | B11: *,** Belarus (2015) | C11: 2015 | D11: 2016 | F11: 0.292 | G11: 0.267 | H11: 0.27 | I11: 0.227 | K11: 0.407 | L11: 0.267 | M11: 0.27 | N11: 0.227
A12: =A11+1 -> 5 | B12: Bolivia (2009) | C12: 2009 | D12: 2009 | F12: 0.503 | G12: 0.493 | H12: 0.5028 | I12: 0.446 | K12: 0.5025 | L12: 0.493 | M12: 0.5028 | N12: 0.446
A13: =A12+1 -> 6 | B13: Brazil (2008) | C13: 2008-09 | D13: 2009 | F13: 0.57301587 | G13: 0.54460712 | H13: 0.54196905 | I13: 0.47931725 | K13: 0.59323816 | L13: 0.54460712 | M13: 0.54196905 | N13: 0.47931725
A14: =A13+1 -> 7 | B14: *,** Burkina Faso (2014) | C14: 2014 | D14: 2014 | F14: 0.3635 | G14: 0.353 | H14: 0.3539 | I14: 0.3283 | K14: 0.3667 | L14: 0.353 | M14: 0.3539 | N14: 0.3283
A15: =A14+1 -> 8 | B15: Chile (2013) | C15: 2013 | D15: 2013 | F15: 0.49359692 | G15: 0.46684199 | H15: 0.46409278 | I15: 0.41959384 | K15: 0.50284354 | L15: 0.46676243 | M15: 0.46400819 | N15: 0.41948503
A16: =A15+1 -> 9 | B16: Colombia (2010) | C16: 2010 | D16: 2010 | F16: 0.57761229 | G16: 0.56653029 | H16: 0.55869628 | I16: 0.51327697 | K16: 0.57498707 | L16: 0.56653029 | M16: 0.55869628 | N16: 0.51327697
B17: Colombia (2014) | C17: 2014 | D17: 2014 | F17: 0.57526175 | G17: 0.56551802 | H17: 0.55923427 | I17: 0.51464942 | K17: 0.57457582 | L17: 0.56551802 | M17: 0.55923427 | N17: 0.51464942
A18: =A16+1 -> 10 | B18: *,** Comoros (2014) | C18: 2014 | F18: 0.437 | H18: 0.45 | I18: 0.404
A19: =A18+1 -> 11 | B19: Costa Rica (2010) | C19: 2010 | D19: 2010 | F19: 0.508 | G19: 0.489 | H19: 0.486 | I19: 0.402 | K19: 0.512 | L19: 0.488 | M19: 0.485 | N19: 0.4
A20: =A19+1 -> 12 | B20: *,** Croatia (2014) | C20: 2014 | D20: 2014 | F20: 0.39179141 | G20: 0.325 | H20: 0.355 | I20: 0.291 | K20: 0.513 | L20: 0.325 | M20: 0.355 | N20: 0.291
A21: =A20+1 -> 13 | B21: Dominican Republic (2006) | C21: 2006-07 | D21: 2013 | F21: 0.5166611 | G21: 0.5053576 | H21: 0.49509696 | I21: 0.46501155 | K21: 0.51729887 | L21: 0.5053576 | M21: 0.49509696 | N21: 0.46501155
A22: =A21+1 -> 14 | B22: Ecuador (2011) | C22: 2011-12 | D22: 2011 | F22: 0.47850555 | G22: 0.45701572 | H22: 0.44568938 | I22: 0.40462824 | K22: 0.48233714 | L22: 0.45212875 | M22: 0.44085193 | N22: 0.40016075
A23: =A22+1 -> 15 | B23: *,** Egypt (2015) | C23: 2015 | D23: 2015 | F23: 0.325 | G23: 0.307 | H23: 0.299 | I23: 0.281
A24: =A23+1 -> 16 | B24: El Salvador (2011) | C24: 2011 | D24: 2011 | F24: 0.44114552 | G24: 0.42091392 | H24: 0.41063727 | I24: 0.38339826 | K24: 0.43813338 | L24: 0.42091392 | M24: 0.41063727 | N24: 0.38339826
A25: =A24+1 -> 17 | B25: Ethiopia (2010) | C25: 2010-11 | D25: 2011 | F25: 0.32167086 | G25: 0.30468106 | H25: 0.30187649 | I25: 0.29906484
A26: =A25+1 -> 18 | B26: Georgia (2013) | C26: 2013 | D26: 2013 | K26: 0.50744782 | L26: 0.39486926 | M26: 0.41130303 | N26: 0.38303767
A27: =A26+1 -> 19 | B27: Ghana (2012) | C27: 2012-13 | D27: 2013 | F27: 0.43698289 | G27: 0.42367803 | H27: 0.42328982 | I27: 0.40213141
A28: =A27+1 -> 20 | B28: Guatemala (2011) | C28: 2011 | D28: 2011 | F28: 0.512876 | G28: 0.504953 | H28: 0.505832 | I28: 0.489362 | K28: 0.511437 | L28: 0.503084 | M28: 0.503949 | N28: 0.487376
A29: =A28+1 -> 21 | B29: *,** Guinea (2012) | C29: 2012 | D29: 2016 | K29: 0.319 | L29: 0.317 | M29: 0.319 | N29: 0.317
A30: =A29+1 -> 22 | B30: Honduras (2011) | C30: 2011 | D30: 2011 | F30: 0.564099 | G30: 0.5566494 | H30: 0.551806 | I30: 0.5380545 | K30: 0.5612189 | L30: 0.556317 | M30: 0.5515012 | N30: 0.5377351
A31: =A30+1 -> 23 | B31: Indonesia (2012) | C31: 2012 | D31: 2012 | F31: 0.39826859 | G31: 0.38988379 | H31: 0.39062523 | I31: 0.37047561 | K31: 0.3944 | L31: 0.3893 | M31: 0.39 | N31: 0.3698477
A32: =A31+1 -> 24 | B32: Iran (2011) | C32: 2011-12 | D32: 2011-12 | F32: 0.42856971 | G32: 0.36860859 | H32: 0.37124157 | I32: 0.34317052
A33: =A32+1 -> 25 | B33: Jordan (2010) | C33: 2010-11 | D33: 2010 | F33: 0.34151424 | G33: 0.32833663 | H33: 0.32543258 | I33: 0.31855528 | K33: 0.3505 | L33: 0.3283 | M33: 0.3254 | N33: 0.3186
A34: =A33+1 -> 26 | B34: *,** Kenya (2015) | C34: 2015-16 | D34: 2015-16 | F34: 0.362 | G34: 0.336 | H34: 0.328 | I34: 0.297
A35: =A34+1 -> 27 | B35: *,** Mali (2014) | C35: 2014 | D35: 2014 | K35: 0.491 | L35: 0.486 | M35: 0.482 | N35: 0.469
A36: =A35+1 -> 28 | B36: Mexico (2010) | C36: 2010 | D36: 2010 | F36: 0.51067918 | G36: 0.48764237 | H36: 0.48088023 | I36: 0.42938942 | K36: 0.50873534 | L36: 0.48764237 | M36: 0.48065147 | N36: 0.42918418
B37: Mexico (2012) | C37: 2012 | D37: 2012 | F37: 0.52389439 | G37: 0.49286862 | H37: 0.48632189 | I37: 0.43993635 | K37: 0.52099103 | L37: 0.49286862 | M37: 0.48632189 | N37: 0.43993635
B38: Mexico (2014) | C38: 2014 | D38: 2014 | F38: 0.52801653 | G38: 0.49432719 | H38: 0.48998956 | I38: 0.44169476 | K38: 0.52772937 | L38: 0.49432719 | M38: 0.48998956 | N38: 0.44169476
A39: =A36+1 -> 29 | B39: *,** Mongolia (2016) | C39: 2016 | D39: 2016 | K39: 0.4183 | L39: 0.3626 | M39: 0.3752 | N39: 0.3507
A40: =A39+1 -> 30 | B40: *,** Namibia (2009) | C40: 2009 | D40: 2009 -10 | F40: 0.635 | G40: 0.594 | H40: 0.59 | I40: 0.429
A41: =A40+1 -> 31 | B41: Nicaragua (2009) | C41: 2009 | D41: 2009 | F41: 0.48176913 | G41: 0.46724375 | H41: 0.46482961 | I41: 0.43466658 | K41: 0.48196262 | L41: 0.46803349 | M41: 0.46566141 | N41: 0.43534372
A42: =A41+1 -> 32 | B42: *,** Niger (2014) | C42: 2014 -15 | D42: 2014 | K42: 0.337 | L42: 0.327 | M42: 0.326 | N42: 0.318
A43: =A42+1 -> 33 | B43: Panama (2016) | C43: 2016 | D43: 2015 | F43: 0.55655946 | G43: 0.5339104 | H43: 0.52872147 | I43: 0.46703448 | K43: 0.55468967 | L43: 0.5339104 | M43: 0.52872147 | N43: 0.46703448
A44: =A43+1 -> 34 | B44: Paraguay (2014) | C44: 2014 | D44: 2014 | F44: 0.52160396 | G44: 0.51264643 | H44: 0.50990945 | I44: 0.47327764
A45: =A44+1 -> 35 | B45: Peru (2009) | C45: 2009 | D45: 2009 | F45: 0.5039 | G45: 0.4937 | H45: 0.4921 | I45: 0.465705 | K45: 0.502518 | L45: 0.493034 | M45: 0.491352 | N45: 0.464
B46: Peru (2011) | C46: 2011 | D46: 2011 | F46: 0.4731859 | G46: 0.46653779 | H46: 0.46040006 | I46: 0.43044614 | K46: 0.47385548 | L46: 0.46653779 | M46: 0.46040006 | N46: 0.43044614
A47: =A45+1 -> 36 | B47: *,** Poland (2014) | C47: 2014 | D47: 2014 | F47: 0.41208269 | G47: 0.34490968 | H47: 0.35521191 | I47: 0.29066345 | K47: 0.52647071 | L47: 0.3427859 | M47: 0.35472409 | N47: 0.2821
A48: =A47+1 -> 37 | B48: *,** Romania (2016) | C48: 2016 | D48: 2016 | F48: 0.37809162 | G48: 0.33412756 | H48: 0.3363644 | I48: 0.30744559 | K48: 0.487 | L48: 0.334 | M48: 0.34 | N48: 0.31
A49: =A48+1 -> 38 | B49: Russia (2010) | C49: 2010 | D49: 2010 | F49: 0.37876103 | G49: 0.34846259 | H49: 0.35087875 | I49: 0.32258529 | K49: 0.49212282 | L49: 0.34846259 | M49: 0.35087875 | N49: 0.32258529
A50: =A49+1 -> 39 | B50: South Africa (2010) | C50: 2010-11 | D50: 2010 | F50: 0.7712094 | G50: 0.69443095 | H50: 0.69461615 | I50: 0.59545356
A51: =A50+1 -> 40 | B51: Sri Lanka (2009) | C51: 2009-10 | D51: 2010 | F51: 0.34444843 | G51: 0.33664711 | H51: 0.33850775 | I51: 0.32647127
A52: =A51+1 -> 41 | B52: Tanzania (2011) | C52: 2011-12 | D52: 2011-12 | F52: 0.38511288 | G52: 0.35754551 | H52: 0.34462611 | I52: 0.3357093
A53: =A52+1 -> 42 | B53: Tunisia (2010) | C53: 2010 | D53: 2010 | F53: 0.4307 | G53: 0.3972 | H53: 0.3812 | I53: 0.3516 | K53: 0.4096 | L53: 0.3972 | M53: 0.3812 | N53: 0.3516
A54: =A53+1 -> 43 | B54: Uganda (2012) | C54: 2012-13 | D54: 2012-13 | F54: 0.41383471 | G54: 0.40040254 | H54: 0.3977082 | I54: 0.38107285
A55: =A54+1 -> 44 | B55: *,** Ukraine (2016) | C55: 2016 | D55: 2016 | F55: 0.3111 | G55: 0.241 | H55: 0.247 | I55: 0.223
A56: =A55+1 -> 45 | B56: United States (2011) | C56: 2011 | D56: 2011 | F56: 0.448 | G56: 0.376 | H56: 0.378 | I56: 0.331 | K56: 0.484 | L56: 0.372 | M56: 0.374 | N56: 0.325
A57: =A56+1 -> 46 | B57: Uruguay (2009) | C57: 2009 | D57: 2009 | F57: 0.50504682 | G57: 0.46688208 | H57: 0.4682924 | I57: 0.41824548 | K57: 0.54393064 | L57: 0.46688208 | M57: 0.4682924 | N57: 0.41824548
A58: =A57+1 -> 47 | B58: Venezuela (2013) | C58: 2013 | D58: 2013 | F58: 0.401 | G58: 0.3878 | H58: 0.3805 | I58: 0.3424 | K58: 0.4108 | L58: 0.3869 | M58: 0.3795 | N58: 0.3409
C61: not applicable; means that the indicator should not be calculated due to methodological reasons or characteristics of the fiscal system.
C63: not calculated; means that the indicator was not calculated by the author/s.
C65: not available; means that the indicator was calculated but it is not publicly available, requests should be put directly to author/s.
C67: not available; means that the indicator is no published on the World Bank's report
B70: * The information published here is from World Bank led CEQ assessments and has not undergone quality control by the CEQ Institute. The information is taken from World Bank Policy Research Working Papers. See References for further detail.
B71: ** At least some information for this CEQ Assessment was extracted directly from World Bank Policy Research Working Papers, Reports, Working Papers (numbered series) and Poverty Assessment.
B72: *** Note that the Market Income (PGT) scenario is an eye-ball estimate only; the precise estimate needs to be confirmed with the Albania team.
B74: Notes
B75: 1. The year represented by the data in parentheses.
B76: 2. Because national and international agencies often update their data series, the information included here may be subject to change.
B77: 3. The letters "C" and "I" indicate that the study used consumption or income data, respectively.
B78: 4. In Armenia, Costa Rica, Iran, Peru, South Africa and Uruguay there are no indirect subsidies.
B79: 5. Bolivia does not have personal income taxes.
B80: 6. In Bolivia, Costa Rica, Ecuador, Honduras, South Africa and Sri Lanka, market income does not include consumption of own production because the data was either not available or not reliable.
B81: 7. For Brazil, the results for the analysis presented here differ from the results published in Higgins and Pereira (2014) because the latter include taxes on services (ISS), on goods and services to finance pensions (CONFINS) and to finance Social Workers (PIS), while the results presented here do not include them. Post publishing the mentioned paper, the authors concluded that the source for these taxes was not reliable.
B82: 8. Gini coefficients for Chile are estimated here using total income and, thus, differ from official figures of inequality which are estimated using monetary income (i.e., official figures exclude owner’s occupied imputed rent).
... B100: Source: CEQ Institute’s Data Center on Fiscal Redistribution. Based on the following Master Workbooks of Results, for United States the source is the publication of Higgins, et al. (2016):
A101: =A8 -> 1 | B101: =(CONCATENATE(B8,": ",'26. Source - CEQ MWBs'!C11)) -> *,** Albania (2015): n.a.
A102: =A9 -> 2 | B102: =(CONCATENATE(B9,": ",'26. Source - CEQ MWBs'!C12)) -> Argentina (2012): Rossignolo, Dario. 2017. “CEQ Master Workbook: Argentina (2012-2013),” CEQ Data Center on Fiscal Redistribution (CEQ Institute, Tulane University). Jun 8, 2018.
A103: =A10 -> 3 | B103: =(CONCATENATE(B10,": ",'26. Source - CEQ MWBs'!C13)) -> Armenia (2011): Younger, Stephen D., Artsvi Khachatryan, Gohar Gyulumyan, Nistha Sinha, and Ulrich Bartsch. 2019. “CEQ Master Workbook: Armenia (2011),” CEQ Data Center on Fiscal Redistribution (CEQ Institute, Tulane University and the World Bank). June 8, 2019.
A104: =A11 -> 4 | B104: =(CONCATENATE(B11,": ",'26. Source - CEQ MWBs'!C14)) -> *,** Belarus (2015): n.a.
A105: =A12 -> 5 | B105: =(CONCATENATE(B12,": ",'26. Source - CEQ MWBs'!C15)) -> Bolivia (2009): Paz Arauco, Veronica, George Gray-Molina, Wilson Jimenez and Ernesto Yañez. 2014. “CEQ Master Workbook: Bolivia (2009),” CEQ Data Center on Fiscal Redistribution (CEQ Institute, Tulane University). September 22, 2014.
A106: =A13 -> 6 | B106: =(CONCATENATE(B13,": ",'26. Source - CEQ MWBs'!C16)) -> Brazil (2008): Higgins, Sean, Claudiney Pereira, and, Maynor Cabrera. 2019. “CEQ Master Workbook: Brazil (2008-2009),” CEQ Data Center on Fiscal Redistribution (CEQ Institute, Tulane University). May 3, 2019.
A107: =A14 -> 7 | B107: =(CONCATENATE(B14,": ",'26. Source - CEQ MWBs'!C17)) -> *,** Burkina Faso (2014): n.a.
A108: =A15 -> 8 | B108: =(CONCATENATE(B15,": ",'26. Source - CEQ MWBs'!C18)) -> Chile (2013): Martinez-Aguilar, Sandra and Eduardo Ortiz-Juarez. 2016. “CEQ Master Workbook: Chile (2013),” CEQ Data Center on Fiscal Redistribution (CEQ Institute, Tulane University and the World Bank). October 7, 2016.
A109: =A16 -> 9 | B109: =(CONCATENATE(B16,": ",'26. Source - CEQ MWBs'!C19)) -> Colombia (2010): Melendez, Marcela and Valentina Martinez. 2019. “CEQ Master Workbook: Colombia (2010),” CEQ Data Center on Fiscal Redistribution (CEQ Institute, Tulane University and Inter-American Development Bank). February 20, 2019.
A110: =A17 -> 0 | B110: =(CONCATENATE(B17,": ",'26. Source - CEQ MWBs'!C20)) -> Colombia (2014): Melendez, Marcela and Valentina Martinez. 2019. “CEQ Master Workbook: Colombia (2014),” CEQ Data Center on Fiscal Redistribution (CEQ Institute, Tulane University and Inter-American Development Bank). February 28, 2019.
A111: =A18 -> 10 | B111: =(CONCATENATE(B18,": ",'26. Source - CEQ MWBs'!C21)) -> *,** Comoros (2014): n.a.
A112: =A19 -> 11 | B112: =(CONCATENATE(B19,": ",'26. Source - CEQ MWBs'!C22)) -> Costa Rica (2010): Sauma, Pablo and Juan Diego Trejos. 2014. “CEQ Master Workbook: Costa Rica (2010),” CEQ Data Center on Fiscal Redistribution (CEQ Institute, Tulane University). February 14, 2014.
... A151: =A58 -> 47 | B151: =(CONCATENATE(B58,": ",'26. Source - CEQ MWBs'!C61)) -> Venezuela (2013): Molina, Emiro. 2016. “CEQ Master Workbook: Venezuela (2012),” CEQ Data Center on Fiscal Redistribution (CEQ Institute, Tulane University). April 5, 2018.

Sheet 6.Inequality - Theil index
A1: Go to Contents
B3: Inequality - Theil index
B4: NOTE: FOR SOURCES AND CITATIONS SEE BOTTOM OF PAGE
B6: Country | C6: Year of survey | D6: Year of budgetary data and fiscal system | F6: Contributory pensions as deferred income | K6: Contributory pensions as government transfer
F7: Market income plus pensions | G7: Disposable income | H7: Consumable income | I7: Final income | K7: Market income | L7: Disposable income | M7: Consumable income | N7: Final income
A8: =A7+1 -> 1 | B8: *,** Albania (2015) | C8: 2015 | D8: 2015
A9: =A8+1 -> 2 | B9: Argentina (2012) | C9: 2012-13 | D9: 2012 | F9: 0.4139067 | G9: 0.3020465 | H9: 0.328989 | I9: 0.2069367 | K9: 0.4537431 | L9: 0.3014081 | M9: 0.3286514 | N9: 0.2062115
A10: =A9+1 -> 3 | B10: Armenia (2011) | C10: 2011 | D10: 2011 | F10: 0.29351843 | G10: 0.25239742 | H10: 0.25523365 | I10: 0.23100364 | K10: 0.39353479 | L10: 0.25239742 | M10: 0.25523365 | N10: 0.23100364
A11: =A10+1 -> 4 | B11: *,** Belarus (2015) | C11: 2015 | D11: 2016 | F11: 0.15084802 | G11: 0.12936801 | H11: 0.13144089 | I11: 0.094420009 | K11: 0.25891151 | L11: 0.12936801 | M11: 0.13144089 | N11: 0.094420009
A12: =A11+1 -> 5 | B12: Bolivia (2009) | C12: 2009 | D12: 2009 | F12: 0.4969 | G12: 0.4777 | H12: 0.499 | I12: 0.3967 | K12: 0.4963 | L12: 0.4777 | M12: 0.499 | N12: 0.3967
A13: =A12+1 -> 6 | B13: Brazil (2008) | C13: 2008-09 | D13: 2009 | F13: 0.66466623 | G13: 0.5933286 | H13: 0.58647793 | I13: 0.47052721 | K13: 0.69953011 | L13: 0.5933286 | M13: 0.58647793 | N13: 0.47052721
A14: =A13+1 -> 7 | B14: *,** Burkina Faso (2014) | C14: 2014 | D14: 2014 | F14: 0.2637 | G14: 0.2424 | H14: 0.242 | I14: 0.2068 | K14: 0.2748 | L14: 0.2424 | M14: 0.242 | N14: 0.2068
A15: =A14+1 -> 8 | B15: Chile (2013) | C15: 2013 | D15: 2013 | F15: 0.49029653 | G15: 0.43300057 | H15: 0.42784733 | I15: 0.35559887 | K15: 0.51072639 | L15: 0.43300057 | M15: 0.42784733 | N15: 0.35708041
A16: =A15+1 -> 9 | B16: Colombia (2010) | C16: 2010 | D16: 2010 | F16: 0.70625479 | G16: 0.68607351 | H16: 0.66911748 | I16: 0.57320107 | K16: 0.71024334 | L16: 0.68607351 | M16: 0.66911748 | N16: 0.57320107
B17: Colombia (2014) | C17: 2014 | D17: 2014 | F17: 0.74476068 | G17: 0.72507598 | H17: 0.7159254 | I17: 0.61741439 | K17: 0.74920683 | L17: 0.72507598 | M17: 0.7159254 | N17: 0.61741439
A18: =A16+1 -> 10 | B18: *,** Comoros (2014) | C18: 2014
A19: =A18+1 -> 11 | B19: Costa Rica (2010) | C19: 2010 | D19: 2010
A20: =A19+1 -> 12 | B20: *,** Croatia (2014) | C20: 2014 | D20: 2014 | F20: 0.27000109 | G20: 0.18062743 | H20: 0.21516028 | I20: 0.14063791 | K20: 0.45802559 | L20: 0.18062743 | M20: 0.21516028 | N20: 0.14063791
A21: =A20+1 -> 13 | B21: Dominican Republic (2006) | C21: 2006-07 | D21: 2013 | F21: 0.52686511 | G21: 0.50135302 | H21: 0.47450242 | I21: 0.42455776 | K21: 0.52919688 | L21: 0.50135302 | M21: 0.47450242 | N21: 0.42455776
A22: =A21+1 -> 14 | B22: Ecuador (2011) | C22: 2011-12 | D22: 2011 | F22: 0.4519368 | G22: 0.41687091 | H22: 0.39545749 | I22: 0.33476308 | K22: 0.46152118 | L22: 0.40978988 | M22: 0.38858212 | N22: 0.32903645
A23: =A22+1 -> 15 | B23: *,** Egypt (2015) | C23: 2015 | D23: 2015
A24: =A23+1 -> 16 | B24: El Salvador (2011) | C24: 2011 | D24: 2011 | F24: 0.36127258 | G24: 0.33032167 | H24: 0.3133004 | I24: 0.27479751 | K24: 0.35555666 | L24: 0.33032167 | M24: 0.3133004 | N24: 0.27479751
A25: =A24+1 -> 17 | B25: Ethiopia (2010) | C25: 2010-11 | D25: 2011 | F25: 0.20925465 | G25: 0.18397009 | H25: 0.18027546 | I25: 0.17863119
A26: =A25+1 -> 18 | B26: Georgia (2013) | C26: 2013 | D26: 2013 | K26: 0.4543 | L26: 0.2778 | M26: 0.2934 | N26: 0.2616
A27: =A26+1 -> 19 | B27: Ghana (2012) | C27: 2012-13 | D27: 2013 | F27: 0.34386673 | G27: 0.32075623 | H27: 0.31918099 | I27: 0.28894964
A28: =A27+1 -> 20 | B28: Guatemala (2011) | C28: 2011 | D28: 2011 | F28: 0.64632 | G28: 0.631128 | H28: 0.64626 | I28: 0.606918 | K28: 0.645289 | L28: 0.629759 | M28: 0.645191 | N28: 0.605519
A29: =A28+1 -> 21 | B29: *,** Guinea (2012) | C29: 2012 | D29: 2016
A30: =A29+1 -> 22 | B30: Honduras (2011) | C30: 2011 | D30: 2011 | F30: 0.6805379 | G30: 0.6674805 | H30: 0.6644207 | I30: 0.6358788 | K30: 0.6719523 | L30: 0.6667623 | M30: 0.6638092 | N30: 0.6352507
A31: =A30+1 -> 23 | B31: Indonesia (2012) | C31: 2012 | D31: 2012 | F31: 0.3077 | G31: 0.302 | H31: 0.3012 | I31: 0.2721025 | K31: 0.308 | L31: 0.3014 | M31: 0.3006 | N31: 0.2714722
A32: =A31+1 -> 24 | B32: Iran (2011) | C32: 2011-12 | D32: 2011-12 | F32: 0.3313865 | G32: 0.24783927 | H32: 0.2513852 | I32: 0.21223875
A33: =A32+1 -> 25 | B33: Jordan (2010) | C33: 2010-11 | D33: 2010 | F33: 0.21723137 | G33: 0.19389967 | H33: 0.19107169 | I33: 0.19364638 | K33: 0.22912768 | L33: 0.19389967 | M33: 0.19107169 | N33: 0.19364638
A34: =A33+1 -> 26 | B34: *,** Kenya (2015) | C34: 2015-16 | D34: 2015-16
A35: =A34+1 -> 27 | B35: *,** Mali (2014) | C35: 2014 | D35: 2014
A36: =A35+1 -> 28 | B36: Mexico (2010) | C36: 2010 | D36: 2010
B37: Mexico (2012) | C37: 2012 | D37: 2012 | F37: 0.54711687 | G37: 0.485 | H37: 0.47 | I37: 0.39 | K37: 0.54412501 | L37: 0.48541917 | M37: 0.47003725 | N37: 0.38963626
B38: Mexico (2014) | C38: 2014 | D38: 2014 | F38: 0.5925997 | G38: 0.5222389 | H38: 0.51253777 | I38: 0.4239243 | K38: 0.59776654 | L38: 0.5222389 | M38: 0.51253777 | N38: 0.4239243
A39: =A36+1 -> 29 | B39: *,** Mongolia (2016) | C39: 2016 | D39: 2016 | K39: 0.322 | L39: 0.2434 | M39: 0.2581 | N39: 0.2557
A40: =A39+1 -> 30 | B40: *,** Namibia (2009) | C40: 2009 | D40: 2009 -10 | F40: 0.83 | G40: 0.76 | H40: 0.75 | I40: 0.385
A41: =A40+1 -> 31 | B41: Nicaragua (2009) | C41: 2009 | D41: 2009 | F41: 0.45626045 | G41: 0.42583204 | H41: 0.42395902 | I41: 0.37255926 | K41: 0.45720663 | L41: 0.42729787 | M41: 0.42548289 | N41: 0.37372405
A42: =A41+1 -> 32 | B42: *,** Niger (2014) | C42: 2014 -15 | D42: 2014
A43: =A42+1 -> 33 | B43: Panama (2016) | C43: 2016 | D43: 2015 | F43: 0.72359152 | G43: 0.69182765 | H43: 0.68089191 | I43: 0.55571223 | K43: 0.71661912 | L43: 0.69182765 | M43: 0.68089191 | N43: 0.55571223
A44: =A43+1 -> 34 | B44: Paraguay (2014) | C44: 2014 | D44: 2014 | F44: 0.5867 | G44: 0.5285 | H44: 0.535 | I44: 0.5113
A45: =A44+1 -> 35 | B45: Peru (2009) | C45: 2009 | D45: 2009
B46: Peru (2011) | C46: 2011 | D46: 2011 | F46: 0.4256463 | G46: 0.41236962 | H46: 0.40119499 | I46: 0.35285446 | K46: 0.42802542 | L46: 0.41236962 | M46: 0.40119499 | N46: 0.35285446
A47: =A45+1 -> 36 | B47: *,** Poland (2014) | C47: 2014 | D47: 2014 | F47: 0.29603969 | G47: 0.21157183 | H47: 0.22197477 | I47: 0.15474431 | K47: 0.4563621 | L47: 0.21176203 | M47: 0.22516618 | N47: 0.14945796
A48: =A47+1 -> 37 | B48: *,** Romania (2016) | C48: 2016 | D48: 2016 | F48: 0.24303307 | G48: 0.18835133 | H48: 0.19130382 | I48: 0.15967784 | K48: 0.40078052 | L48: 0.18835133 | M48: 0.19130382 | N48: 0.15967784
A49: =A48+1 -> 38 | B49: Russia (2010) | C49: 2010 | D49: 2010 | F49: 0.2550738 | G49: 0.2230065 | H49: 0.2276023 | I49: 0.19525178 | K49: 0.38044931 | L49: 0.2230065 | M49: 0.2276023 | N49: 0.19525178
A50: =A49+1 -> 39 | B50: South Africa (2010) | C50: 2010-11 | D50: 2010 | F50: 1.2218195 | G50: 0.97256855 | H50: 0.97122793 | I50: 0.72299094
A51: =A50+1 -> 40 | B51: Sri Lanka (2009) | C51: 2009-10 | D51: 2010 | F51: 0.24498902 | G51: 0.23299705 | H51: 0.23735488 | I51: 0.22209116
A52: =A51+1 -> 41 | B52: Tanzania (2011) | C52: 2011-12 | D52: 2011-12 | F52: 0.32104249 | G52: 0.261 | H52: 0.244 | I52: 0.232
A53: =A52+1 -> 42 | B53: Tunisia (2010) | C53: 2010 | D53: 2010 | F53: 0.3301 | G53: 0.2814 | H53: 0.2591 | I53: 0.2198 | K53: 0.3 | L53: 0.2814 | M53: 0.2591 | N53: 0.2198
A54: =A53+1 -> 43 | B54: Uganda (2012) | C54: 2012-13 | D54: 2012-13 | F54: 0.33164267 | G54: 0.30239022 | H54: 0.29814574 | I54: 0.27575308
A55: =A54+1 -> 44 | B55: *,** Ukraine (2016) | C55: 2016 | D55: 2016
A56: =A55+1 -> 45 | B56: United States (2011) | C56: 2011 | D56: 2011
A57: =A56+1 -> 46 | B57: Uruguay (2009) | C57: 2009 | D57: 2009 | F57: 0.48373774 | G57: 0.41475374 | H57: 0.41757192 | I57: 0.34079833 | K57: 0.55190003 | L57: 0.46688208 | M57: 0.4682924 | N57: 0.41824548
A58: =A57+1 -> 47 | B58: Venezuela (2013) | C58: 2013 | D58: 2013 | F58: 0.2907 | G58: 0.2677 | H58: 0.2576 | I58: 0.2109 | K58: 0.3062 | L58: 0.2665 | M58: 0.2562 | N58: 0.2092
C61: not applicable; means that the indicator should not be calculated due to methodological reasons or characteristics of the fiscal system.
C63: not calculated; means that the indicator was not calculated by the author/s.
C65: not available; means that the indicator was calculated but it is not publicly available, requests should be put directly to author/s.
C67: not available; means that the indicator is no published on the World Bank's report
B70: * The information published here is from World Bank led CEQ assessments and has not undergone quality control by the CEQ Institute. The information is taken from World Bank Policy Research Working Papers. See References for further detail.
B71: ** At least some information for this CEQ Assessment was extracted directly from World Bank Policy Research Working Papers, Reports, Working Papers (numbered series) and Poverty Assessment.
B72: *** Note that the Market Income (PGT) scenario is an eye-ball estimate only; the precise estimate needs to be confirmed with the Albania team.
B74: Notes
B75: 1. The year represented by the data in parentheses.
B76: 2. Because national and international agencies often update their data series, the information included here may be subject to change.
B77: 3. The letters "C" and "I" indicate that the study used consumption or income data, respectively.
B78: 4. In Armenia, Costa Rica, Iran, Peru, South Africa and Uruguay there are no indirect subsidies.
B79: 5. Bolivia does not have personal income taxes.
B80: 6. In Bolivia, Costa Rica, Ecuador, Honduras, South Africa and Sri Lanka, market income does not include consumption of own production because the data was either not available or not reliable.
B81: 7. For Brazil, the results for the analysis presented here differ from the results published in Higgins and Pereira (2014) because the latter include taxes on services (ISS), on goods and services to finance pensions (CONFINS) and to finance Social Workers (PIS), while the results presented here do not include them. Post publishing the mentioned paper, the authors concluded that the source for these taxes was not reliable.
B82: 8. Gini coefficients for Chile are estimated here using total income and, thus, differ from official figures of inequality which are estimated using monetary income (i.e., official figures exclude owner’s occupied imputed rent).
... B100: Source: CEQ Institute’s Data Center on Fiscal Redistribution. Based on the following Master Workbooks of Results, for United States the source is the publication of Higgins, et al. (2016):
A101: =A8 -> 1 | B101: =(CONCATENATE(B8,": ",'26. Source - CEQ MWBs'!C11)) -> *,** Albania (2015): n.a.
A102: =A9 -> 2 | B102: =(CONCATENATE(B9,": ",'26. Source - CEQ MWBs'!C12)) -> Argentina (2012): Rossignolo, Dario. 2017. “CEQ Master Workbook: Argentina (2012-2013),” CEQ Data Center on Fiscal Redistribution (CEQ Institute, Tulane University). Jun 8, 2018.
A103: =A10 -> 3 | B103: =(CONCATENATE(B10,": ",'26. Source - CEQ MWBs'!C13)) -> Armenia (2011): Younger, Stephen D., Artsvi Khachatryan, Gohar Gyulumyan, Nistha Sinha, and Ulrich Bartsch. 2019. “CEQ Master Workbook: Armenia (2011),” CEQ Data Center on Fiscal Redistribution (CEQ Institute, Tulane University and the World Bank). June 8, 2019.
A104: =A11 -> 4 | B104: =(CONCATENATE(B11,": ",'26. Source - CEQ MWBs'!C14)) -> *,** Belarus (2015): n.a.
A105: =A12 -> 5 | B105: =(CONCATENATE(B12,": ",'26. Source - CEQ MWBs'!C15)) -> Bolivia (2009): Paz Arauco, Veronica, George Gray-Molina, Wilson Jimenez and Ernesto Yañez. 2014. “CEQ Master Workbook: Bolivia (2009),” CEQ Data Center on Fiscal Redistribution (CEQ Institute, Tulane University). September 22, 2014.
A106: =A13 -> 6 | B106: =(CONCATENATE(B13,": ",'26. Source - CEQ MWBs'!C16)) -> Brazil (2008): Higgins, Sean, Claudiney Pereira, and, Maynor Cabrera. 2019. “CEQ Master Workbook: Brazil (2008-2009),” CEQ Data Center on Fiscal Redistribution (CEQ Institute, Tulane University). May 3, 2019.
A107: =A14 -> 7 | B107: =(CONCATENATE(B14,": ",'26. Source - CEQ MWBs'!C17)) -> *,** Burkina Faso (2014): n.a.
A108: =A15 -> 8 | B108: =(CONCATENATE(B15,": ",'26. Source - CEQ MWBs'!C18)) -> Chile (2013): Martinez-Aguilar, Sandra and Eduardo Ortiz-Juarez. 2016. “CEQ Master Workbook: Chile (2013),” CEQ Data Center on Fiscal Redistribution (CEQ Institute, Tulane University and the World Bank). October 7, 2016.
A109: =A16 -> 9 | B109: =(CONCATENATE(B16,": ",'26. Source - CEQ MWBs'!C19)) -> Colombia (2010): Melendez, Marcela and Valentina Martinez. 2019. “CEQ Master Workbook: Colombia (2010),” CEQ Data Center on Fiscal Redistribution (CEQ Institute, Tulane University and Inter-American Development Bank). February 20, 2019.
A110: =A17 -> 0 | B110: =(CONCATENATE(B17,": ",'26. Source - CEQ MWBs'!C20)) -> Colombia (2014): Melendez, Marcela and Valentina Martinez. 2019. “CEQ Master Workbook: Colombia (2014),” CEQ Data Center on Fiscal Redistribution (CEQ Institute, Tulane University and Inter-American Development Bank). February 28, 2019.
A111: =A18 -> 10 | B111: =(CONCATENATE(B18,": ",'26. Source - CEQ MWBs'!C21)) -> *,** Comoros (2014): n.a.
A112: =A19 -> 11 | B112: =(CONCATENATE(B19,": ",'26. Source - CEQ MWBs'!C22)) -> Costa Rica (2010): Sauma, Pablo and Juan Diego Trejos. 2014. “CEQ Master Workbook: Costa Rica (2010),” CEQ Data Center on Fiscal Redistribution (CEQ Institute, Tulane University). February 14, 2014.
... A151: =A58 -> 47 | B151: =(CONCATENATE(B58,": ",'26. Source - CEQ MWBs'!C61)) -> Venezuela (2013): Molina, Emiro. 2016. “CEQ Master Workbook: Venezuela (2012),” CEQ Data Center on Fiscal Redistribution (CEQ Institute, Tulane University). April 5, 2018.

Sheet 7.Inequality - 90-10 ratio
A1: Go to Contents
B3: Inequality - 90/10 ratio
B4: NOTE: FOR SOURCES AND CITATIONS SEE BOTTOM OF PAGE
B6: Country | C6: Year of survey | D6: Year of budgetary data and fiscal system | F6: Contributory pensions as deferred income | K6: Contributory pensions as government transfer
F7: Market income plus pensions | G7: Disposable income | H7: Consumable income | I7: Final income | K7: Market income | L7: Disposable income | M7: Consumable income | N7: Final income
A8: =A7+1 -> 1 | B8: *,** Albania (2015) | C8: 2015 | D8: 2015
A9: =A8+1 -> 2 | B9: Argentina (2012) | C9: 2012-13 | D9: 2012 | F9: 11.00895 | G9: 6.85328 | H9: 6.90946 | I9: 3.765487 | K9: 17.94447 | L9: 6.842407 | M9: 6.846781 | N9: 3.744113
A10: =A9+1 -> 3 | B10: Armenia (2011) | C10: 2011 | D10: 2011 | F10: 8.0612256 | G10: 6.2751309 | H10: 6.3708408 | I10: 5.4855778 | K10: 21.806957 | L10: 6.2751309 | M10: 6.3708408 | N10: 5.4855778
A11: =A10+1 -> 4 | B11: *,** Belarus (2015) | C11: 2015 | D11: 2016 | F11: 3.7040852 | G11: 3.254104 | H11: 3.3165308 | I11: 2.6051263 | K11: 14.819509 | L11: 3.254104 | M11: 3.3165308 | N11: 2.6051263
A12: =A11+1 -> 5 | B12: Bolivia (2009) | C12: 2009 | D12: 2009 | F12: 14.7935 | G12: 12.3959 | H12: 13.7976 | I12: 8.1925 | K12: 14.9366 | L12: 12.3959 | M12: 13.7976 | N12: 8.1925
A13: =A12+1 -> 6 | B13: Brazil (2008) | C13: 2008-09 | D13: 2009 | F13: 16.246427 | G13: 12.868963 | H13: 12.642493 | I13: 7.3034645 | K13: 20.538376 | L13: 12.868963 | M13: 12.642493 | N13: 7.3034645
A14: =A13+1 -> 7 | B14: *,** Burkina Faso (2014) | C14: 2014 | D14: 2014 | F14: 4.18 | G14: 4.09 | H14: 4.14 | I14: 3.79 | K14: 4.16 | L14: 4.09 | M14: 4.14 | N14: 3.79
A15: =A14+1 -> 8 | B15: Chile (2013) | C15: 2013 | D15: 2013 | F15: 8.2768268 | G15: 6.877269 | H15: 6.795696 | I15: 5.1462503 | K15: 8.6917128 | L15: 6.877269 | M15: 6.795696 | N15: 5.1764703
A16: =A15+1 -> 9 | B16: Colombia (2010) | C16: 2010 | D16: 2010 | F16: 13.321492 | G16: 11.686769 | H16: 11.003238 | I16: 7.7178186 | K16: 12.899748 | L16: 11.686769 | M16: 11.003238 | N16: 7.7178186
B17: Colombia (2014) | C17: 2014 | D17: 2014 | F17: 12.858193 | G17: 11.474934 | H17: 10.977106 | I17: 7.6796113 | K17: 13.114946 | L17: 11.474934 | M17: 10.977106 | N17: 7.6796113
A18: =A16+1 -> 10 | B18: *,** Comoros (2014) | C18: 2014 | H18: 8.8
A19: =A18+1 -> 11 | B19: Costa Rica (2010) | C19: 2010 | D19: 2010
A20: =A19+1 -> 12 | B20: *,** Croatia (2014) | C20: 2014 | D20: 2014 | F20: 7.069971 | G20: 4.7009715 | H20: 5.8334298 | I20: 4.0487448 | K20: 59.300133 | L20: 4.7009715 | M20: 5.8334298 | N20: 4.0487448
A21: =A20+1 -> 13 | B21: Dominican Republic (2006) | C21: 2006-07 | D21: 2013 | F21: 10.55293 | G21: 9.8303759 | H21: 9.4238346 | I21: 7.5179177 | K21: 10.521596 | L21: 9.8303759 | M21: 9.4238346 | N21: 7.5179177
A22: =A21+1 -> 14 | B22: Ecuador (2011) | C22: 2011-12 | D22: 2011 | F22: 8.8941748 | G22: 7.5109776 | H22: 7.0428845 | I22: 5.2679813 | K22: 9.142158 | L22: 7.2832993 | M22: 6.8710005 | N22: 5.1683642
A23: =A22+1 -> 15 | B23: *,** Egypt (2015) | C23: 2015 | D23: 2015
A24: =A23+1 -> 16 | B24: El Salvador (2011) | C24: 2011 | D24: 2011 | F24: 7.6327016 | G24: 6.6228048 | H24: 6.2571839 | I24: 5.3235685 | K24: 7.5697933 | L24: 6.6228048 | M24: 6.2571839 | N24: 5.3235685
A25: =A24+1 -> 17 | B25: Ethiopia (2010) | C25: 2010-11 | D25: 2011 | F25: 3.9618945 | G25: 3.6686614 | H25: 3.6627493 | I25: 3.5155466
A26: =A25+1 -> 18 | B26: Georgia (2013) | C26: 2013 | D26: 2013 | K26: 18.7137 | L26: 6.2475 | M26: 6.9733 | N26: 5.8004
A27: =A26+1 -> 19 | B27: Ghana (2012) | C27: 2012-13 | D27: 2013 | F27: 7.5701371 | G27: 7.1996604 | H27: 7.1505083 | I27: 6.2083979
A28: =A27+1 -> 20 | B28: Guatemala (2011) | C28: 2011 | D28: 2011 | F28: 7.145436 | G28: 6.755588 | H28: 6.657371 | I28: 6.105704 | K28: 7.043408 | L28: 6.698902 | M28: 6.552021 | N28: 6.023415
A29: =A28+1 -> 21 | B29: *,** Guinea (2012) | C29: 2012 | D29: 2016
A30: =A29+1 -> 22 | B30: Honduras (2011) | C30: 2011 | D30: 2011 | F30: 15.48048 | G30: 14.05968 | H30: 13.14222 | I30: 11.39818 | K30: 15.3342 | L30: 14.0367 | M30: 13.13607 | N30: 11.38509
A31: =A30+1 -> 23 | B31: Indonesia (2012) | C31: 2012 | D31: 2012 | F31: 5.0454 | G31: 4.9157 | H31: 4.9692 | I31: 4.516526 | K31: 5.0345 | L31: 4.9009 | M31: 4.9422 | N31: 4.497878
A32: =A31+1 -> 24 | B32: Iran (2011) | C32: 2011-12 | D32: 2011-12 | F32: 8.466712 | G32: 5.3479481 | H32: 5.4450818 | I32: 4.6708357
A33: =A32+1 -> 25 | B33: Jordan (2010) | C33: 2010-11 | D33: 2010 | F33: 4.2046877 | G33: 4.0618429 | H33: 4.0094613 | I33: 3.7260417 | K33: 4.445588 | L33: 4.0618429 | M33: 4.0094613 | N33: 3.7260417
A34: =A33+1 -> 26 | B34: *,** Kenya (2015) | C34: 2015-16 | D34: 2015-16
A35: =A34+1 -> 27 | B35: *,** Mali (2014) | C35: 2014 | D35: 2014
A36: =A35+1 -> 28 | B36: Mexico (2010) | C36: 2010 | D36: 2010
B37: Mexico (2012) | C37: 2012 | D37: 2012 | F37: 11.431235 | G37: 8.8518507 | H37: 8.6389662 | I37: 6.0961224 | K37: 11.377033 | L37: 8.8518507 | M37: 8.6389662 | N37: 6.0961224
B38: Mexico (2014) | C38: 2014 | D38: 2014 | F38: 10.458887 | G38: 7.9238839 | H38: 7.7557617 | I38: 5.7980015 | K38: 10.316017 | L38: 7.924 | M38: 7.756 | N38: 5.798
A39: =A36+1 -> 29 | B39: *,** Mongolia (2016) | C39: 2016 | D39: 2016 | K39: 7.8513 | L39: 5.1933 | M39: 5.7006 | N39: 4.9468
A40: =A39+1 -> 30 | B40: *,** Namibia (2009) | C40: 2009 | D40: 2009 -10 | F40: 16.8 | G40: 10.8 | H40: 10.6 | I40: 5.9
A41: =A40+1 -> 31 | B41: Nicaragua (2009) | C41: 2009 | D41: 2009 | F41: 7.9343273 | G41: 7.5762931 | H41: 7.3367374 | I41: 6.1328911 | K41: 7.9837668 | L41: 7.5852134 | M41: 7.3470321 | N41: 6.1241419
A42: =A41+1 -> 32 | B42: *,** Niger (2014) | C42: 2014 -15 | D42: 2014
A43: =A42+1 -> 33 | B43: Panama (2016) | C43: 2016 | D43: 2015 | F43: 15.674275 | G43: 11.517 | H43: 11.087196 | I43: 6.4518952 | K43: 16.498396 | L43: 11.517 | M43: 11.087196 | N43: 6.4518952
A44: =A43+1 -> 34 | B44: Paraguay (2014) | C44: 2014 | D44: 2014 | F44: 12.6973 | G44: 11.8292 | H44: 11.8292 | I44: 11.8292
A45: =A44+1 -> 35 | B45: Peru (2009) | C45: 2009 | D45: 2009
B46: Peru (2011) | C46: 2011 | D46: 2011 | F46: 10.225804 | G46: 9.5328944 | H46: 9.1309182 | I46: 7.0167684 | K46: 10.132871 | L46: 9.5328944 | M46: 9.1309182 | N46: 7.0167684
A47: =A45+1 -> 36 | B47: *,** Poland (2014) | C47: 2014 | D47: 2014 | F47: 8.7987212 | G47: 4.747 | H47: 4.971 | I47: 3.54 | K47: 123.30223 | L47: 4.5674553 | M47: 4.8310699 | N47: 3.3812079
A48: =A47+1 -> 37 | B48: *,** Romania (2016) | C48: 2016 | D48: 2016 | F48: 7.5338657 | G48: 5.3889667 | H48: 5.4702014 | I48: 4.4397081 | K48: 19.069127 | L48: 5.3889667 | M48: 5.4702014 | N48: 4.4397081
A49: =A48+1 -> 38 | B49: Russia (2010) | C49: 2010 | D49: 2010 | F49: 5.966478 | G49: 4.7560163 | H49: 4.8869781 | I49: 4.106844 | K49: 55.61503 | L49: 4.7560163 | M49: 4.8869781 | N49: 4.106844
A50: =A49+1 -> 39 | B50: South Africa (2010) | C50: 2010-11 | D50: 2010 | F50: 198.94814 | G50: 32.697799 | H50: 33.245407 | I50: 12.237052
A51: =A50+1 -> 40 | B51: Sri Lanka (2009) | C51: 2009-10 | D51: 2010 | F51: 4.1015337 | G51: 4.006965 | H51: 4.0534036 | I51: 3.813406
A52: =A51+1 -> 41 | B52: Tanzania (2011) | C52: 2011-12 | D52: 2011-12 | F52: 4.6758195 | G52: 4.372419 | H52: 4.1310688 | I52: 3.8950275
A53: =A52+1 -> 42 | B53: Tunisia (2010) | C53: 2010 | D53: 2010 | F53: 7.7892 | G53: 6.3454 | H53: 5.6458 | I53: 4.7429 | K53: 6.7624 | L53: 6.3454 | M53: 5.6458 | N53: 4.7429
A54: =A53+1 -> 43 | B54: Uganda (2012) | C54: 2012-13 | D54: 2012-13 | F54: 5.6131464 | G54: 5.411 | H54: 5.369 | I54: 4.919
A55: =A54+1 -> 44 | B55: *,** Ukraine (2016) | C55: 2016 | D55: 2016
A56: =A55+1 -> 45 | B56: United States (2011) | C56: 2011 | D56: 2011
A57: =A56+1 -> 46 | B57: Uruguay (2009) | C57: 2009 | D57: 2009 | F57: 12.091199 | G57: 8.5228465 | H57: 8.5123202 | I57: 5.8353824 | K57: 17.94964 | L57: 8.5228465 | M57: 8.5123202 | N57: 5.8353824
A58: =A57+1 -> 47 | B58: Venezuela (2013) | C58: 2013 | D58: 2013 | F58: 6.7092 | G58: 6.253 | H58: 5.9787 | I58: 4.6583 | K58: 7.4642 | L58: 6.2204 | M58: 5.9482 | N58: 4.6116
C61: not applicable; means that the indicator should not be calculated due to methodological reasons or characteristics of the fiscal system.
C63: not calculated; means that the indicator was not calculated by the author/s.
C65: not available; means that the indicator was calculated but it is not publicly available, requests should be put directly to author/s.
C67: not available; means that the indicator is no published on the World Bank's report
B70: * The information published here is from World Bank led CEQ assessments and has not undergone quality control by the CEQ Institute. The information is taken from World Bank Policy Research Working Papers. See References for further detail.
B71: ** At least some information for this CEQ Assessment was extracted directly from World Bank Policy Research Working Papers, Reports, Working Papers (numbered series) and Poverty Assessment.
B72: *** Note that the Market Income (PGT) scenario is an eye-ball estimate only; the precise estimate needs to be confirmed with the Albania team.
B74: Notes
B75: 1. The year represented by the data in parentheses.
B76: 2. Because national and international agencies often update their data series, the information included here may be subject to change.
B77: 3. The letters "C" and "I" indicate that the study used consumption or income data, respectively.
B78: 4. In Armenia, Costa Rica, Iran, Peru, South Africa and Uruguay there are no indirect subsidies.
B79: 5. Bolivia does not have personal income taxes.
B80: 6. In Bolivia, Costa Rica, Ecuador, Honduras, South Africa and Sri Lanka, market income does not include consumption of own production because the data was either not available or not reliable.
B81: 7. For Brazil, the results for the analysis presented here differ from the results published in Higgins and Pereira (2014) because the latter include taxes on services (ISS), on goods and services to finance pensions (CONFINS) and to finance Social Workers (PIS), while the results presented here do not include them. Post publishing the mentioned paper, the authors concluded that the source for these taxes was not reliable.
B82: 8. Gini coefficients for Chile are estimated here using total income and, thus, differ from official figures of inequality which are estimated using monetary income (i.e., official figures exclude owner’s occupied imputed rent).
... B100: Source: CEQ Institute’s Data Center on Fiscal Redistribution. Based on the following Master Workbooks of Results, for United States the source is the publication of Higgins, et al. (2016):
A101: =A8 -> 1 | B101: =(CONCATENATE(B8,": ",'26. Source - CEQ MWBs'!C11)) -> *,** Albania (2015): n.a.
A102: =A9 -> 2 | B102: =(CONCATENATE(B9,": ",'26. Source - CEQ MWBs'!C12)) -> Argentina (2012): Rossignolo, Dario. 2017. “CEQ Master Workbook: Argentina (2012-2013),” CEQ Data Center on Fiscal Redistribution (CEQ Institute, Tulane University). Jun 8, 2018.
A103: =A10 -> 3 | B103: =(CONCATENATE(B10,": ",'26. Source - CEQ MWBs'!C13)) -> Armenia (2011): Younger, Stephen D., Artsvi Khachatryan, Gohar Gyulumyan, Nistha Sinha, and Ulrich Bartsch. 2019. “CEQ Master Workbook: Armenia (2011),” CEQ Data Center on Fiscal Redistribution (CEQ Institute, Tulane University and the World Bank). June 8, 2019.
A104: =A11 -> 4 | B104: =(CONCATENATE(B11,": ",'26. Source - CEQ MWBs'!C14)) -> *,** Belarus (2015): n.a.
A105: =A12 -> 5 | B105: =(CONCATENATE(B12,": ",'26. Source - CEQ MWBs'!C15)) -> Bolivia (2009): Paz Arauco, Veronica, George Gray-Molina, Wilson Jimenez and Ernesto Yañez. 2014. “CEQ Master Workbook: Bolivia (2009),” CEQ Data Center on Fiscal Redistribution (CEQ Institute, Tulane University). September 22, 2014.
A106: =A13 -> 6 | B106: =(CONCATENATE(B13,": ",'26. Source - CEQ MWBs'!C16)) -> Brazil (2008): Higgins, Sean, Claudiney Pereira, and, Maynor Cabrera. 2019. “CEQ Master Workbook: Brazil (2008-2009),” CEQ Data Center on Fiscal Redistribution (CEQ Institute, Tulane University). May 3, 2019.
A107: =A14 -> 7 | B107: =(CONCATENATE(B14,": ",'26. Source - CEQ MWBs'!C17)) -> *,** Burkina Faso (2014): n.a.
A108: =A15 -> 8 | B108: =(CONCATENATE(B15,": ",'26. Source - CEQ MWBs'!C18)) -> Chile (2013): Martinez-Aguilar, Sandra and Eduardo Ortiz-Juarez. 2016. “CEQ Master Workbook: Chile (2013),” CEQ Data Center on Fiscal Redistribution (CEQ Institute, Tulane University and the World Bank). October 7, 2016.
A109: =A16 -> 9 | B109: =(CONCATENATE(B16,": ",'26. Source - CEQ MWBs'!C19)) -> Colombia (2010): Melendez, Marcela and Valentina Martinez. 2019. “CEQ Master Workbook: Colombia (2010),” CEQ Data Center on Fiscal Redistribution (CEQ Institute, Tulane University and Inter-American Development Bank). February 20, 2019.
A110: =A17 -> 0 | B110: =(CONCATENATE(B17,": ",'26. Source - CEQ MWBs'!C20)) -> Colombia (2014): Melendez, Marcela and Valentina Martinez. 2019. “CEQ Master Workbook: Colombia (2014),” CEQ Data Center on Fiscal Redistribution (CEQ Institute, Tulane University and Inter-American Development Bank). February 28, 2019.
A111: =A18 -> 10 | B111: =(CONCATENATE(B18,": ",'26. Source - CEQ MWBs'!C21)) -> *,** Comoros (2014): n.a.
A112: =A19 -> 11 | B112: =(CONCATENATE(B19,": ",'26. Source - CEQ MWBs'!C22)) -> Costa Rica (2010): Sauma, Pablo and Juan Diego Trejos. 2014. “CEQ Master Workbook: Costa Rica (2010),” CEQ Data Center on Fiscal Redistribution (CEQ Institute, Tulane University). February 14, 2014.
... A151: =A58 -> 47 | B151: =(CONCATENATE(B58,": ",'26. Source - CEQ MWBs'!C61)) -> Venezuela (2013): Molina, Emiro. 2016. “CEQ Master Workbook: Venezuela (2012),” CEQ Data Center on Fiscal Redistribution (CEQ Institute, Tulane University). April 5, 2018.

Sheet 8. Inequality - Absolute Gini
A1: Go to Contents
B3: Inequality - Absolute Gini
B4: NOTE: FOR SOURCES AND CITATIONS SEE BOTTOM OF PAGE
B6: Country | C6: Year of survey | D6: Year of budgetary data and fiscal system | F6: Contributory pensions as deferred income | K6: Contributory pensions as government transfer
F7: Market income plus pensions | G7: Disposable income | H7: Consumable income | I7: Final income | K7: Market income | L7: Disposable income | M7: Consumable income | N7: Final income
A8: =A7+1 -> 1 | B8: *,** Albania (2015) | C8: 2015 | D8: 2015
A9: =A8+1 -> 2 | B9: Argentina (2012) | C9: 2012-13 | D9: 2012
A10: =A9+1 -> 3 | B10: Armenia (2011) | C10: 2011 | D10: 2011 | F10: 180942.07 | G10: 166313.06 | H10: 148885.13 | I10: 148422.8 | K10: 201583.73 | L10: 166313.06 | M10: 148885.13 | N10: 148422.8
A11: =A10+1 -> 4 | B11: *,** Belarus (2015) | C11: 2015 | D11: 2016
A12: =A11+1 -> 5 | B12: Bolivia (2009) | C12: 2009 | D12: 2009
A13: =A12+1 -> 6 | B13: Brazil (2008) | C13: 2008-09 | D13: 2009 | F13: 5081 | G13: 4662.4261 | H13: 3945.5521 | I13: 3859.4746 | K13: 4683.9329 | L13: 4662.4261 | M13: 3945.5521 | N13: 3859.4746
A14: =A13+1 -> 7 | B14: *,** Burkina Faso (2014) | C14: 2014 | D14: 2014
A15: =A14+1 -> 8 | B15: Chile (2013) | C15: 2013 | D15: 2013 | F15: 1762031.6 | G15: 1635609.2 | H15: 1464046.2 | I15: 1438479.6 | K15: 1736747 | L15: 1635609.2 | M15: 1464046.2 | N15: 1438479.6
A16: =A15+1 -> 9 | B16: Colombia (2010) | C16: 2010 | D16: 2010 | F16: 3261981.9 | G16: 3077480.2 | H16: 2854182.8 | I16: 2857929.1 | K16: 3027030.5 | L16: 3077480.2 | M16: 2854182.8 | N16: 2857929.1
B17: Colombia (2014) | C17: 2014 | D17: 2014 | F17: 4131852.3 | G17: 4010260.9 | H17: 3751922.5 | I17: 3761519.4 | K17: 3876621.7 | L17: 4010260.9 | M17: 3751922.5 | N17: 3761519.4
A18: =A16+1 -> 10 | B18: *,** Comoros (2014) | C18: 2014
A19: =A18+1 -> 11 | B19: Costa Rica (2010) | C19: 2010 | D19: 2010
A20: =A19+1 -> 12 | B20: *,** Croatia (2014) | C20: 2014 | D20: 2014
A21: =A20+1 -> 13 | B21: Dominican Republic (2006) | C21: 2006-07 | D21: 2013 | F21: 37550.931 | G21: 36539.191 | H21: 33549.502 | I21: 32948.362 | K21: 37296.961 | L21: 36539.191 | M21: 33549.502 | N21: 32948.362
A22: =A21+1 -> 14 | B22: Ecuador (2011) | C22: 2011-12 | D22: 2011 | F22: 99.714133 | G22: 95.778319 | H22: 91.405696 | I22: 88.87393 | K22: 95.979729 | L22: 92.516124 | M22: 88.373176 | N22: 85.903321
A23: =A22+1 -> 15 | B23: *,** Egypt (2015) | C23: 2015 | D23: 2015
A24: =A23+1 -> 16 | B24: El Salvador (2011) | C24: 2011 | D24: 2011 | F24: 731.43916 | G24: 683.94354 | H24: 617.94971 | I24: 619.87303 | K24: 704.24966 | L24: 683.94354 | M24: 617.94971 | N24: 619.87303
A25: =A24+1 -> 17 | B25: Ethiopia (2010) | C25: 2010-11 | D25: 2011
A26: =A25+1 -> 18 | B26: Georgia (2013) | C26: 2013 | D26: 2013 | F26: . | G26: . | H26: . | I26: . | K26: . | L26: . | M26: . | N26: .
A27: =A26+1 -> 19 | B27: Ghana (2012) | C27: 2012-13 | D27: 2013 | F27: 1033.2933 | G27: 957.83362 | H27: 915.11109 | I27: 964.10176
A28: =A27+1 -> 20 | B28: Guatemala (2011) | C28: 2011 | D28: 2011
A29: =A28+1 -> 21 | B29: *,** Guinea (2012) | C29: 2012 | D29: 2016
A30: =A29+1 -> 22 | B30: Honduras (2011) | C30: 2011 | D30: 2011
A31: =A30+1 -> 23 | B31: Indonesia (2012) | C31: 2012 | D31: 2012
A32: =A31+1 -> 24 | B32: Iran (2011) | C32: 2011-12 | D32: 2011-12 | F32: 11157234 | G32: 10833725 | H32: 10562329 | I32: 10577442
A33: =A32+1 -> 25 | B33: Jordan (2010) | C33: 2010-11 | D33: 2010 | F33: 583.00252 | G33: 560.792 | H33: 557.79074 | I33: 584.32002 | K33: 565.58004 | L33: 560.792 | M33: 557.79074 | N33: 584.32002
A34: =A33+1 -> 26 | B34: *,** Kenya (2015) | C34: 2015-16 | D34: 2015-16
A35: =A34+1 -> 27 | B35: *,** Mali (2014) | C35: 2014 | D35: 2014
A36: =A35+1 -> 28 | B36: Mexico (2010) | C36: 2010 | D36: 2010
B37: Mexico (2012) | C37: 2012 | D37: 2012 | F37: 22751.921 | G37: 20219.984 | H37: 19652.225 | I37: 19670.499 | K37: 21511.552 | L37: 20219.984 | M37: 19652.225 | N37: 19670.499
B38: Mexico (2014) | C38: 2014 | D38: 2014 | F38: 23714.484 | G38: 20819.692 | H38: 19975.616 | I38: 20041.344 | K38: 22786.515 | L38: 20819.692 | M38: 19975.616 | N38: 20041.344
A39: =A36+1 -> 29 | B39: *,** Mongolia (2016) | C39: 2016 | D39: 2016
A40: =A39+1 -> 30 | B40: *,** Namibia (2009) | C40: 2009 | D40: 2009 -10
A41: =A40+1 -> 31 | B41: Nicaragua (2009) | C41: 2009 | D41: 2009
A42: =A41+1 -> 32 | B42: *,** Niger (2014) | C42: 2014 -15 | D42: 2014
A43: =A42+1 -> 33 | B43: Panama (2016) | C43: 2016 | D43: 2015 | F43: 3102.867 | G43: 2827.2697 | H43: 2743.2201 | I43: 2698.9824 | K43: 2965.9303 | L43: 2827.2697 | M43: 2743.2201 | N43: 2698.9824
A44: =A43+1 -> 34 | B44: Paraguay (2014) | C44: 2014 | D44: 2014 | F44: 11105822 | G44: 10979092 | H44: 10600746 | I44: 10463888
A45: =A44+1 -> 35 | B45: Peru (2009) | C45: 2009 | D45: 2009
B46: Peru (2011) | C46: 2011 | D46: 2011 | F46: 3538.9278 | G46: 3463.24 | H46: 3259.4128 | I46: 3239.8955 | K46: 3480.334 | L46: 3463.24 | M46: 3259.4128 | N46: 3239.8955
A47: =A45+1 -> 36 | B47: *,** Poland (2014) | C47: 2014 | D47: 2014
A48: =A47+1 -> 37 | B48: *,** Romania (2016) | C48: 2016 | D48: 2016
A49: =A48+1 -> 38 | B49: Russia (2010) | C49: 2010 | D49: 2010 | F49: 53946.715 | G49: 48535.508 | H49: 44877.045 | I49: 44556.993 | K49: 60633.624 | L49: 48535.508 | M49: 44877.045 | N49: 44556.993
A50: =A49+1 -> 39 | B50: South Africa (2010) | C50: 2010-11 | D50: 2010 | F50: . | G50: . | H50: . | I50: . | K50: . | L50: . | M50: . | N50: .
A51: =A50+1 -> 40 | B51: Sri Lanka (2009) | C51: 2009-10 | D51: 2010 | F51: 28952.252 | G51: 29137.221 | H51: 27555.62 | I51: 27626.843
A52: =A51+1 -> 41 | B52: Tanzania (2011) | C52: 2011-12 | D52: 2011-12 | F52: 247637.16 | G52: 218663.91 | H52: 184909.88 | I52: 196684.26
A53: =A52+1 -> 42 | B53: Tunisia (2010) | C53: 2010 | D53: 2010
A54: =A53+1 -> 43 | B54: Uganda (2012) | C54: 2012-13 | D54: 2012-13
A55: =A54+1 -> 44 | B55: *,** Ukraine (2016) | C55: 2016 | D55: 2016
A56: =A55+1 -> 45 | B56: United States (2011) | C56: 2011 | D56: 2011
A57: =A56+1 -> 46 | B57: Uruguay (2009) | C57: 2009 | D57: 2009 | F57: 60860.964 | G57: 53020.423 | H57: 47506.608 | I57: 46375.114 | K57: 63544.479 | L57: 53020.423 | M57: 47506.608 | N57: 46375.114
A58: =A57+1 -> 47 | B58: Venezuela (2013) | C58: 2013 | D58: 2013
C61: not applicable; means that the indicator should not be calculated due to methodological reasons or characteristics of the fiscal system.
C63: not calculated; means that the indicator was not calculated by the author/s.
C65: not available; means that the indicator was calculated but it is not publicly available, requests should be put directly to author/s.
C67: not available; means that the indicator is no published on the World Bank's report
B70: * The information published here is from World Bank led CEQ assessments and has not undergone quality control by the CEQ Institute. The information is taken from World Bank Policy Research Working Papers. See References for further detail.
B71: ** At least some information for this CEQ Assessment was extracted directly from World Bank Policy Research Working Papers, Reports, Working Papers (numbered series) and Poverty Assessment.
B72: *** Note that the Market Income (PGT) scenario is an eye-ball estimate only; the precise estimate needs to be confirmed with the Albania team.
B74: Notes
B75: 1. The year represented by the data in parentheses.
B76: 2. Because national and international agencies often update their data series, the information included here may be subject to change.
B77: 3. The letters "C" and "I" indicate that the study used consumption or income data, respectively.
B78: 4. In Armenia, Costa Rica, Iran, Peru, South Africa and Uruguay there are no indirect subsidies.
B79: 5. Bolivia does not have personal income taxes.
B80: 6. In Bolivia, Costa Rica, Ecuador, Honduras, South Africa and Sri Lanka, market income does not include consumption of own production because the data was either not available or not reliable.
B81: 7. For Brazil, the results for the analysis presented here differ from the results published in Higgins and Pereira (2014) because the latter include taxes on services (ISS), on goods and services to finance pensions (CONFINS) and to finance Social Workers (PIS), while the results presented here do not include them. Post publishing the mentioned paper, the authors concluded that the source for these taxes was not reliable.
B82: 8. Gini coefficients for Chile are estimated here using total income and, thus, differ from official figures of inequality which are estimated using monetary income (i.e., official figures exclude owner’s occupied imputed rent).
... B100: Source: CEQ Institute’s Data Center on Fiscal Redistribution. Based on the following Master Workbooks of Results, for United States the source is the publication of Higgins, et al. (2016):
A101: =A8 -> 1 | B101: =(CONCATENATE(B8,": ",'26. Source - CEQ MWBs'!C11)) -> *,** Albania (2015): n.a.
A102: =A9 -> 2 | B102: =(CONCATENATE(B9,": ",'26. Source - CEQ MWBs'!C12)) -> Argentina (2012): Rossignolo, Dario. 2017. “CEQ Master Workbook: Argentina (2012-2013),” CEQ Data Center on Fiscal Redistribution (CEQ Institute, Tulane University). Jun 8, 2018.
A103: =A10 -> 3 | B103: =(CONCATENATE(B10,": ",'26. Source - CEQ MWBs'!C13)) -> Armenia (2011): Younger, Stephen D., Artsvi Khachatryan, Gohar Gyulumyan, Nistha Sinha, and Ulrich Bartsch. 2019. “CEQ Master Workbook: Armenia (2011),” CEQ Data Center on Fiscal Redistribution (CEQ Institute, Tulane University and the World Bank). June 8, 2019.
A104: =A11 -> 4 | B104: =(CONCATENATE(B11,": ",'26. Source - CEQ MWBs'!C14)) -> *,** Belarus (2015): n.a.
A105: =A12 -> 5 | B105: =(CONCATENATE(B12,": ",'26. Source - CEQ MWBs'!C15)) -> Bolivia (2009): Paz Arauco, Veronica, George Gray-Molina, Wilson Jimenez and Ernesto Yañez. 2014. “CEQ Master Workbook: Bolivia (2009),” CEQ Data Center on Fiscal Redistribution (CEQ Institute, Tulane University). September 22, 2014.
A106: =A13 -> 6 | B106: =(CONCATENATE(B13,": ",'26. Source - CEQ MWBs'!C16)) -> Brazil (2008): Higgins, Sean, Claudiney Pereira, and, Maynor Cabrera. 2019. “CEQ Master Workbook: Brazil (2008-2009),” CEQ Data Center on Fiscal Redistribution (CEQ Institute, Tulane University). May 3, 2019.
A107: =A14 -> 7 | B107: =(CONCATENATE(B14,": ",'26. Source - CEQ MWBs'!C17)) -> *,** Burkina Faso (2014): n.a.
A108: =A15 -> 8 | B108: =(CONCATENATE(B15,": ",'26. Source - CEQ MWBs'!C18)) -> Chile (2013): Martinez-Aguilar, Sandra and Eduardo Ortiz-Juarez. 2016. “CEQ Master Workbook: Chile (2013),” CEQ Data Center on Fiscal Redistribution (CEQ Institute, Tulane University and the World Bank). October 7, 2016.
A109: =A16 -> 9 | B109: =(CONCATENATE(B16,": ",'26. Source - CEQ MWBs'!C19)) -> Colombia (2010): Melendez, Marcela and Valentina Martinez. 2019. “CEQ Master Workbook: Colombia (2010),” CEQ Data Center on Fiscal Redistribution (CEQ Institute, Tulane University and Inter-American Development Bank). February 20, 2019.
A110: =A17 -> 0 | B110: =(CONCATENATE(B17,": ",'26. Source - CEQ MWBs'!C20)) -> Colombia (2014): Melendez, Marcela and Valentina Martinez. 2019. “CEQ Master Workbook: Colombia (2014),” CEQ Data Center on Fiscal Redistribution (CEQ Institute, Tulane University and Inter-American Development Bank). February 28, 2019.
A111: =A18 -> 10 | B111: =(CONCATENATE(B18,": ",'26. Source - CEQ MWBs'!C21)) -> *,** Comoros (2014): n.a.
A112: =A19 -> 11 | B112: =(CONCATENATE(B19,": ",'26. Source - CEQ MWBs'!C22)) -> Costa Rica (2010): Sauma, Pablo and Juan Diego Trejos. 2014. “CEQ Master Workbook: Costa Rica (2010),” CEQ Data Center on Fiscal Redistribution (CEQ Institute, Tulane University). February 14, 2014.
... A151: =A58 -> 47 | B151: =(CONCATENATE(B58,": ",'26. Source - CEQ MWBs'!C61)) -> Venezuela (2013): Molina, Emiro. 2016. “CEQ Master Workbook: Venezuela (2012),” CEQ Data Center on Fiscal Redistribution (CEQ Institute, Tulane University). April 5, 2018.

Sheet 9.Poverty - Headcount ratio P05
A1: Go to Contents
B3: Poverty: Headcount ratio based international poverty lines in 2005 PPP $
B4: NOTE: FOR SOURCES AND CITATIONS SEE BOTTOM OF PAGE
B6: Country | C6: Year of survey | D6: Year of budgetary data and fiscal system | E6: Consumer price index 2005 | F6: Consumer price index 2011 | G6: Consumer price index year of survey | H6: PPP Conversion factor 2005 | I6: PPP Conversion factor 2011 | J6: Poverty line: $1.25 2005PPP/day converted to 2011PPP | K6: Poverty line: $2.5 2005PPP/day converted to 2011PPP | L6: Poverty line: $4 2005PPP/day converted to 2011PPP | N6: Poverty Headcount ratio
N7: Contributory pensions as deferred income | Z7: Contributory pensions as government transfer
N8: Poverty line: $1.25 2005PPP/day | R8: Poverty line: $2.5 2005PPP/day | V8: Poverty line: $4 2005PPP/day | Z8: Poverty line: $1.25 2005PPP/day | AD8: Poverty line: $2.5 2005PPP/day | AH8: Poverty line: $4 2005PPP/day
N9: Market income plus pensions | O9: Disposable income | P9: Consumable income | R9: Market income plus pensions | S9: Disposable income | T9: Consumable income | V9: Market income plus pensions | W9: Disposable income | X9: Consumable income | Z9: Market income | AA9: Disposable income | AB9: Consumable income | AD9: Market income | AE9: Disposable income | AF9: Consumable income | AH9: Market income | AI9: Disposable income | AJ9: Consumable income
A10: =A9+1 -> 1 | B10: *,** Albania (2015) | C10: 2015 | D10: 2015 | E10: 86.675568 | F10: 103.44284 | G10: 111.40497 | H10: 55.653665 | I10: 55.587503 | J10: 1.4935864 | K10: 2.9871728 | L10: 4.7794765 | R10: 0.07515 | S10: 0.048986 | T10: 0.081217 | V10: 0.225838 | W10: 0.212895 | X10: 0.291802 | AD10: 0.2304 | AE10: 0.048986 | AF10: 0.081217 | AI10: 0.212895 | AJ10: 0.291802
A11: =A10+1 -> 2 | B11: Argentina (2012) | C11: 2012-13 | D11: 2012 | G11: 110.61845 | H11: 1.3525982 | I11: 2.768382 | N11: 0.0131584 | O11: 0.0028047 | P11: 0.0045512 | R11: 0.0468899 | S11: 0.0182982 | T11: 0.0302906 | V11: 0.123191 | W11: 0.0727097 | X11: 0.1251874 | Z11: 0.0428835 | AA11: 0.0028047 | AB11: 0.0045512 | AD11: 0.0851461 | AE11: 0.0182982 | AF11: 0.0305623 | AH11: 0.1734772 | AI11: 0.0728372 | AJ11: 0.1252842
A12: =A11+1 -> 3 | B12: Armenia (2011) | C12: 2011 | D12: 2011 | E12: 76.379601 | F12: 107.65001 | G12: 107.65001 | H12: 196.18863 | I12: 183.7796 | J12: 1.8807161 | K12: 3.7614321 | L12: 6.0182914 | N12: 0.13102547 | O12: 0.098267843 | P12: 0.11864206 | R12: 0.31937487 | S12: 0.29684635 | T12: 0.35430746 | V12: 0.56016219 | W12: 0.56070078 | X12: 0.62793082 | Z12: 0.21348542 | AA12: 0.098267843 | AB12: 0.11864206 | AD12: 0.39585907 | AE12: 0.29684635 | AF12: 0.35430746 | AH12: 0.58762044 | AI12: 0.56070078 | AJ12: 0.62793082
A13: =A12+1 -> 4 | B13: *,** Belarus (2015) | C13: 2015 | D13: 2016 | H13: 759.62347 | I13: 0.18324348 | R13: 0.001775915 | V13: 0.0038691682 | Z13: 0.05884519 | AD13: 0.083035542 | AH13: 0.10584152
A14: =A13+1 -> 5 | B14: Bolivia (2009) | C14: 2009 | D14: 2009 | E14: 68.29517 | F14: 109.883 | G14: 97.559484 | H14: 2.5707953 | I14: 2.9061057 | J14: 1.402441 | K14: 2.804882 | L14: 4.4878111 | N14: 0.0996 | O14: 0.083523 | P14: 0.0973 | R14: 0.19604 | S14: 0.17573 | T14: 0.20245 | V14: 0.32488 | W14: 0.30656 | X14: 0.33926 | Z14: 0.10252 | AA14: 0.08352 | AB14: 0.09728 | AD14: 0.2001 | AE14: 0.1757 | AF14: 0.20246 | AH14: 0.33128 | AI14: 0.30656 | AJ14: 0.33926
A15: =A14+1 -> 6 | B15: Brazil (2008) | C15: 2008-09 | D15: 2009 | E15: 79.543671 | F15: 106.63637 | G15: 95.20298 | H15: 1.5713184 | I15: 1.6587826 | J15: 1.2652456 | K15: 2.5304912 | L15: 4.048786 | N15: 0.065500437 | O15: 0.041141782 | P15: 0.053183523 | R15: 0.17172535 | S15: 0.14412839 | T15: 0.17968315 | V15: 0.29488168 | W15: 0.27632963 | X15: 0.32923244 | Z15: 0.10492452 | AA15: 0.041141782 | AB15: 0.053183523 | AD15: 0.22994707 | AE15: 0.14412839 | AF15: 0.17968315 | AH15: 0.35929634 | AI15: 0.27632963 | AJ15: 0.32923244
A16: =A15+1 -> 7 | B16: *,** Burkina Faso (2014) | C16: 2014 | D16: 2014 | E16: 86.925362 | F16: 102.75977 | G16: 106.97589 | H16: 242.41742 | I16: 222.24197 | J16: 1.6118491 | K16: 3.2236982 | L16: 5.1579171 | N16: 0.1352 | O16: 0.1264 | P16: 0.1913 | R16: 0.6398 | S16: 0.6338 | T16: 0.6895 | V16: 0.8508 | W16: 0.85 | X16: 0.875 | Z16: 0.1346 | AA16: 0.1264 | AB16: 0.1913 | AD16: 0.6373 | AE16: 0.6338 | AF16: 0.6895 | AH16: 0.8517 | AI16: 0.85 | AJ16: 0.875
A17: =A16+1 -> 8 | B17: Chile (2013) | C17: 2013 | D17: 2013 | E17: 83.727998 | F17: 103.34032 | G17: 108.4998 | H17: 387.36 | I17: 370.19874 | J17: 1.6143175 | K17: 3.2286349 | L17: 5.1658159 | N17: 0.0076229909 | O17: 0.0023023004 | P17: 0.0025755932 | R17: 0.027769351 | S17: 0.011555428 | T17: 0.013394244 | V17: 0.074626371 | W17: 0.043890148 | X17: 0.056563955 | Z17: 0.0097319117 | AA17: 0.0023023004 | AB17: 0.0025755932 | AD17: 0.034267762 | AE17: 0.011555428 | AF17: 0.013394244 | AH17: 0.089219081 | AI17: 0.043913038 | AJ17: 0.056677943
A18: =A17+1 -> 9 | B18: Colombia (2010) | C18: 2010 | D18: 2010 | E18: 79.671288 | F18: 103.41503 | G18: 100 | H18: 1191.7422 | I18: 1196.9546 | J18: 1.5105293 | K18: 3.0210586 | L18: 4.8336937 | N18: 0.07091563 | O18: 0.059518315 | P18: 0.060102 | R18: 0.20627428 | S18: 0.19623415 | T18: 0.20010745 | V18: 0.36579362 | W18: 0.36911578 | X18: 0.37926598 | Z18: 0.077503463 | AA18: 0.059518315 | AB18: 0.060102 | AD18: 0.2186013 | AE18: 0.19623415 | AF18: 0.20010745 | AH18: 0.38723769 | AI18: 0.36911578 | AJ18: 0.37926598
B19: Colombia (2014) | C19: 2014 | D19: 2014 | E19: 79.671287 | F19: 103.41503 | G19: 111.99978 | H19: 1191.7422 | I19: 1196.9546 | J19: 1.615461 | K19: 3.230922 | L19: 5.1694753 | N19: 0.060589831 | O19: 0.048495375 | P19: 0.048946906 | R19: 0.16940025 | S19: 0.15501918 | T19: 0.15831921 | V19: 0.32011982 | W19: 0.31249526 | X19: 0.31846621 | Z19: 0.067480453 | AA19: 0.048495375 | AB19: 0.048946906 | AD19: 0.18332896 | AE19: 0.15501918 | AF19: 0.15831921 | AH19: 0.34003303 | AI19: 0.31249526 | AJ19: 0.31846621
A20: =A18+1 -> 10 | B20: *,** Comoros (2014) | C20: 2014 | E20: 84.413689 | F20: 101.84267 | H20: 294.41086 | I20: 220.57249 | J20: =IF(D20>2011,1.25*$H20*($G20/$E20)/$I20*($F20/$G20), 1.25*$H20*($G20/$E20)/$I20*($G20/$F20)) -> 0 | K20: =IF(D20>2011,2.5*$H20*($G20/$E20)/$I20*($F20/$G20), 2.5*$H20*($G20/$E20)/$I20*($G20/$F20)) -> 0 | L20: =IF(D20>2011,4*$H20*($G20/$E20)/$I20*($F20/$G20), 4*$H20*($G20/$E20)/$I20*($G20/$F20)) -> 0
A21: =A20+1 -> 11 | B21: Costa Rica (2010) | C21: 2010 | D21: 2010 | E21: 63.470569 | F21: 104.87815 | G21: 100 | H21: 278.9614 | I21: 343.78567 | J21: 1.5237333 | K21: 3.0474665 | L21: 4.8759464 | N21: 0.022 | O21: 0.012 | P21: 0.017 | R21: 0.054 | S21: 0.039 | T21: 0.042 | V21: 0.108 | W21: 0.093 | X21: 0.111 | Z21: 0.028 | AA21: 0.012 | AB21: 0.017 | AD21: 0.068 | AE21: 0.039 | AF21: 0.044 | AH21: 0.131 | AI21: 0.096 | AJ21: 0.117
A22: =A21+1 -> 12 | B22: *,** Croatia (2014) | C22: 2014 | D22: 2014 | E22: 85.835719 | F22: 102.27273 | G22: 107.87402 | H22: 4.4176406 | I22: 4.2908092 | J22: 1.5333913 | K22: 3.0667826 | L22: 4.9068521 | O22: 0.013809333 | P22: 0.022668348 | R22: 0.052 | S22: 0.023608859 | T22: 0.059380242 | W22: 0.053468265 | X22: 0.11505594 | Z22: 0.032949556 | AA22: 0.013809333 | AB22: 0.022668348 | AD22: 0.049892184 | AE22: 0.023608859 | AF22: 0.059380242 | AH22: 0.071177218 | AI22: 0.053468265 | AJ22: 0.11505594
A23: =A22+1 -> 13 | B23: Dominican Republic (2006) | C23: 2006-07 | D23: 2013 | E23: 73.38369 | F23: 108.74036 | G23: 83.79068 | H23: 20.39608 | I23: 20.74103 | J23: 1.8214515 | K23: 3.6429031 | L23: 5.8286449 | N23: 0.05848418 | O23: 0.047682449 | P23: 0.050624152 | R23: 0.20107433 | S23: 0.18952074 | T23: 0.20140992 | V23: 0.37566942 | W23: 0.36583126 | X23: 0.38436664 | Z23: 0.060461775 | AA23: 0.047682449 | AB23: 0.050624152 | AD23: 0.20313325 | AE23: 0.18952074 | AF23: 0.20140992 | AH23: 0.38045282 | AI23: 0.36583126 | AJ23: 0.38436664
A24: =A23+1 -> 14 | B24: Ecuador (2011) | C24: 2011-12 | D24: 2011 | E24: 80.182916 | F24: 104.47453 | G24: 104.47453 | H24: 0.50084672 | I24: 0.54723445 | J24: 1.4906305 | K24: 2.981261 | L24: 4.7700175 | N24: 0.034481222 | O24: 0.018622977 | P24: 0.015843483 | R24: 0.10822856 | S24: 0.077203211 | T24: 0.070332297 | V24: 0.24227293 | W24: 0.21076723 | X24: 0.20422147 | Z24: 0.042526642 | AA24: 0.018637902 | AB24: 0.015843483 | AD24: 0.12153477 | AE24: 0.077419231 | AF24: 0.070464746 | AH24: 0.2621792 | AI24: 0.21297437 | AJ24: 0.20629496
A25: =A24+1 -> 15 | B25: *,** Egypt (2015) | C25: 2015 | D25: 2015 | E25: 57.757275 | F25: 110.05392 | G25: 156.80304 | H25: 2.0223918 | I25: 1.8029792 | J25: =IF(D25>2011,1.25*$H25*($G25/$E25)/$I25*($F25/$G25), 1.25*$H25*($G25/$E25)/$I25*($G25/$F25)) -> 2.6716737 | K25: =IF(D25>2011,2.5*$H25*($G25/$E25)/$I25*($F25/$G25), 2.5*$H25*($G25/$E25)/$I25*($G25/$F25)) -> 5.3433474 | L25: =IF(D25>2011,4*$H25*($G25/$E25)/$I25*($F25/$G25), 4*$H25*($G25/$E25)/$I25*($G25/$F25)) -> 8.5493558
A26: =A25+1 -> 16 | B26: El Salvador (2011) | C26: 2011 | D26: 2011 | E26: 84.240434 | F26: 105.12892 | G26: 105.12892 | H26: 0.5499814 | I26: 0.53077351 | J26: 1.6164057 | K26: 3.2328115 | L26: 5.1724984 | N26: 0.045538211 | O26: 0.030378507 | P26: 0.033913876 | R26: 0.20466075 | S26: 0.18624878 | T26: 0.20166292 | V26: 0.41968444 | W26: 0.40957577 | X26: 0.44389063 | Z26: 0.050390366 | AA26: 0.030378507 | AB26: 0.033913876 | AD26: 0.2145232 | AE26: 0.18624878 | AF26: 0.20166292 | AH26: 0.43045062 | AI26: 0.40957577 | AJ26: 0.44389063
A27: =A26+1 -> 17 | B27: Ethiopia (2010) | C27: 2010-11 | D27: 2011 | E27: 44.845641 | F27: 133.2499 | G27: 100 | H27: 2.7512605 | I27: 5.4386136 | J27: 1.0581967 | K27: 2.1163934 | L27: 3.3862294 | N27: 0.3191441 | O27: 0.30870569 | P27: 0.33239695
A28: =A27+1 -> 18 | B28: Georgia (2013) | C28: 2013 | D28: 2013 | E28: 69.963517 | F28: 108.54293 | G28: 106.9681 | H28: 0.78454581 | I28: 0.84190709 | J28: 1.8071494 | K28: 3.6142988 | L28: 5.7828781 | Z28: 0.20470993 | AA28: 0.059996379 | AB28: 0.093743244 | AD28: 0.39185606 | AE28: 0.23267023 | AF28: 0.30041614
A29: =A28+1 -> 19 | B29: Ghana (2012) | C29: 2012-13 | D29: 2013 | E29: 52.928097 | F29: 108.72684 | G29: 130.06329 | H29: 0.44758219 | I29: 0.78802174 | J29: 1.4584619 | K29: 2.9169239 | L29: 4.6670782 | N29: 0.057563929 | O29: 0.056538082 | P29: 0.065076173 | R29: 0.25759067 | S29: 0.26095938 | T29: 0.27907576 | V29: 0.48093345 | W29: 0.48932386 | X29: 0.5121255
A30: =A29+1 -> 20 | B30: Guatemala (2011) | C30: 2011 | D30: 2011 | E30: 74.573472 | F30: 106.21412 | G30: 106.21412 | H30: 4.540333 | I30: 3.8732392 | J30: 2.0869944 | K30: 4.1739889 | L30: 6.6783822 | N30: 0.05623587 | O30: 0.05157292 | P30: 0.05760734 | R30: 0.33259069 | S30: 0.32318842 | T30: 0.35052606 | V30: 0.58493425 | W30: 0.58263349 | X30: 0.60900584 | Z30: 0.05665734 | AA30: 0.05182694 | AB30: 0.05852474 | AD30: 0.33288139 | AE30: 0.32457341 | AF30: 0.35338534 | AH30: 0.58539303 | AI30: 0.58474494 | AJ30: 0.61324431
A31: =A30+1 -> 21 | B31: *,** Guinea (2012) | C31: 2012 | D31: 2016 | E31: 42.235538 | F31: 121.35046 | G31: 139.8262 | H31: 1479.5656 | I31: 2572.343 | J31: =IF(D31>2011,1.25*$H31*($G31/$E31)/$I31*($F31/$G31), 1.25*$H31*($G31/$E31)/$I31*($G31/$F31)) -> 2.0657547 | K31: =IF(D31>2011,2.5*$H31*($G31/$E31)/$I31*($F31/$G31), 2.5*$H31*($G31/$E31)/$I31*($G31/$F31)) -> 4.1315095 | L31: =IF(D31>2011,4*$H31*($G31/$E31)/$I31*($F31/$G31), 4*$H31*($G31/$E31)/$I31*($G31/$F31)) -> 6.6104152
A32: =A31+1 -> 22 | B32: Honduras (2011) | C32: 2011 | D32: 2011 | E32: 71.982139 | F32: 106.76228 | G32: 106.76228 | H32: 9.662104 | I32: 10.080314 | J32: 1.7770545 | K32: 3.554109 | L32: 5.6865745 | N32: 0.1024404 | O32: 0.0906782 | P32: 0.0934526 | R32: 0.2505869 | S32: 0.2423458 | T32: 0.2519343 | V32: 0.3966696 | W32: 0.3899848 | X32: 0.4162806 | Z32: 0.1042577 | AA32: 0.0906782 | AB32: 0.0934526 | AD32: 0.2505869 | AE32: 0.2423458 | AF32: 0.2519343 | AH32: 0.3989126 | AI32: 0.3902389 | AJ32: 0.4163644
A33: =A32+1 -> 23 | B33: Indonesia (2012) | C33: 2012 | D33: 2012 | E33: 68.684857 | F33: 105.35605 | G33: 109.86476 | H33: 4192.8254 | I33: 4091.9391 | J33: 1.9646542 | K33: 3.9293083 | L33: 6.2868933 | N33: 0.12043262 | O33: 0.10826644 | P33: 0.10537795 | R33: 0.56049046 | S33: 0.55847882 | T33: 0.5476096 | V33: 0.77970595 | W33: 0.78254816 | X33: 0.77767989 | Z33: 0.1255 | AA33: 0.1084 | AB33: 0.1056 | AD33: 0.57 | AE33: 0.5596 | AF33: 0.5487 | AH33: 0.7886 | AI33: 0.7837 | AJ33: 0.7788
A34: =A33+1 -> 24 | B34: Iran (2011) | C34: 2011-12 | D34: 2011-12 | E34: 49.410841 | F34: 120.86934 | G34: 120.86934 | H34: 2714.8227 | I34: 5001.3634 | J34: 1.6598047 | K34: 3.3196093 | L34: 5.3113749 | N34: 0.036164016 | O34: 0.0027047087 | P34: 0.0034472371 | R34: 0.10263171 | S34: 0.021164273 | T34: 0.025896638 | V34: 0.210625 | W34: 0.093882035 | X34: 0.10569595
A35: =A34+1 -> 25 | B35: Jordan (2010) | C35: 2010-11 | D35: 2010 | E35: 75.760664 | F35: 104.16927 | G35: 100 | H35: 0.49294881 | I35: 0.31933158 | J35: 2.4450434 | K35: 4.8900868 | L35: 7.8241389 | N35: 0.0047339573 | O35: 0.0014405247 | P35: 0.0011176206 | R35: 0.052427733 | S35: 0.039867203 | T35: 0.034173445 | V35: 0.25813831 | W35: 0.24612036 | X35: 0.23636245 | Z35: 0.0104 | AA35: 0.0014 | AB35: 0.0011 | AD35: 0.0888 | AE35: 0.0421 | AF35: 0.0377 | AH35: 0.3113 | AI35: 0.2524 | AJ35: 0.2428
A36: =A35+1 -> 26 | B36: *,** Kenya (2015) | C36: 2015-16 | D36: 2015-16 | E36: 55.52692 | F36: 114.02249 | G36: 150.18964 | H36: 32.683746 | I36: 35.429596 | J36: 2.3678957 | K36: 4.7357915 | L36: 7.5772664
A37: =A36+1 -> 27 | B37: *,** Mali (2014) | C37: 2014 | D37: 2014 | E37: 85.8601 | F37: 102.95564 | G37: 108.73074 | H37: 289.67868 | I37: 221.86832 | J37: =IF(D37>2011,1.25*$H37*($G37/$E37)/$I37*($F37/$G37), 1.25*$H37*($G37/$E37)/$I37*($G37/$F37)) -> 1.9569963 | K37: =IF(D37>2011,2.5*$H37*($G37/$E37)/$I37*($F37/$G37), 2.5*$H37*($G37/$E37)/$I37*($G37/$F37)) -> 3.9139926 | L37: =IF(D37>2011,4*$H37*($G37/$E37)/$I37*($F37/$G37), 4*$H37*($G37/$E37)/$I37*($G37/$F37)) -> 6.2623881
A38: =A37+1 -> 28 | B38: Mexico (2010) | C38: 2010 | D38: 2010 | E38: 80.502825 | F38: 103.40738 | G38: 100 | H38: 7.6483314 | I38: 8.940212 | J38: 1.284595 | K38: 2.5691901 | L38: 4.1107041 | N38: 0.049651 | O38: 0.0328232 | P38: 0.0322718 | R38: 0.1256087 | S38: 0.1068438 | T38: 0.1066049 | V38: 0.2468308 | W38: 0.2314823 | X38: 0.2382034 | Z38: 0.0529022 | AA38: 0.0328232 | AB38: 0.0320565 | AD38: 0.1331496 | AE38: 0.1068438 | AF38: 0.1065708 | AH38: 0.2601003 | AI38: 0.2314823 | AJ38: 0.2376067
B39: Mexico (2012) | C39: 2012 | D39: 2012 | E39: 80.502823 | F39: 103.40738 | G39: 107.65898 | H39: 7.6483312 | I39: 8.9402122 | J39: 1.3736285 | K39: 2.747257 | L39: 4.3956112 | N39: 0.048783245 | O39: 0.020698221 | P39: 0.018930441 | R39: 0.13045304 | S39: 0.10173278 | T39: 0.099293573 | V39: 0.26228418 | W39: 0.2381871 | X39: 0.23601468 | Z39: 0.051658784 | AA39: 0.020698221 | AB39: 0.018930441 | AD39: 0.13876194 | AE39: 0.10173278 | AF39: 0.099293573 | AH39: 0.27555074 | AI39: 0.2381871 | AJ39: 0.23601468
B40: Mexico (2014) | C40: 2014 | D40: 2014 | E40: 80.502824 | F40: 103.40738 | G40: 116.24798 | H40: 7.6483314 | I40: 8.9402122 | J40: 1.3736285 | K40: 2.7472571 | L40: 4.3956113 | N40: 0.050469954 | O40: 0.021606119 | P40: 0.021552568 | R40: 0.13104548 | S40: 0.097048644 | T40: 0.099214919 | V40: 0.26880491 | W40: 0.25143076 | X40: 0.25890578 | Z40: 0.053379383 | AA40: 0.021606119 | AB40: 0.021552568 | AD40: 0.14102354 | AE40: 0.097048644 | AF40: 0.099214919 | AH40: 0.2833296 | AI40: 0.25143076 | AJ40: 0.25890578
A41: =A38+1 -> 29 | B41: *,** Mongolia (2016) | C41: 2016 | D41: 2016 | E41: 57.265934 | F41: 108.40917 | G41: 165.50894 | H41: 522.49286 | I41: 590.3299 | J41: =IF(D41>2011,1.25*$H41*($G41/$E41)/$I41*($F41/$G41), 1.25*$H41*($G41/$E41)/$I41*($G41/$F41)) -> 2.0944272 | K41: =IF(D41>2011,2.5*$H41*($G41/$E41)/$I41*($F41/$G41), 2.5*$H41*($G41/$E41)/$I41*($G41/$F41)) -> 4.1888543 | L41: =IF(D41>2011,4*$H41*($G41/$E41)/$I41*($F41/$G41), 4*$H41*($G41/$E41)/$I41*($G41/$F41)) -> 6.7021669
A42: =A41+1 -> 30 | B42: *,** Namibia (2009) | C42: 2009 | D42: 2009 -10 | E42: 71.405037 | F42: 105.00559 | G42: 100 | H42: 5.0639524 | I42: 5.130702 | J42: =IF(D42>2011,1.25*$H42*($G42/$E42)/$I42*($F42/$G42), 1.25*$H42*($G42/$E42)/$I42*($G42/$F42)) -> 1.8142888 | K42: =IF(D42>2011,2.5*$H42*($G42/$E42)/$I42*($F42/$G42), 2.5*$H42*($G42/$E42)/$I42*($G42/$F42)) -> 3.6285775 | L42: =IF(D42>2011,4*$H42*($G42/$E42)/$I42*($F42/$G42), 4*$H42*($G42/$E42)/$I42*($G42/$F42)) -> 5.805724
A43: =A42+1 -> 31 | B43: Nicaragua (2009) | C43: 2009 | D43: 2009 | E43: 62.929181 | F43: 108.08239 | G43: 94.827057 | H43: 7.297259 | I43: 9.1600754 | J43: 1.3165224 | K43: 2.6330448 | L43: 4.2128717 | N43: 0.066519903 | O43: 0.067624533 | P43: 0.068257236 | R43: 0.27021612 | S43: 0.26843959 | T43: 0.28141019 | V43: 0.50146183 | W43: 0.50669186 | X43: 0.52546866 | Z43: 0.068969548 | AA43: 0.06766876 | AB43: 0.068523464 | AD43: 0.27341745 | AE43: 0.27141267 | AF43: 0.28515889 | AH43: 0.50788824 | AI43: 0.50923291 | AJ43: 0.52807908
A44: =A43+1 -> 32 | B44: *,** Niger (2014) | C44: 2014 -15 | D44: 2014 | E44: 88.526352 | F44: 102.94238 | G44: 104.80234 | H44: 267.33093 | I44: 228.75316 | J44: =IF(D44>2011,1.25*$H44*($G44/$E44)/$I44*($F44/$G44), 1.25*$H44*($G44/$E44)/$I44*($G44/$F44)) -> 1.6986885 | K44: =IF(D44>2011,2.5*$H44*($G44/$E44)/$I44*($F44/$G44), 2.5*$H44*($G44/$E44)/$I44*($G44/$F44)) -> 3.3973771 | L44: =IF(D44>2011,4*$H44*($G44/$E44)/$I44*($F44/$G44), 4*$H44*($G44/$E44)/$I44*($G44/$F44)) -> 5.4358033
A45: =A44+1 -> 33 | B45: Panama (2016) | C45: 2016 | D45: 2015 | E45: 81.28521 | F45: 105.8758 | G45: 120.52139 | H45: 0.61135751 | I45: 0.55340803 | J45: 1.798643 | K45: 3.5972861 | L45: 5.7556577 | N45: 0.0545638 | O45: 0.026932677 | P45: 0.026341801 | R45: 0.1214236 | S45: 0.09319247 | T45: 0.091756761 | V45: 0.20466962 | W45: 0.17825729 | X45: 0.17627079 | Z45: 0.060229257 | AA45: 0.026932677 | AB45: 0.026341801 | AD45: 0.13257261 | AE45: 0.09319247 | AF45: 0.091756761 | AH45: 0.21570395 | AI45: 0.17825729 | AJ45: 0.17627079
A46: =A45+1 -> 34 | B46: Paraguay (2014) | C46: 2014 | D46: 2014 | E46: 71.354743 | F46: 108.25397 | G46: 121.04097 | H46: 2127.7958 | I46: 2309.43 | J46: 1.7472544 | K46: 3.4945088 | L46: 5.5912141 | N46: 0.019271281 | O46: 0.010264429 | P46: 0.010264429 | R46: 0.073355904 | S46: 0.060453323 | T46: 0.061053574 | V46: 0.16308036 | W46: 0.14549582 | X46: 0.14637629
A47: =A46+1 -> 35 | B47: Peru (2009) | C47: 2009 | D47: 2009 | E47: 87.125377 | F47: 103.36931 | G47: 98.494685 | H47: 1.6534499 | I47: 1.568639 | J47: 1.4192776 | K47: 2.8385552 | L47: 4.5416883 | R47: 0.1515 | S47: 0.1404 | T47: 0.1448 | V47: 0.2857 | W47: 0.278 | X47: 0.2869 | AD47: 0.1545 | AE47: 0.1405 | AF47: 0.145 | AH47: 0.2925 | AI47: 0.2783 | AJ47: 0.2874
B48: Peru (2011) | C48: 2011 | D48: 2011 | E48: 87.125374 | F48: 103.36931 | G48: 103.36931 | H48: 1.6534499 | I48: 1.568639 | J48: 1.5632377 | K48: 3.1264753 | L48: 5.0023605 | N48: 0.043193089 | O48: 0.034605108 | P48: 0.035711421 | R48: 0.13852388 | S48: 0.13226854 | T48: 0.13531933 | V48: 0.25784328 | W48: 0.25634279 | X48: 0.26366254 | Z48: 0.043643482 | AA48: 0.034605108 | AB48: 0.035711421 | AD48: 0.14094222 | AE48: 0.13226854 | AF48: 0.13531933 | AH48: 0.26535647 | AI48: 0.25634279 | AJ48: 0.26366254
A49: =A47+1 -> 36 | B49: *,** Poland (2014) | C49: 2014 | D49: 2014 | E49: 86.884388 | F49: 104.2394 | G49: 109.08024 | H49: 2.1335834 | I49: 1.920205 | J49: 1.6663345 | K49: 3.3326691 | L49: 5.3322705 | N49: 0.046917658 | O49: 0.012661768 | P49: 0.016383905 | R49: 0.064 | S49: 0.017 | T49: 0.025 | V49: 0.087578145 | W49: 0.029545089 | X49: 0.045447826 | Z49: 0.14478084 | AA49: 0.013301135 | AB49: 0.018433596 | AD49: 0.18994995 | AE49: 0.018944325 | AF49: 0.028728881 | AH49: 0.24637147 | AI49: 0.034937638 | AJ49: 0.057950925
A50: =A49+1 -> 37 | B50: *,**Romania (2016) | C50: 2016 | D50: 2016 | E50: 74.093498 | F50: 105.78925 | G50: 112.44076 | H50: 1.7119983 | I50: 1.8589569 | J50: =IF(D50>2011,1.25*$H50*($G50/$E50)/$I50*($F50/$G50), 1.25*$H50*($G50/$E50)/$I50*($G50/$F50)) -> 1.6436353 | K50: =IF(D50>2011,2.5*$H50*($G50/$E50)/$I50*($F50/$G50), 2.5*$H50*($G50/$E50)/$I50*($G50/$F50)) -> 3.2872706 | L50: =IF(D50>2011,4*$H50*($G50/$E50)/$I50*($F50/$G50), 4*$H50*($G50/$E50)/$I50*($G50/$F50)) -> 5.259633
A51: =A50+1 -> 38 | B51: Russia (2010) | C51: 2010 | D51: 2010 | E51: 61.449009 | F51: 108.44047 | G51: 100 | H51: 13.390844 | I51: 16.769129 | J51: 1.4979633 | K51: 2.9959267 | L51: 4.7934827 | N51: 0.023824439 | O51: 0.013612787 | P51: 0.01424384 | R51: 0.038140535 | S51: 0.025242929 | T51: 0.028950786 | V51: 0.06147987 | W51: 0.043637819 | X51: 0.050897425 | Z51: 0.12676326 | AA51: 0.013612787 | AB51: 0.01424384 | AD51: 0.16208151 | AE51: 0.025242929 | AF51: 0.028950786 | AH51: 0.20483517 | AI51: 0.043637819 | AJ51: 0.050897425
A52: =A51+1 -> 39 | B52: South Africa (2010) | C52: 2010-11 | D52: 2010 | E52: 74.256773 | F52: 105.01716 | G52: 105.01716 | H52: 4.5716545 | I52: 5.0675346 | J52: 1.5948171 | K52: 3.1896342 | L52: 5.1034148 | N52: 0.37041253 | O52: 0.16142416 | P52: 0.21237981 | R52: 0.49291383 | S52: 0.38749495 | T52: 0.44089823 | V52: 0.57495641 | W52: 0.52887407 | X52: 0.57329036
A53: =A52+1 -> 40 | B53: Sri Lanka (2009) | C53: 2009-10 | D53: 2010 | E53: 58.251419 | F53: 106.71677 | G53: 94.146317 | H53: 40.039497 | I53: 42.218933 | J53: 1.6902808 | K53: 3.3805616 | L53: 5.4088986 | N53: 0.054208743 | O53: 0.038580621 | P53: 0.052643169 | R53: 0.40925739 | S53: 0.38647691 | T53: 0.43718169 | V53: 0.73581483 | W53: 0.71872481 | X53: 0.75062597
A54: =A53+1 -> 41 | B54: Tanzania (2011) | C54: 2011-12 | D54: 2011-12 | E54: 66.33255 | F54: 112.69097 | G54: 112.69097 | H54: 482.45093 | I54: 585.52039 | J54: 1.7497805 | K54: 3.4995609 | L54: 5.5992975 | N54: 0.33437317 | O54: 0.33341255 | P54: 0.4062818 | R54: 0.77198065 | S54: 0.78147598 | T54: 0.8344785 | V54: 0.91121266 | W54: 0.92325203 | X54: 0.94768986
A55: =A54+1 -> 42 | B55: Tunisia (2010) | C55: 2010 | D55: 2010 | E55: 84.166019 | F55: 103.54403 | G55: 100 | H55: 0.69612007 | I55: 0.69653375 | J55: 1.4334751 | K55: 2.8669502 | L55: 4.5871203 | N55: 0.0052 | O55: 0.0034 | P55: 0.0024 | R55: 0.0503 | S55: 0.0461 | T55: 0.0376 | V55: 0.1427 | W55: 0.1489 | X55: 0.1466 | Z55: 0.0052 | AA55: 0.0034 | AB55: 0.0024 | AD55: 0.0528 | AE55: 0.0461 | AF55: 0.0376 | AH55: 0.1528 | AI55: 0.1489 | AJ55: 0.1466
A56: =A55+1 -> 43 | B56: Uganda (2012) | C56: 2012-13 | D56: 2012-13 | E56: 66.678946 | F56: 116.56435 | G56: 137.78626 | H56: 744.61789 | I56: 946.89042 | J56: 1.7183862 | K56: 3.4367724 | L56: 5.4988358 | N56: 0.17951709 | O56: 0.17724734 | P56: 0.18074301 | R56: 0.59816221 | S56: 0.60025451 | T56: 0.60832467 | V56: 0.81027743 | W56: 0.81439274 | X56: 0.82017004
A57: =A56+1 -> 44 | B57: *,** Ukraine (2016) | C57: 2016 | D57: 2016 | E57: 51.202007 | F57: 107.95573 | G57: 205.61224 | H57: 1.7091367 | I57: 3.3112316 | J57: =IF(D57>2011,1.25*$H57*($G57/$E57)/$I57*($F57/$G57), 1.25*$H57*($G57/$E57)/$I57*($G57/$F57)) -> 1.3603666 | K57: =IF(D57>2011,2.5*$H57*($G57/$E57)/$I57*($F57/$G57), 2.5*$H57*($G57/$E57)/$I57*($G57/$F57)) -> 2.7207333 | L57: =IF(D57>2011,4*$H57*($G57/$E57)/$I57*($F57/$G57), 4*$H57*($G57/$E57)/$I57*($G57/$F57)) -> 4.3531732
A58: =A57+1 -> 45 | B58: United States (2011) | C58: 2011 | D58: 2011 | E58: 89.560532 | F58: 103.15684 | G58: 103.15684 | H58: 1 | I58: 1 | J58: 1.4397642 | K58: 2.8795285 | L58: 4.6072455
A59: =A58+1 -> 46 | B59: Uruguay (2009) | C59: 2009 | D59: 2009 | E59: 70.543804 | F59: 108.09283 | G59: 93.721846 | H59: 15.310342 | I59: 16.42385 | J59: 1.3422884 | K59: 2.6845768 | L59: 4.2953229 | N59: 0.029114851 | O59: 0.0024024303 | P59: 0.0036896839 | R59: 0.083151595 | S59: 0.034472816 | T59: 0.047658278 | V59: 0.16537338 | W59: 0.12195357 | X59: 0.15715788 | Z59: 0.061702796 | AA59: 0.0024024303 | AB59: 0.0036896839 | AD59: 0.13797431 | AE59: 0.034472816 | AF59: 0.047658278 | AH59: 0.22494182 | AI59: 0.12195357 | AJ59: 0.15715788
A60: =A59+1 -> 47 | B60: Venezuela (2013) | C60: 2013 | D60: 2013 | E60: 34 | F60: 127.1 | G60: 213.3 | H60: 1.2511222 | I60: 2.9150053 | J60: 2.0055663 | K60: 4.0111326 | L60: 6.4178122 | N60: 0.0442 | O60: 0.0314 | P60: 0.0283 | R60: 0.1634 | S60: 0.1522 | T60: 0.1503 | V60: 0.3397 | W60: 0.3385 | X60: 0.3465 | Z60: 0.0685 | AA60: 0.0317 | AB60: 0.0284 | AD60: 0.1989 | AE60: 0.1544 | AF60: 0.1529 | AH60: 0.384 | AI60: 0.3449 | AJ60: 0.355
C63: not applicable; means that the indicator should not be calculated due to methodological reasons or characteristics of the fiscal system.
C65: not calculated; means that the indicator was not calculated by the author/s.
C67: not available; means that the indicator was calculated but it is not publicly available, requests should be put directly to author/s.
C69: omitted for being unreliable data
C71: not available; means that the indicator is no published on the World Bank's report
B74: * The information published here is from World Bank led CEQ assessments and has not undergone quality control by the CEQ Institute. The information is taken from World Bank Policy Research Working Papers. See References for further detail.
B75: ** At least some information for this CEQ Assessment was extracted directly from World Bank Policy Research Working Papers, Reports, Working Papers (numbered series) and Poverty Assessment.
B77: Notes
B78: 1. The year represented by the data in parentheses.
B79: 2. Because national and international agencies often update their data series, the information included here may be subject to change.
B80: 3. The letters "C" and "I" indicate that the study used consumption or income data, respectively.
B81: 4. In Armenia, Costa Rica, Iran, Peru, South Africa and Uruguay there are no indirect subsidies.
B82: 5. Bolivia does not have personal income taxes.
B83: 6. In Bolivia, Costa Rica, Ecuador, Honduras, South Africa and Sri Lanka, market income does not include consumption of own production because the data was either not available or not reliable.
B84: 7. For Brazil, the results for the analysis presented here differ from the results published in Higgins and Pereira (2014) because the latter include taxes on services (ISS), on goods and services to finance pensions (CONFINS) and to finance Social Workers (PIS), while the results presented here do not include them. Post publishing the mentioned paper, the authors concluded that the source for these taxes was not reliable.
B85: 8. Gini coefficients for Chile are estimated here using total income and, thus, differ from official figures of inequality which are estimated using monetary income (i.e., official figures exclude owner’s occupied imputed rent).
B86: 9. For Dominican Republic, the study analyzes the effects of fiscal policy in 2013, but the household income and expenditure survey dates back to 2006-07.
... B107: Source: CEQ Institute’s Data Center on Fiscal Redistribution. Based on the following Master Workbooks of Results, for United States the source is the publication of Higgins, et al. (2016):
A108: =A10 -> 1 | B108: ='5.Inequality - Gini coefficient'!B101 -> *,** Albania (2015): n.a.
A109: =A11 -> 2 | B109: ='5.Inequality - Gini coefficient'!B102 -> Argentina (2012): Rossignolo, Dario. 2017. “CEQ Master Workbook: Argentina (2012-2013),” CEQ Data Center on Fiscal Redistribution (CEQ Institute, Tulane University). Jun 8, 2018.
A110: =A12 -> 3 | B110: ='5.Inequality - Gini coefficient'!B103 -> Armenia (2011): Younger, Stephen D., Artsvi Khachatryan, Gohar Gyulumyan, Nistha Sinha, and Ulrich Bartsch. 2019. “CEQ Master Workbook: Armenia (2011),” CEQ Data Center on Fiscal Redistribution (CEQ Institute, Tulane University and the World Bank). June 8, 2019.
A111: =A13 -> 4 | B111: ='5.Inequality - Gini coefficient'!B104 -> *,** Belarus (2015): n.a.
A112: =A14 -> 5 | B112: ='5.Inequality - Gini coefficient'!B105 -> Bolivia (2009): Paz Arauco, Veronica, George Gray-Molina, Wilson Jimenez and Ernesto Yañez. 2014. “CEQ Master Workbook: Bolivia (2009),” CEQ Data Center on Fiscal Redistribution (CEQ Institute, Tulane University). September 22, 2014.
A113: =A15 -> 6 | B113: ='5.Inequality - Gini coefficient'!B106 -> Brazil (2008): Higgins, Sean, Claudiney Pereira, and, Maynor Cabrera. 2019. “CEQ Master Workbook: Brazil (2008-2009),” CEQ Data Center on Fiscal Redistribution (CEQ Institute, Tulane University). May 3, 2019.
A114: =A16 -> 7 | B114: ='5.Inequality - Gini coefficient'!B107 -> *,** Burkina Faso (2014): n.a.
A115: =A17 -> 8 | B115: ='5.Inequality - Gini coefficient'!B108 -> Chile (2013): Martinez-Aguilar, Sandra and Eduardo Ortiz-Juarez. 2016. “CEQ Master Workbook: Chile (2013),” CEQ Data Center on Fiscal Redistribution (CEQ Institute, Tulane University and the World Bank). October 7, 2016.
A116: =A18 -> 9 | B116: ='5.Inequality - Gini coefficient'!B109 -> Colombia (2010): Melendez, Marcela and Valentina Martinez. 2019. “CEQ Master Workbook: Colombia (2010),” CEQ Data Center on Fiscal Redistribution (CEQ Institute, Tulane University and Inter-American Development Bank). February 20, 2019.
A117: =A19 -> 0 | B117: ='5.Inequality - Gini coefficient'!B110 -> Colombia (2014): Melendez, Marcela and Valentina Martinez. 2019. “CEQ Master Workbook: Colombia (2014),” CEQ Data Center on Fiscal Redistribution (CEQ Institute, Tulane University and Inter-American Development Bank). February 28, 2019.
A118: =A20 -> 10 | B118: ='5.Inequality - Gini coefficient'!B111 -> *,** Comoros (2014): n.a.
A119: =A21 -> 11 | B119: ='5.Inequality - Gini coefficient'!B112 -> Costa Rica (2010): Sauma, Pablo and Juan Diego Trejos. 2014. “CEQ Master Workbook: Costa Rica (2010),” CEQ Data Center on Fiscal Redistribution (CEQ Institute, Tulane University). February 14, 2014.
... A158: =A60 -> 47 | B158: ='5.Inequality - Gini coefficient'!B151 -> Venezuela (2013): Molina, Emiro. 2016. “CEQ Master Workbook: Venezuela (2012),” CEQ Data Center on Fiscal Redistribution (CEQ Institute, Tulane University). April 5, 2018.

Sheet 10.Poverty -Headcount ratio P11
A1: Go to Contents
B3: Poverty: Headcount ratio based on international poverty lines in 2011 PPP $
B4: NOTE: FOR SOURCES AND CITATIONS SEE BOTTOM OF PAGE
B6: Country | C6: Year of survey | D6: Year of budgetary data and fiscal system | E6: Consumer price index 2005 | F6: Consumer price index 2011 | G6: Consumer price index year of survey | H6: PPP Conversion factor 2005 | I6: PPP Conversion factor 2011 | K6: Poverty Headcount ratio
K7: Contributory pensions as deferred income | W7: Contributory pensions as government transfer
K8: Poverty line: $1.9 2011PPP/day | O8: Poverty line: $3.2 2011PPP/day | S8: Poverty line: $5.5 2011PPP/day | W8: Poverty line: $1.9 2011PPP/day | AA8: Poverty line: $3.2 2011PPP/day | AE8: Poverty line: $5.5 2011PPP/day
K9: Market income plus pensions | L9: Disposable income | M9: Consumable income | O9: Market income plus pensions | P9: Disposable income | Q9: Consumable income | S9: Market income plus pensions | T9: Disposable income | U9: Consumable income | W9: Market income | X9: Disposable income | Y9: Consumable income | AA9: Market income | AB9: Disposable income | AC9: Consumable income | AE9: Market income | AF9: Disposable income | AG9: Consumable income
A10: =A9+1 -> 1 | B10: *,** Albania (2015) | C10: 2015 | D10: 2015 | E10: 86.675568 | F10: 103.44284 | G10: 111.40497 | H10: 55.653665 | I10: 55.587503
A11: =A10+1 -> 2 | B11: Argentina (2012) | C11: 2012-13 | D11: 2012 | G11: 110.61845 | H11: 1.3525982 | I11: 2.768382
A12: =A11+1 -> 3 | B12: Armenia (2011) | C12: 2011 | D12: 2011 | E12: 76.379601 | F12: 107.65001 | G12: 107.65001 | H12: 196.18863 | I12: 183.7796 | K12: 0.13211965 | L12: 0.099064172 | M12: 0.11966967 | O12: 0.25531936 | P12: 0.22659738 | Q12: 0.27591709 | S12: 0.50757824 | T12: 0.50946791 | U12: 0.5739034 | W12: 0.21503819 | X12: 0.099064172 | Y12: 0.11966967 | AA12: 0.34383564 | AB12: 0.22659738 | AC12: 0.27591709 | AE12: 0.54756477 | AF12: 0.50946791 | AG12: 0.5739034
A13: =A12+1 -> 4 | B13: *,** Belarus (2015) | C13: 2015 | D13: 2016 | H13: 759.62347 | I13: 0.18324348
A14: =A13+1 -> 5 | B14: Bolivia (2009) | C14: 2009 | D14: 2009 | E14: 68.29517 | F14: 109.883 | G14: 97.559484 | H14: 2.5707953 | I14: 2.9061057
A15: =A14+1 -> 6 | B15: Brazil (2008) | C15: 2008-09 | D15: 2009 | E15: 79.543671 | F15: 106.63637 | G15: 95.20298 | H15: 1.5713184 | I15: 1.6587826 | K15: 0.084076308 | L15: 0.0580028 | M15: 0.075140489 | O15: 0.17329953 | P15: 0.14536958 | Q15: 0.18153755 | S15: 0.32203757 | T15: 0.30467015 | U15: 0.35930323 | W15: 0.12909816 | X15: 0.0580028 | Y15: 0.075140489 | AA15: 0.23162424 | AB15: 0.14536958 | AC15: 0.18153755 | AE15: 0.38645003 | AF15: 0.30467015 | AG15: 0.35930323
A16: =A15+1 -> 7 | B16: *,** Burkina Faso (2014) | C16: 2014 | D16: 2014 | E16: 86.925362 | F16: 102.75977 | G16: 106.97589 | H16: 242.41742 | I16: 222.24197
A17: =A16+1 -> 8 | B17: Chile (2013) | C17: 2013 | D17: 2013 | E17: 83.727998 | F17: 103.34032 | G17: 108.4998 | H17: 387.36 | I17: 370.19874 | K17: 0.0098934187 | L17: 0.0033120233 | M17: 0.0036202021 | O17: 0.027446337 | P17: 0.011221462 | Q17: 0.013225029 | S17: 0.084873633 | T17: 0.053164253 | U17: 0.067531827 | W17: 0.012797879 | X17: 0.0033120233 | Y17: 0.0036202021 | AA17: 0.033789036 | AB17: 0.011221462 | AC17: 0.013225029 | AE17: 0.10074206 | AF17: 0.053187144 | AG17: 0.067644424
A18: =A17+1 -> 9 | B18: Colombia (2010) | C18: 2010 | D18: 2010 | E18: 79.671288 | F18: 103.41503 | G18: 100 | H18: 1191.7422 | I18: 1196.9546 | K18: 0.092493597 | L18: 0.082351078 | M18: 0.083489481 | O18: 0.20425278 | P18: 0.19390612 | Q18: 0.19755381 | S18: 0.39280098 | T18: 0.39518562 | U18: 0.40779307 | W18: 0.10015806 | X18: 0.082351078 | Y18: 0.083489481 | AA18: 0.2166166 | AB18: 0.19390612 | AC18: 0.19755381 | AE18: 0.41467992 | AF18: 0.39518562 | AG18: 0.40779307
B19: Colombia (2014) | C19: 2014 | D19: 2014 | E19: 79.671287 | F19: 103.41503 | G19: 111.99978 | H19: 1191.7422 | I19: 1196.9546 | K19: 0.073524429 | L19: 0.06271758 | M19: 0.063969236 | O19: 0.16711444 | P19: 0.15262681 | Q19: 0.15533892 | S19: 0.34018322 | T19: 0.33386595 | U19: 0.34308646 | W19: 0.081106097 | X19: 0.06271758 | Y19: 0.063969236 | AA19: 0.18115602 | AB19: 0.15262681 | AC19: 0.15533892 | AE19: 0.36095913 | AF19: 0.33386595 | AG19: 0.34308646
A20: =A18+1 -> 10 | B20: *,** Comoros (2014) | C20: 2014 | E20: 84.413689 | F20: 101.84267 | H20: 294.41086 | I20: 220.57249
A21: =A20+1 -> 11 | B21: Costa Rica (2010) | C21: 2010 | D21: 2010 | E21: 63.470569 | F21: 104.87815 | G21: 100 | H21: 278.9614 | I21: 343.78567
A22: =A21+1 -> 12 | B22: *,** Croatia (2014) | C22: 2014 | D22: 2014 | E22: 85.835719 | F22: 102.27273 | G22: 107.87402 | H22: 4.4176406 | I22: 4.2908092
A23: =A22+1 -> 13 | B23: Dominican Republic (2006) | C23: 2006-07 | D23: 2013 | E23: 73.38369 | F23: 108.74036 | G23: 83.79068 | H23: 20.39608 | I23: 20.74103 | K23: 0.063816389 | L23: 0.054462607 | M23: 0.056120746 | O23: 0.16811241 | P23: 0.15342891 | Q23: 0.1635691 | S23: 0.35185857 | T23: 0.34225248 | U23: 0.35937413 | W23: 0.065916461 | X23: 0.054462607 | Y23: 0.056120746 | AA23: 0.17051516 | AB23: 0.15342891 | AC23: 0.1635691 | AE23: 0.35647953 | AF23: 0.34225248 | AG23: 0.35937413
A24: =A23+1 -> 14 | B24: Ecuador (2011) | C24: 2011-12 | D24: 2011 | E24: 80.182916 | F24: 104.47453 | G24: 104.47453 | H24: 0.50084672 | I24: 0.54723445
A25: =A24+1 -> 15 | B25: *,** Egypt (2015) | C25: 2015 | D25: 2015 | E25: 57.757275 | F25: 110.05392 | G25: 156.80304 | H25: 2.0223918 | I25: 1.8029792
A26: =A25+1 -> 16 | B26: El Salvador (2011) | C26: 2011 | D26: 2011 | E26: 84.240434 | F26: 105.12892 | G26: 105.12892 | H26: 0.5499814 | I26: 0.53077351 | K26: 0.069924272 | L26: 0.050834018 | M26: 0.055265066 | O26: 0.20056804 | P26: 0.18235414 | Q26: 0.19779259 | S26: 0.44971093 | T26: 0.44432172 | U26: 0.48023581 | W26: 0.075199788 | X26: 0.050834018 | Y26: 0.055265066 | AA26: 0.21063451 | AB26: 0.18235414 | AC26: 0.19779259 | AE26: 0.46117922 | AF26: 0.44432172 | AG26: 0.48023581
A27: =A26+1 -> 17 | B27: Ethiopia (2010) | C27: 2010-11 | D27: 2011 | E27: 44.845641 | F27: 133.2499 | G27: 100 | H27: 2.7512605 | I27: 5.4386136
A28: =A27+1 -> 18 | B28: Georgia (2013) | C28: 2013 | D28: 2013 | E28: 69.963517 | F28: 108.54293 | G28: 106.9681 | H28: 0.78454581 | I28: 0.84190709
A29: =A28+1 -> 19 | B29: Ghana (2012) | C29: 2012-13 | D29: 2013 | E29: 52.928097 | F29: 108.72684 | G29: 130.06329 | H29: 0.44758219 | I29: 0.78802174 | K29: 0.10521126 | L29: 0.10694557 | M29: 0.11872252 | O29: 0.29759821 | P29: 0.30133142 | Q29: 0.32161829 | S29: 0.56769518 | T29: 0.58003946 | U29: 0.6025234
A30: =A29+1 -> 20 | B30: Guatemala (2011) | C30: 2011 | D30: 2011 | E30: 74.573472 | F30: 106.21412 | G30: 106.21412 | H30: 4.540333 | I30: 3.8732392
A31: =A30+1 -> 21 | B31: *,** Guinea (2012) | C31: 2012 | D31: 2016 | E31: 42.235538 | F31: 121.35046 | G31: 139.8262 | H31: 1479.5656 | I31: 2572.343
A32: =A31+1 -> 22 | B32: Honduras (2011) | C32: 2011 | D32: 2011 | E32: 71.982139 | F32: 106.76228 | G32: 106.76228 | H32: 9.662104 | I32: 10.080314
A33: =A32+1 -> 23 | B33: Indonesia (2012) | C33: 2012 | D33: 2012 | E33: 68.684857 | F33: 105.35605 | G33: 109.86476 | H33: 4192.8254 | I33: 4091.9391
A34: =A33+1 -> 24 | B34: Iran (2011) | C34: 2011-12 | D34: 2011-12 | E34: 49.410841 | F34: 120.86934 | G34: 120.86934 | H34: 2714.8227 | I34: 5001.3634
A35: =A34+1 -> 25 | B35: Jordan (2010) | C35: 2010-11 | D35: 2010 | E35: 75.760664 | F35: 104.16927 | G35: 100 | H35: 0.49294881 | I35: 0.31933158
A36: =A35+1 -> 26 | B36: *,** Kenya (2015) | C36: 2015-16 | D36: 2015-16 | E36: 55.52692 | F36: 114.02249 | G36: 150.18964 | H36: 32.683746 | I36: 35.429596 | K36: 0.356
A37: =A36+1 -> 27 | B37: *,** Mali (2014) | C37: 2014 | D37: 2014 | E37: 85.8601 | F37: 102.95564 | G37: 108.73074 | H37: 289.67868 | I37: 221.86832
A38: =A37+1 -> 28 | B38: Mexico (2010) | C38: 2010 | D38: 2010 | E38: 80.502825 | F38: 103.40738 | G38: 100 | H38: 7.6483314 | I38: 8.940212
B39: Mexico (2012) | C39: 2012 | D39: 2012 | E39: 80.502823 | F39: 103.40738 | G39: 107.65898 | H39: 7.6483312 | I39: 8.9402122 | K39: 0.077606815 | L39: 0.046023083 | M39: 0.045092158 | O39: 0.16595107 | P39: 0.1361415 | Q39: 0.1353379 | S39: 0.34241325 | T39: 0.33498535 | U39: 0.33380805 | W39: 0.082638446 | X39: 0.046023083 | Y39: 0.045092158 | AA39: 0.17589464 | AB39: 0.1361415 | AC39: 0.1353379 | AE39: 0.35554996 | AF39: 0.33498535 | AG39: 0.33380805
B40: Mexico (2014) | C40: 2014 | D40: 2014 | E40: 80.502824 | F40: 103.40738 | G40: 116.24798 | H40: 7.6483314 | I40: 8.9402122 | K40: 0.076143181 | L40: 0.045867786 | M40: 0.046380069 | O40: 0.16870971 | P40: 0.13405212 | Q40: 0.14035657 | S40: 0.36282784 | T40: 0.36090954 | U40: 0.37301897 | W40: 0.081122226 | X40: 0.045867786 | Y40: 0.046380069 | AA40: 0.1802533 | AB40: 0.13405212 | AC40: 0.14035657 | AE40: 0.38023856 | AF40: 0.36090954 | AG40: 0.37301897
A41: =A38+1 -> 29 | B41: *,** Mongolia (2016) | C41: 2016 | D41: 2016 | E41: 57.265934 | F41: 108.40917 | G41: 165.50894 | H41: 522.49286 | I41: 590.3299
A42: =A41+1 -> 30 | B42: *,** Namibia (2009) | C42: 2009 | D42: 2009 -10 | E42: 71.405037 | F42: 105.00559 | G42: 100 | H42: 5.0639524 | I42: 5.130702 | K42: 0.22 | L42: 0.153 | M42: 0.166
A43: =A42+1 -> 31 | B43: Nicaragua (2009) | C43: 2009 | D43: 2009 | E43: 62.929181 | F43: 108.08239 | G43: 94.827057 | H43: 7.297259 | I43: 9.1600754
A44: =A43+1 -> 32 | B44: *,** Niger (2014) | C44: 2014 -15 | D44: 2014 | E44: 88.526352 | F44: 102.94238 | G44: 104.80234 | H44: 267.33093 | I44: 228.75316
A45: =A44+1 -> 33 | B45: Panama (2016) | C45: 2016 | D45: 2015 | E45: 81.28521 | F45: 105.8758 | G45: 120.52139 | H45: 0.61135751 | I45: 0.55340803 | K45: 0.058481746 | L45: 0.029652888 | M45: 0.029799275 | O45: 0.10920828 | P45: 0.077385715 | Q45: 0.075835586 | S45: 0.19354573 | T45: 0.1664829 | U45: 0.16576289 | W45: 0.06433672 | X45: 0.029652888 | Y45: 0.029799275 | AA45: 0.11850931 | AB45: 0.077385715 | AC45: 0.075835586 | AE45: 0.20308981 | AF45: 0.1664829 | AG45: 0.16576289
A46: =A45+1 -> 34 | B46: Paraguay (2014) | C46: 2014 | D46: 2014 | E46: 71.354743 | F46: 108.25397 | G46: 121.04097 | H46: 2127.7958 | I46: 2309.43 | K46: 0.023928605 | L46: 0.016300411 | M46: 0.016192749 | O46: 0.060833678 | P46: 0.047016416 | Q46: 0.047946288 | S46: 0.15903877 | T46: 0.14146294 | U46: 0.14365982
A47: =A46+1 -> 35 | B47: Peru (2009) | C47: 2009 | D47: 2009 | E47: 87.125377 | F47: 103.36931 | G47: 98.494685 | H47: 1.6534499 | I47: 1.568639
B48: Peru (2011) | C48: 2011 | D48: 2011 | E48: 87.125374 | F48: 103.36931 | G48: 103.36931 | H48: 1.6534499 | I48: 1.568639 | K48: 0.064799108 | L48: 0.05543569 | M48: 0.057081503 | O48: 0.14283029 | P48: 0.1365853 | Q48: 0.14056387 | S48: 0.28649345 | T48: 0.28685346 | U48: 0.29702774 | W48: 0.065653597 | X48: 0.05543569 | Y48: 0.057081503 | AA48: 0.14526312 | AB48: 0.1365853 | AC48: 0.14056387 | AE48: 0.29526107 | AF48: 0.28685346 | AG48: 0.29702774
A49: =A47+1 -> 36 | B49: *,** Poland (2014) | C49: 2014 | D49: 2014 | E49: 86.884388 | F49: 104.2394 | G49: 109.08024 | H49: 2.1335834 | I49: 1.920205
A50: =A49+1 -> 37 | B50: *,** Romania (2016) | C50: 2016 | D50: 2016 | E50: 74.093498 | F50: 105.78925 | G50: 112.44076 | H50: 1.7119983 | I50: 1.8589569 | K50: 0.037647293 | L50: 0.0050385876 | M50: 0.0090133302 | O50: 0.073 | P50: 3.5%% | Q50: 0.049 | S50: 0.139 | T50: 0.121 | U50: 0.154 | W50: 0.096 | X50: 0.0050385876 | Y50: 0.0090133302 | AA50: 0.17483689 | AB50: 0.035 | AC50: 0.049 | AE50: 0.28054229 | AF50: 0.121 | AG50: 0.144
A51: =A50+1 -> 38 | B51: Russia (2010) | C51: 2010 | D51: 2010 | E51: 61.449009 | F51: 108.44047 | G51: 100 | H51: 13.390844 | I51: 16.769129 | K51: 0.024711221 | L51: 0.014382328 | M51: 0.014851844 | O51: 0.034777025 | P51: 0.023178254 | Q51: 0.026140546 | S51: 0.05996096 | T51: 0.042488097 | U51: 0.048249894 | W51: 0.13016853 | X51: 0.014382328 | Y51: 0.014851844 | AA51: 0.15874016 | AB51: 0.023178254 | AC51: 0.026140546 | AE51: 0.20192886 | AF51: 0.042488097 | AG51: 0.048249894
A52: =A51+1 -> 39 | B52: South Africa (2010) | C52: 2010-11 | D52: 2010 | E52: 74.256773 | F52: 105.01716 | G52: 105.01716 | H52: 4.5716545 | I52: 5.0675346
A53: =A52+1 -> 40 | B53: Sri Lanka (2009) | C53: 2009-10 | D53: 2010 | E53: 58.251419 | F53: 106.71677 | G53: 94.146317 | H53: 40.039497 | I53: 42.218933 | K53: 0.035578407 | L53: 0.022489995 | M53: 0.029968439 | O53: 0.20048749 | P53: 0.17879357 | Q53: 0.21383076 | S53: 0.59046541 | T53: 0.57024636 | U53: 0.61119956
A54: =A53+1 -> 41 | B54: Tanzania (2011) | C54: 2011-12 | D54: 2011-12 | E54: 66.33255 | F54: 112.69097 | G54: 112.69097 | H54: 482.45093 | I54: 585.52039 | K54: 0.38797343 | L54: 0.38666364 | M54: 0.46489159 | O54: 0.73109006 | P54: 0.73920399 | Q54: 0.80346891 | S54: 0.90766091 | T54: 0.91949789 | U54: 0.94532386
A55: =A54+1 -> 42 | B55: Tunisia (2010) | C55: 2010 | D55: 2010 | E55: 84.166019 | F55: 103.54403 | G55: 100 | H55: 0.69612007 | I55: 0.69653375
A56: =A55+1 -> 43 | B56: Uganda (2012) | C56: 2012-13 | D56: 2012-13 | E56: 66.678946 | F56: 116.56435 | G56: 137.78626 | H56: 744.61789 | I56: 946.89042
A57: =A56+1 -> 44 | B57: *,** Ukraine (2016) | C57: 2016 | D57: 2016 | E57: 51.202007 | F57: 107.95573 | G57: 205.61224 | H57: 1.7091367 | I57: 3.3112316
A58: =A57+1 -> 45 | B58: United States (2011) | C58: 2011 | D58: 2011 | E58: 89.560532 | F58: 103.15684 | G58: 103.15684 | H58: 1 | I58: 1
A59: =A58+1 -> 46 | B59: Uruguay (2009) | C59: 2009 | D59: 2009 | E59: 70.543804 | F59: 108.09283 | G59: 93.721846 | H59: 15.310342 | I59: 16.42385 | K59: 0.031939169 | L59: 0.0033126432 | M59: 0.0045706636 | O59: 0.069209726 | P59: 0.023725328 | Q59: 0.034073518 | S59: 0.15650578 | T59: 0.11263917 | U59: 0.14536464 | W59: 0.065407096 | X59: 0.0033126432 | Y59: 0.0045706636 | AA59: 0.12006936 | AB59: 0.023725328 | AC59: 0.034073518 | AE59: 0.21689142 | AF59: 0.11263917 | AG59: 0.14536464
A60: =A59+1 -> 47 | B60: Venezuela (2013) | C60: 2013 | D60: 2013 | E60: 34 | F60: 127.1 | G60: 213.3 | H60: 1.2511222 | I60: 2.9150053
C63: not applicable; means that the indicator should not be calculated due to methodological reasons or characteristics of the fiscal system.
C65: not calculated; means that the indicator was not calculated by the author/s.
C67: not calculated; means that the indicator has not been calculated.
C69: not available; means that the indicator was calculated but it is not publicly available, requests should be put directly to author/s.
C71: omitted for being unreliable data
C73: not available; means that the indicator is no published on the World Bank's report
B76: * The information published here is from World Bank led CEQ assessments and has not undergone quality control by the CEQ Institute. The information is taken from World Bank Policy Research Working Papers. See References for further detail.
B77: ** At least some information for this CEQ Assessment was extracted directly from World Bank Policy Research Working Papers, Reports, Working Papers (numbered series) and Poverty Assessment.
B79: Notes
B80: 1. The year represented by the data in parentheses.
B81: 2. Because national and international agencies often update their data series, the information included here may be subject to change.
B82: 3. The letters "C" and "I" indicate that the study used consumption or income data, respectively.
B83: 4. In Armenia, Costa Rica, Iran, Peru, South Africa and Uruguay there are no indirect subsidies.
B84: 5. Bolivia does not have personal income taxes.
B85: 6. In Bolivia, Costa Rica, Ecuador, Honduras, South Africa and Sri Lanka, market income does not include consumption of own production because the data was either not available or not reliable.
B86: 7. For Brazil, the results for the analysis presented here differ from the results published in Higgins and Pereira (2014) because the latter include taxes on services (ISS), on goods and services to finance pensions (CONFINS) and to finance Social Workers (PIS), while the results presented here do not include them. Post publishing the mentioned paper, the authors concluded that the source for these taxes was not reliable.
B87: 8. Gini coefficients for Chile are estimated here using total income and, thus, differ from official figures of inequality which are estimated using monetary income (i.e., official figures exclude owner’s occupied imputed rent).
B88: 9. For Dominican Republic, the study analyzes the effects of fiscal policy in 2013, but the household income and expenditure survey dates back to 2006-07.
... B109: Source: CEQ Institute’s Data Center on Fiscal Redistribution. Based on the following Master Workbooks of Results, for United States the source is the publication of Higgins, et al. (2016):
A110: =A10 -> 1 | B110: ='5.Inequality - Gini coefficient'!B101 -> *,** Albania (2015): n.a.
A111: =A11 -> 2 | B111: ='5.Inequality - Gini coefficient'!B102 -> Argentina (2012): Rossignolo, Dario. 2017. “CEQ Master Workbook: Argentina (2012-2013),” CEQ Data Center on Fiscal Redistribution (CEQ Institute, Tulane University). Jun 8, 2018.
A112: =A12 -> 3 | B112: ='5.Inequality - Gini coefficient'!B103 -> Armenia (2011): Younger, Stephen D., Artsvi Khachatryan, Gohar Gyulumyan, Nistha Sinha, and Ulrich Bartsch. 2019. “CEQ Master Workbook: Armenia (2011),” CEQ Data Center on Fiscal Redistribution (CEQ Institute, Tulane University and the World Bank). June 8, 2019.
A113: =A13 -> 4 | B113: ='5.Inequality - Gini coefficient'!B104 -> *,** Belarus (2015): n.a.
A114: =A14 -> 5 | B114: ='5.Inequality - Gini coefficient'!B105 -> Bolivia (2009): Paz Arauco, Veronica, George Gray-Molina, Wilson Jimenez and Ernesto Yañez. 2014. “CEQ Master Workbook: Bolivia (2009),” CEQ Data Center on Fiscal Redistribution (CEQ Institute, Tulane University). September 22, 2014.
A115: =A15 -> 6 | B115: ='5.Inequality - Gini coefficient'!B106 -> Brazil (2008): Higgins, Sean, Claudiney Pereira, and, Maynor Cabrera. 2019. “CEQ Master Workbook: Brazil (2008-2009),” CEQ Data Center on Fiscal Redistribution (CEQ Institute, Tulane University). May 3, 2019.
A116: =A16 -> 7 | B116: ='5.Inequality - Gini coefficient'!B107 -> *,** Burkina Faso (2014): n.a.
A117: =A17 -> 8 | B117: ='5.Inequality - Gini coefficient'!B108 -> Chile (2013): Martinez-Aguilar, Sandra and Eduardo Ortiz-Juarez. 2016. “CEQ Master Workbook: Chile (2013),” CEQ Data Center on Fiscal Redistribution (CEQ Institute, Tulane University and the World Bank). October 7, 2016.
A118: =A18 -> 9 | B118: ='5.Inequality - Gini coefficient'!B109 -> Colombia (2010): Melendez, Marcela and Valentina Martinez. 2019. “CEQ Master Workbook: Colombia (2010),” CEQ Data Center on Fiscal Redistribution (CEQ Institute, Tulane University and Inter-American Development Bank). February 20, 2019.
A119: =A19 -> 0 | B119: ='5.Inequality - Gini coefficient'!B110 -> Colombia (2014): Melendez, Marcela and Valentina Martinez. 2019. “CEQ Master Workbook: Colombia (2014),” CEQ Data Center on Fiscal Redistribution (CEQ Institute, Tulane University and Inter-American Development Bank). February 28, 2019.
A120: =A20 -> 10 | B120: ='5.Inequality - Gini coefficient'!B111 -> *,** Comoros (2014): n.a.
A121: =A21 -> 11 | B121: ='5.Inequality - Gini coefficient'!B112 -> Costa Rica (2010): Sauma, Pablo and Juan Diego Trejos. 2014. “CEQ Master Workbook: Costa Rica (2010),” CEQ Data Center on Fiscal Redistribution (CEQ Institute, Tulane University). February 14, 2014.
... A160: =A60 -> 47 | B160: ='5.Inequality - Gini coefficient'!B151 -> Venezuela (2013): Molina, Emiro. 2016. “CEQ Master Workbook: Venezuela (2012),” CEQ Data Center on Fiscal Redistribution (CEQ Institute, Tulane University). April 5, 2018.

Sheet 11.Pov-Pov & sq pov gap PDI P05
A1: Go to Contents
B3: Poverty: Poverty gap and squared poverty gap ratios based on international poverty lines in 2005 PPP $- Contributory pensions as deferred income scenario
B4: NOTE: FOR SOURCES AND CITATIONS SEE BOTTOM OF PAGE
AB5: x
C6: Country | D6: Year of survey | E6: Year of budgetary data and fiscal system | F6: Population | G6: Disposable income in LCU | H6: Consumer price index (indexed to 2005) | I6: Consumer price index 2011 | J6: Consumer price index year of survey | K6: PPP Conversion factor 2005 | L6: PPP Conversion factor 2011 | M6: Disposable income (USD PPP 2005) | N6: Poverty line: $1.25 2005PPP/day converted to 2011PPP | O6: Poverty line: $2.5 2005PPP/day converted to 2011PPP | P6: Poverty line: $4 2005PPP/day converted to 2011PPP | R6: Contributory pensions as deferred income
R7: 1.25 | AG7: 2.5 | AV7: 4
R8: 2005 PPP | AG8: 2005 PPP | AV8: 2005 PPP
R9: Market income plus pensions | W9: Disposable income | AB9: Consumable income | AG9: Market income plus pensions | AL9: Disposable income | AQ9: Consumable Income | AV9: Market income plus pensions | BA9: Disposable income | BF9: Consumable income
R10: Poverty gap ratio | S10: Squared poverty gap ratio | T10: National (USD PPP 2005) | U10: National (as % of disposable income) | W10: Poverty gap ratio | X10: Squared poverty gap ratio | Y10: National (USD PPP 2005) | Z10: National (as % of disposable income) | AB10: Poverty gap ratio | AC10: Squared poverty gap ratio | AD10: National (USD PPP 2005) | AE10: National (as % of disposable income) | AG10: Poverty gap ratio | AH10: Squared poverty gap ratio | AI10: National (USD PPP 2005) | AJ10: National (as % of disposable income) | AL10: Poverty gap ratio | AM10: Squared poverty gap ratio | AN10: National (USD PPP 2005) | AO10: National (as % of disposable income) | AQ10: Poverty gap ratio | AR10: Squared poverty gap ratio | AS10: National (USD PPP 2005) | AT10: National (as % of disposable income) | AV10: Poverty gap ratio | AW10: Squared poverty gap ratio | AX10: National (USD PPP 2005) | AY10: National (as % of disposable income) | BA10: Poverty gap ratio | BB10: Squared poverty gap ratio | BC10: National (USD PPP 2005) | BD10: National (as % of disposable income) | BF10: Poverty gap ratio | BG10: Squared poverty gap ratio | BH10: National (USD PPP 2005) | BI10: National (as % of disposable income)
B11: =B10+1 -> 1 | C11: *,** Albania (2015) | D11: 2015 | E11: 2015 | F11: 2880703 | H11: 86.675568 | I11: 103.44284 | J11: 111.40497 | K11: 55.653665 | L11: 55.587503 | N11: 1.4935864 | O11: 2.9871728 | P11: 4.7794765 | AG11: 0.022 | AH11: 0.011 | AI11: 57830113 | AL11: 0.011 | AM11: 0.004 | AN11: 28915056 | AQ11: 0.018 | AR11: 0.006 | AS11: 47315547 | AV11: 0.068 | AW11: 0.032 | AX11: 2.8599619e+08 | BA11: 0.053 | BB11: 0.02 | BC11: 2.229088e+08 | BF11: 0.08 | BG11: 0.032 | BH11: 3.3646611e+08
B12: =B11+1 -> 2 | C12: Argentina (2012) | D12: 2012-13 | E12: 2012 | F12: 36138213 | G12: 1.0026617e+12 | J12: 110.61845 | K12: 1.3525982 | L12: 2.768382 | R12: 0.0064925 | S12: 0.0044115 | T12: 1.0704873e+08 | W12: 0.0006834 | X12: 0.0003378 | Y12: 11267940 | AB12: 0.0011582 | AC12: 0.0005348 | AD12: 19096471 | AG12: 0.0176844 | AH12: 0.0101774 | AI12: 5.8316289e+08 | AL12: 0.0051234 | AM12: 0.0021404 | AN12: 1.6894985e+08 | AQ12: 0.0083616 | AR12: 0.0035731 | AS12: 2.7573312e+08 | AV12: 0.0422523 | AW12: 0.0222897 | AX12: 2.229307e+09 | BA12: 0.018406 | BB12: 0.0076676 | BC12: 9.7113352e+08 | BF12: 0.0325068 | BG12: 0.0133383 | BH12: 1.715117e+09
B13: =B12+1 -> 3 | C13: Armenia (2011) | D13: 2011 | E13: 2011 | F13: 2965466.5 | G13: 1.3142893e+12 | H13: 76.379601 | I13: 107.65001 | J13: 107.65001 | K13: 196.18863 | L13: 183.7796 | M13: 4.7531381e+09 | N13: 1.8807161 | O13: 3.7614321 | P13: 6.0182914 | R13: 0.059924387 | S13: 0.039582492 | T13: 81077342 | U13: 0.017057645 | W13: 0.038572012 | X13: 0.02316804 | Y13: 52187705 | Z13: 0.010979631 | AB13: 0.046562293 | AC13: 0.027324197 | AD13: 62998507 | AE13: 0.013254087 | AG13: 0.13969464 | AH13: 0.086831503 | AI13: 3.7801204e+08 | AJ13: 0.07952894 | AL13: 0.11364494 | AM13: 0.064041525 | AN13: 3.0752186e+08 | AO13: 0.0646987 | AQ13: 0.13751701 | AR13: 0.077166942 | AS13: 3.7211942e+08 | AT13: 0.078289208 | AV13: 0.25219732 | AW13: 0.15543714 | AX13: 1.0919088e+09 | AY13: 0.22972376 | BA13: 0.23310323 | BB13: 0.13275665 | BC13: 1.0092393e+09 | BD13: 0.21233116 | BF13: 0.27311436 | BG13: 0.15831417 | BH13: 1.1824708e+09 | BI13: 0.24877686
B14: =B13+1 -> 4 | C14: *,** Belarus (2015) | D14: 2015 | E14: 2016 | F14: 9489616 | K14: 759.62347 | L14: 0.18324348 | R14: 0.001
B15: =B14+1 -> 5 | C15: Bolivia (2009) | D15: 2009 | E15: 2009 | F15: 10232625 | G15: 119460660000 | H15: 68.29517 | I15: 109.883 | J15: 97.559484 | K15: 2.5707953 | L15: 2.9061057 | M15: 3.2529539e+10 | N15: 1.402441 | O15: 2.804882 | P15: 4.4878111 | R15: 0.0457 | S15: 0.02699 | T15: 2.1335663e+08 | U15: 0.006558858 | W15: 0.0351 | X15: 0.01902 | Y15: 1.6386909e+08 | Z15: 0.0050375474 | AB15: 0.0467 | AC15: 0.02883 | AD15: 2.1802526e+08 | AE15: 0.0067023779 | AG15: 0.09814 | AH15: 0.06329 | AI15: 9.1635971e+08 | AJ15: 0.02817008 | AL15: 0.08238 | AM15: 0.05085 | AN15: 7.6920433e+08 | AO15: 0.023646334 | AQ15: 0.09791 | AR15: 0.06384 | AS15: 9.1421214e+08 | AT15: 0.028104061 | AV15: 0.15872 | AW15: 0.1042 | AX15: 2.3712185e+09 | AY15: 0.072894315 | BA15: 0.14146 | BB15: 0.08911 | BC15: 2.1133604e+09 | BD15: 0.064967426 | BF15: 0.16262 | BG15: 0.10565 | BH15: 2.429483e+09 | BI15: 0.074685443
B16: =B15+1 -> 6 | C16: Brazil (2008) | D16: 2008-09 | E16: 2009 | F16: 1.905193e+08 | G16: 1.6310513e+12 | H16: 79.543671 | I16: 106.63637 | J16: 95.20298 | K16: 1.5713184 | L16: 1.6587826 | M16: 8.6727835e+11 | N16: 1.2652456 | O16: 2.5304912 | P16: 4.048786 | R16: 0.026468696 | S16: 0.015332631 | T16: 2.3007763e+09 | U16: 0.0026528695 | W16: 0.012717538 | X16: 0.0059583363 | Y16: 1.1054647e+09 | Z16: 0.0012746366 | AB16: 0.016897851 | AC16: 0.0079224985 | AD16: 1.4688361e+09 | AE16: 0.0016936155 | AG16: 0.072100727 | AH16: 0.042001561 | AI16: 1.2534629e+10 | AJ16: 0.014452833 | AL16: 0.051087017 | AM16: 0.025867162 | AN16: 8.8814196e+09 | AO16: 0.010240564 | AQ16: 0.065687809 | AR16: 0.033704429 | AS16: 1.1419751e+10 | AT16: 0.013167342 | AV16: 0.1327931 | AW16: 0.080235151 | AX16: 3.6937486e+10 | AY16: 0.042590116 | BA16: 0.11087947 | BB16: 0.060567696 | BC16: 3.0842032e+10 | BD16: 0.035561861 | BF16: 0.13730987 | BG16: 0.076502998 | BH16: 3.8193862e+10 | BI16: 0.044038758
B17: =B16+1 -> 7 | C17: *,** Burkina Faso (2014) | D17: 2014 | E17: 2014 | F17: 17586017 | H17: 86.925362 | I17: 102.75977 | J17: 106.97589 | K17: 242.41742 | L17: 222.24197 | N17: 1.6118491 | O17: 3.2236982 | P17: 5.1579171 | R17: 0.0233 | S17: 0.0061 | T17: 1.8695035e+08 | W17: 0.0214 | X17: 0.0055 | Y17: 1.7170547e+08 | AB17: 0.0358 | AC17: 0.01 | AD17: 2.8724561e+08 | AG17: 0.2193 | AH17: 0.0956 | AI17: 3.5191598e+09 | AL17: 0.2146 | AM17: 0.0923 | AN17: 3.4437378e+09 | AQ17: 0.2577 | AR17: 0.1193 | AS17: 4.1353739e+09 | AV17: 0.4238 | AW17: 0.2428 | AX17: 1.0881313e+10 | BA17: 0.4199 | BB17: 0.2388 | BC17: 1.0781178e+10 | BF17: 0.4616 | BG17: 0.2758 | BH17: 1.185185e+10
B18: =B17+1 -> 8 | C18: Chile (2013) | D18: 2013 | E18: 2013 | F18: 17256219 | G18: 6.045821e+13 | H18: 83.727998 | I18: 103.34032 | J18: 108.4998 | K18: 387.36 | L18: 370.19874 | M18: 1.204432e+11 | N18: 1.6143175 | O18: 3.2286349 | P18: 5.1658159 | R18: 0.0033290846 | S18: 0.0022127123 | T18: 26210382 | U18: 0.00021761613 | W18: 0.0010460239 | X18: 0.00073931728 | Y18: 8235503.1 | Z18: 6.8376656e-05 | AB18: 0.00099867891 | AC18: 0.00064531391 | AD18: 7862748.8 | AE18: 6.52818e-05 | AG18: 0.009819385 | AH18: 0.0054630708 | AI18: 1.5461898e+08 | AJ18: 0.0012837502 | AL18: 0.0035749626 | AM18: 0.0018599144 | AN18: 56292434 | AO18: 0.00046737744 | AQ18: 0.0040192869 | AR18: 0.0019669385 | AS18: 63288896 | AT18: 0.00052546675 | AV18: 0.024541368 | AW18: 0.012552738 | AX18: 6.1829718e+08 | AY18: 0.0051335168 | BA18: 0.011675654 | BB18: 0.0051657856 | BC18: 2.9415735e+08 | BD18: 0.0024422911 | BF18: 0.014498227 | BG18: 0.0061246361 | BH18: 3.6526949e+08 | BI18: 0.0030327117
B19: =B18+1 -> 9 | C19: Colombia (2010) | D19: 2010 | E19: 2010 | F19: 45062798 | G19: 2.4478809e+14 | H19: 79.671288 | I19: 103.41503 | J19: 100 | K19: 1191.7422 | L19: 1196.9546 | M19: 1.6364766e+11 | N19: 1.5105293 | O19: 3.0210586 | P19: 4.8336937 | R19: 0.026092328 | S19: 0.014500602 | T19: 5.3645568e+08 | U19: 0.003278114 | W19: 0.020896874 | X19: 0.011124149 | Y19: 4.2963766e+08 | Z19: 0.0026253822 | AB19: 0.020196682 | AC19: 0.010264947 | AD19: 4.1524179e+08 | AE19: 0.0025374135 | AG19: 0.081393284 | AH19: 0.045038846 | AI19: 3.3468758e+09 | AJ19: 0.020451718 | AL19: 0.073278144 | AM19: 0.038820207 | AN19: 3.0131829e+09 | AO19: 0.018412624 | AQ19: 0.074460897 | AR19: 0.038767559 | AS19: 3.0618174e+09 | AT19: 0.018709815 | AV19: 0.15841257 | AW19: 0.092287809 | AX19: 1.042223e+10 | AY19: 0.063687009 | BA19: 0.15210662 | BB19: 0.08534452 | BC19: 1.0007351e+10 | BD19: 0.061151812 | BF19: 0.1571139 | BG19: 0.08724508 | BH19: 1.0336788e+10 | BI19: 0.0631649
C20: Colombia (2014) | D20: 2014 | E20: 2014 | F20: 47203862 | G20: 3.3473699e+14 | H20: 79.671287 | I20: 103.41503 | J20: 111.99978 | K20: 1191.7422 | L20: 1196.9546 | M20: 1.9980486e+11 | N20: 1.615461 | O20: 3.230922 | P20: 5.1694753 | R20: 0.026801886 | S20: 0.017939608 | T20: 5.7722584e+08 | U20: 0.0028889479 | W20: 0.020112933 | X20: 0.012937275 | Y20: 4.3316745e+08 | Z20: 0.0021679525 | AB20: 0.019125558 | AC20: 0.01169887 | AD20: 4.1190259e+08 | AE20: 0.0020615244 | AG20: 0.069113623 | AH20: 0.041173827 | AI20: 2.9769673e+09 | AJ20: 0.014899374 | AL20: 0.05882166 | AM20: 0.033227374 | AN20: 2.5336562e+09 | AO20: 0.012680653 | AQ20: 0.059067657 | AR20: 0.032578467 | AS20: 2.5442522e+09 | AT20: 0.012733685 | AV20: 0.13540436 | AW20: 0.07954 | AX20: 9.3317488e+09 | AY20: 0.046704313 | BA20: 0.12461775 | BB20: 0.069738151 | BC20: 8.5883613e+09 | BD20: 0.042983745 | BF20: 0.12784825 | BG20: 0.070625111 | BH20: 8.8109992e+09 | BI20: 0.044098022
B21: =B19+1 -> 10 | C21: *,** Comoros (2014) | D21: 2014 | F21: 747155 | H21: 84.413689 | I21: 101.84267 | K21: 294.41086 | L21: 220.57249
B22: =B21+1 -> 11 | C22: Costa Rica (2010) | D22: 2010 | E22: 2010 | F22: 4551553 | G22: 1.3618179e+13 | H22: 63.470569 | I22: 104.87815 | J22: 100 | K22: 278.9614 | L22: 343.78567 | M22: 3.0984701e+10 | N22: 1.5237333 | O22: 3.0474665 | P22: 4.8759464 | R22: 0.009594533 | S22: 0.0067035551 | T22: 19924449 | U22: 0.00064304151 | W22: 0.0052631522 | X22: 0.0039847357 | Y22: 10929704 | Z22: 0.00035274518 | AB22: 0.0094311407 | AC22: 0.0098901665 | AD22: 19585141 | AE22: 0.00063209069 | AG22: 0.021039966 | AH22: 0.013405289 | AI22: 87385126 | AJ22: 0.0028202668 | AL22: 0.012003018 | AM22: 0.0074485935 | AN22: 49852039 | AO22: 0.0016089243 | AQ22: 0.016191765 | AR22: 0.012043654 | AS22: 67249131 | AT22: 0.0021703979 | AV22: 0.039787958 | AW22: 0.024041369 | AX22: 2.6440162e+08 | AY22: 0.0085332956 | BA22: 0.026655891 | BB22: 0.014672197 | BC22: 1.7713552e+08 | BD22: 0.0057168704 | BF22: 0.032296325 | BG22: 0.019344972 | BH22: 2.1461772e+08 | BI22: 0.0069265705
B23: =B22+1 -> 12 | C23: *,** Croatia (2014) | D23: 2014 | E23: 2014 | F23: 4238389 | H23: 85.835719 | I23: 102.27273 | J23: 107.87402 | K23: 4.4176406 | L23: 4.2908092 | N23: 1.5333913 | O23: 3.0667826 | P23: 4.9068521 | W23: 0.0057746366 | X23: 0.0033807406 | Y23: =$F23*W23*$R$7*365 -> 11166790 | AB23: 0.012000353 | AC23: 0.00778321 | AD23: =$F23*AB23*$R$7*365 -> 23205863 | AG23: 0.031 | AH23: 0.023 | AI23: 1.1989343e+08 | AL23: 0.012305304 | AM23: 0.0080064455 | AN23: =$F23*AL23*$AG$7*365 -> 47591133 | AQ23: 0.025146648 | AR23: 0.016040668 | AS23: =$F23*AQ23*$AG$7*365 -> 97255413 | BA23: 0.02142178 | BB23: 0.013348053 | BC23: =$F23*BA23*$AV$7*365 -> 1.32559e+08 | BF23: 0.048480689 | BG23: 0.029005162 | BH23: =$F23*BF23*$AV$7*365 -> 3.0000083e+08
B24: =B23+1 -> 13 | C24: Dominican Republic (2006) | D24: 2006-07 | E24: 2013 | F24: 9234446 | G24: 6.6768401e+11 | H24: 73.38369 | I24: 108.74036 | J24: 83.79068 | K24: 20.39608 | L24: 20.74103 | M24: 2.8670027e+10 | N24: 1.8214515 | O24: 3.6429031 | P24: 5.8286449 | R24: 0.020059264 | S24: 0.01042291 | T24: 84514012 | U24: 0.0029478177 | W24: 0.015418668 | X24: 0.0073007374 | Y24: 64962179 | Z24: 0.0022658569 | AB24: 0.015624093 | AC24: 0.0073523842 | AD24: 65827676 | AE24: 0.0022960451 | AG24: 0.072858848 | AH24: 0.037796019 | AI24: 6.1394013e+08 | AJ24: 0.021414006 | AL24: 0.064840892 | AM24: 0.031998534 | AN24: 5.4637737e+08 | AO24: 0.019057442 | AQ24: 0.068087766 | AR24: 0.033276929 | AS24: 5.7373693e+08 | AT24: 0.020011733 | AV24: 0.15294273 | AW24: 0.084945142 | AX24: 2.0620184e+09 | AY24: 0.071922442 | BA24: 0.14417098 | BB24: 0.077486126 | BC24: 1.9437551e+09 | BD24: 0.067797462 | BF24: 0.15149809 | BG24: 0.081298267 | BH24: 2.0425414e+09 | BI24: 0.071243092
B25: =B24+1 -> 14 | C25: Ecuador (2011) | D25: 2011-12 | E25: 2011 | F25: 15223535 | G25: 3.8285369e+10 | H25: 80.182916 | I25: 104.47453 | J25: 104.47453 | K25: 0.50084672 | L25: 0.54723445 | M25: 5.8667748e+10 | N25: 1.4906305 | O25: 2.981261 | P25: 4.7700175 | R25: 0.015581582 | S25: 0.010073418 | T25: 1.0822558e+08 | U25: 0.0018447203 | W25: 0.0060777857 | X25: 0.0030336901 | Y25: 42214706 | Z25: 0.00071955559 | AB25: 0.0046967331 | AC25: 0.0020929953 | AD25: 32622277 | AE25: 0.00055605129 | AG25: 0.041314045 | AH25: 0.024014355 | AI25: 5.7391305e+08 | AJ25: 0.0097824285 | AL25: 0.024489101 | AM25: 0.012061767 | AN25: 3.4018976e+08 | AO25: 0.0057985821 | AQ25: 0.021300878 | AR25: 0.010080792 | AS25: 2.9590064e+08 | AT25: 0.0050436678 | AV25: 0.090740914 | AW25: 0.049897716 | AX25: 2.0168403e+09 | AY25: 0.034377326 | BA25: 0.067952152 | BB25: 0.032760543 | BC25: 1.5103291e+09 | BD25: 0.025743771 | BF25: 0.063130531 | BG25: 0.029408022 | BH25: 1.403162e+09 | BI25: 0.023917093
B26: =B25+1 -> 15 | C26: *,** Egypt (2015) | D26: 2015 | E26: 2015 | F26: 92442547 | H26: 57.757275 | I26: 110.05392 | J26: 156.80304 | K26: 2.0223918 | L26: 1.8029792 | N26: =IF(E26>2011,1.25*$K26*($J26/$H26)/$L26*($I26/$J26), 1.25*$K26*($J26/$H26)/$K26*($J26/$H26)) -> 2.6716737 | O26: =IF(E26>2011,2.5*$K26*($J26/$H26)/$L26*($I26/$J26), 2.5*$K26*($J26/$H26)/$K26*($J26/$H26)) -> 5.3433474 | P26: =IF(E26>2011, 4*$K26*($J26/$H26)/$L26*($I26/$J26), 4*$K26*($J26/$H26)/$K26*($J26/$H26)) -> 8.5493558
B27: =B26+1 -> 16 | C27: El Salvador (2011) | D27: 2011 | E27: 2011 | F27: 6213730 | G27: 1.0090341e+10 | H27: 84.240434 | I27: 105.12892 | J27: 105.12892 | K27: 0.5499814 | L27: 0.53077351 | M27: =G27/(J27/H27*K27) -> 1.4701316e+10 | N27: 1.6164057 | O27: 3.2328115 | P27: 5.1724984 | R27: 0.0115716 | S27: 0.0045046497 | T27: =$F27*R27*$R$7*365 -> 32805652 | U27: =T27/$M27 -> 0.0022314772 | W27: 0.0062603022 | X27: 0.0019160033 | Y27: =$F27*W27*$R$7*365 -> 17748046 | Z27: =Y27/$M27 -> 0.001207242 | AB27: 0.0069178571 | AC27: 0.0021571643 | AD27: =$F27*AB27*$R$7*365 -> 19612224 | AE27: =AD27/$M27 -> 0.0013340454 | AG27: 0.065884408 | AH27: 0.030320318 | AI27: =$F27*AG27*$AG$7*365 -> 3.7356648e+08 | AJ27: =AI27/$M27 -> 0.02541041 | AL27: 0.053610437 | AM27: 0.0223434 | AN27: =$F27*AL27*$AG$7*365 -> 3.0397271e+08 | AO27: =AN27/$M27 -> 0.020676564 | AQ27: 0.058541754 | AR27: 0.024418797 | AS27: =$F27*AQ27*$AG$7*365 -> 3.3193342e+08 | AT27: =AS27/$M27 -> 0.022578483 | AV27: 0.15906313 | AW27: 0.08189229 | AX27: =$F27*AV27*$AV$7*365 -> 1.443028e+09 | AY27: =AX27/$M27 -> 0.09815638 | BA27: 0.14610924 | BB27: 0.070751048 | BC27: =$F27*BA27*$AV$7*365 -> 1.3255097e+09 | BD27: =BC27/$M27 -> 0.090162653 | BF27: 0.158894 | BG27: 0.077128239 | BH27: =$F27*BF27*$AV$7*365 -> 1.4414937e+09 | BI27: =BH27/$M27 -> 0.098052014
B28: =B27+1 -> 17 | C28: Ethiopia (2010) | D28: 2010-11 | E28: 2011 | F28: 76073949 | G28: 3.5196766e+11 | H28: 44.845641 | I28: 133.2499 | J28: 100 | K28: 2.7512605 | L28: 5.4386136 | M28: 5.737085e+10 | N28: 1.0581967 | O28: 2.1163934 | P28: 3.3862294 | R28: 0.091770597 | S28: 0.039222896 | T28: 3.1852417e+09 | U28: 0.055520211 | W28: 0.081559733 | X28: 0.032066647 | Y28: 2.8308355e+09 | Z28: 0.049342749 | AB28: 0.089024127 | AC28: 0.035267249 | AD28: 3.0899152e+09 | AE28: 0.053858626
B29: =B28+1 -> 18 | C29: Georgia (2013) | D29: 2013 | E29: 2013 | F29: 3675078 | H29: 69.963517 | I29: 108.54293 | J29: 106.9681 | K29: 0.78454581 | L29: 0.84190709 | N29: 1.8071494 | O29: 3.6142988 | P29: 5.7828781
B30: =B29+1 -> 19 | C30: Ghana (2012) | D30: 2012-13 | E30: 2013 | F30: 26347424 | G30: 5.9565157e+10 | H30: 52.928097 | I30: 108.72684 | J30: 130.06329 | K30: 0.44758219 | L30: 0.78802174 | M30: 5.4156556e+10 | N30: 1.4584619 | O30: 2.9169239 | P30: 4.6670782 | R30: 0.016063658 | S30: 0.0066718629 | T30: 1.9310142e+08 | U30: 0.0035656149 | W30: 0.01504446 | X30: 0.006019149 | Y30: 1.8084964e+08 | Z30: 0.0033393859 | AB30: 0.017330828 | AC30: 0.0070407157 | AD30: 2.083341e+08 | AE30: 0.003846886 | AG30: 0.082445307 | AH30: 0.038519908 | AI30: 1.9821521e+09 | AJ30: 0.036600408 | AL30: 0.082502057 | AM30: 0.037986163 | AN30: 1.9835164e+09 | AO30: 0.036625602 | AQ30: 0.090868516 | AR30: 0.042392864 | AS30: 2.1846631e+09 | AT30: 0.040339771 | AV30: 0.19068435 | AW30: 0.10066053 | AX30: 7.3351004e+09 | AY30: 0.13544252 | BA30: 0.19338173 | BB30: 0.10129113 | BC30: 7.438861e+09 | BD30: 0.13735846 | BF30: 0.20695527 | BG30: 0.10995568 | BH30: 7.9609979e+09 | BI30: 0.14699971
B31: =B30+1 -> 20 | C31: Guatemala (2011) | D31: 2011 | E31: 2011 | F31: 14636886 | G31: 2.0236933e+11 | H31: 74.573472 | I31: 106.21412 | J31: 106.21412 | K31: 4.540333 | L31: 3.8732392 | M31: 3.1293857e+10 | N31: 2.0869944 | O31: 4.1739889 | P31: 6.6783822 | R31: 0.0132863 | S31: 0.00486607 | T31: 88726964 | U31: 0.0028352837 | W31: 0.01144581 | X31: 0.00403441 | Y31: 76436026 | Z31: 0.0024425249 | AB31: 0.01324191 | AC31: 0.00468326 | AD31: 88430524 | AE31: 0.0028258109 | AG31: 0.09862338 | AH31: 0.04204522 | AI31: 1.3172295e+09 | AJ31: 0.04209227 | AL31: 0.09252283 | AM31: 0.038437 | AN31: 1.2357496e+09 | AO31: 0.039488567 | AQ31: 0.10397429 | AR31: 0.04373955 | AS31: 1.3886971e+09 | AT31: 0.044376028 | AV31: 0.23727137 | AW31: 0.12253307 | AX31: 5.0704544e+09 | AY31: 0.16202715 | BA31: 0.23227275 | BB31: 0.11764129 | BC31: 4.9636347e+09 | BD31: 0.1586137 | BF31: 0.25051756 | BG31: 0.12927661 | BH31: 5.3535236e+09 | BI31: 0.17107266
B32: =B31+1 -> 21 | C32: *,** Guinea (2012) | D32: 2012 | E32: 2016 | F32: 10652029 | H32: 42.235538 | I32: 121.35046 | J32: 139.8262 | K32: 1479.5656 | L32: 2572.343 | N32: =IF(E32>2011,1.25*$K32*($J32/$H32)/$L32*($I32/$J32), 1.25*$K32*($J32/$H32)/$K32*($J32/$H32)) -> 2.0657547 | O32: =IF(E32>2011,2.5*$K32*($J32/$H32)/$L32*($I32/$J32), 2.5*$K32*($J32/$H32)/$K32*($J32/$H32)) -> 4.1315095 | P32: =IF(E32>2011, 4*$K32*($J32/$H32)/$L32*($I32/$J32), 4*$K32*($J32/$H32)/$K32*($J32/$H32)) -> 6.6104152
B33: =B32+1 -> 22 | C33: Honduras (2011) | D33: 2011 | E33: 2011 | F33: 8171770 | G33: 261675716820 | H33: 71.982139 | I33: 106.76228 | J33: 106.76228 | K33: 9.662104 | L33: 10.080314 | M33: 1.825991e+10 | N33: 1.7770545 | O33: 3.554109 | P33: 5.6865745 | R33: 0.0442809 | S33: 0.0278598 | T33: 1.6509558e+08 | U33: 0.0090414238 | W33: 0.0379448 | X33: 0.02294 | Y33: 1.4147226e+08 | Z33: 0.0077476975 | AB33: 0.0392508 | AC33: 0.0236303 | AD33: 1.4634151e+08 | AE33: 0.008014361 | AG33: 0.1098397 | AH33: 0.0666189 | AI33: 8.190461e+08 | AJ33: 0.044854882 | AL33: 0.1017756 | AM33: 0.0597831 | AN33: 7.589142e+08 | AO33: 0.041561772 | AQ33: 0.1063535 | AR33: 0.0622815 | AS33: 7.9305041e+08 | AT33: 0.043431234 | AV33: 0.1905053 | AW33: 0.1197446 | AX33: 2.2728776e+09 | AY33: 0.12447365 | BA33: 0.1829453 | BB33: 0.1122532 | BC33: 2.1826809e+09 | BD33: 0.11953405 | BF33: 0.1920218 | BG33: 0.1173353 | BH33: 2.2909707e+09 | BI33: 0.12546451
B34: =B33+1 -> 23 | C34: Indonesia (2012) | D34: 2012 | E34: 2012 | F34: 245265690 | G34: 1.9319884e+15 | H34: 68.684857 | I34: 105.35605 | J34: 109.86476 | K34: 4192.8254 | L34: 4091.9391 | M34: 2.8807152e+11 | N34: 1.9646542 | O34: 3.9293083 | P34: 6.2868933 | R34: 0.020646398 | S34: 0.0055351497 | T34: 2.310383e+09 | U34: 0.0080201716 | W34: 0.017350302 | X34: 0.0043672439 | Y34: 1.9415416e+09 | Z34: 0.0067397903 | AB34: 0.017239134 | AC34: 0.004436223 | AD34: 1.9291017e+09 | AE34: 0.0066966067 | AG34: 0.19267867 | AH34: 0.08415277 | AI34: 4.3122439e+10 | AJ34: 0.14969352 | AL34: 0.1871269 | AM34: 0.07970482 | AN34: 4.1879926e+10 | AO34: 0.14538031 | AQ34: 0.18209725 | AR34: 0.077580325 | AS34: 4.0754265e+10 | AT34: 0.14147273 | AV34: 0.37786806 | AW34: 0.21466948 | AX34: 1.3530998e+11 | AY34: 0.46970969 | BA34: 0.37494287 | BB34: 0.21042483 | BC34: 1.3426251e+11 | BD34: 0.46607353 | BF34: 0.36904883 | BG34: 0.20606855 | BH34: 1.3215192e+11 | BI34: 0.45874693
B35: =B34+1 -> 24 | C35: Iran (2011) | D35: 2011-12 | E35: 2011-12 | F35: 79511694 | G35: 2.3369173e+15 | H35: 49.410841 | I35: 120.86934 | J35: 120.86934 | K35: 2714.8227 | L35: 5001.3634 | M35: 3.5189085e+11 | N35: 1.6598047 | O35: 3.3196093 | P35: 5.3113749 | R35: 0.013631553 | S35: 0.0074193606 | T35: 4.9451471e+08 | U35: 0.0014053071 | W35: 0.00092883514 | X35: 0.00051533304 | Y35: 33695548 | Z35: 9.5755681e-05 | AB35: 0.0013843228 | AC35: 0.00090892796 | AD35: 50219368 | AE35: 0.00014271291 | AG35: 0.039874135 | AH35: 0.022503762 | AI35: 2.8930448e+09 | AJ35: 0.0082214267 | AL35: 0.0049884704 | AM35: 0.0021251429 | AN35: 3.6193558e+08 | AO35: 0.001028545 | AQ35: 0.0064581134 | AR35: 0.0028897996 | AS35: 4.6856468e+08 | AT35: 0.0013315626 | AV35: 0.082887483 | AW35: 0.046677961 | AX35: 9.6221653e+09 | AY35: 0.027344176 | BA35: 0.022824526 | BB35: 0.0088726539 | BC35: 2.6496325e+09 | BD35: 0.0075296999 | BF35: 0.0269401 | BG35: 0.010867107 | BH35: 3.1273973e+09 | BI35: 0.0088874075
B36: =B35+1 -> 25 | C36: Jordan (2010) | D36: 2010-11 | E36: 2010 | F36: 5961481.8 | G36: 1.0182084e+10 | H36: 75.760664 | I36: 104.16927 | J36: 100 | K36: 0.49294881 | L36: 0.31933158 | M36: 1.5648714e+10 | N36: 2.4450434 | O36: 4.8900868 | P36: 7.8241389 | R36: 0.0015126678 | S36: 0.00069232424 | T36: 4114344.5 | U36: 0.00026291902 | W36: 0.00025709219 | X36: 7.768776e-05 | Y36: 699271.74 | Z36: 4.4685573e-05 | AB36: 0.00020578831 | AC36: 6.4381837e-05 | AD36: 559728.99 | AE36: 3.576837e-05 | AG36: 0.011294995 | AH36: 0.0042831662 | AI36: 61443102 | AJ36: 0.0039263995 | AL36: 0.0072855914 | AM36: 0.0021776382 | AN36: 39632540 | AO36: 0.0025326388 | AQ36: 0.0062511865 | AR36: 0.0018121583 | AS36: 34005530 | AT36: 0.0021730559 | AV36: 0.061591555 | AW36: 0.022539776 | AX36: 5.3607833e+08 | AY36: 0.034257022 | BA36: 0.053816862 | BB36: 0.017868497 | BC36: 4.6840923e+08 | BD36: 0.029932763 | BF36: 0.050540668 | BG36: 0.016320933 | BH36: 4.3989402e+08 | BI36: 0.028110554
B37: =B36+1 -> 26 | C37: *,** Kenya (2015) | D37: 2015-16 | E37: 2015-16 | F37: 48465011 | H37: 55.52692 | I37: 114.02249 | J37: 150.18964 | K37: 32.683746 | L37: 35.429596 | N37: 2.3678957 | O37: 4.7357915 | P37: 7.5772664
B38: =B37+1 -> 27 | C38: *,** Mali (2014) | D38: 2014 | E38: 2014 | F38: 16934220 | H38: 85.8601 | I38: 102.95564 | J38: 108.73074 | K38: 289.67868 | L38: 221.86832 | N38: =IF(E38>2011,1.25*$K38*($J38/$H38)/$L38*($I38/$J38), 1.25*$K38*($J38/$H38)/$K38*($J38/$H38)) -> 1.9569963 | O38: =IF(E38>2011,2.5*$K38*($J38/$H38)/$L38*($I38/$J38), 2.5*$K38*($J38/$H38)/$K38*($J38/$H38)) -> 3.9139926 | P38: =IF(E38>2011, 4*$K38*($J38/$H38)/$L38*($I38/$J38), 4*$K38*($J38/$H38)/$K38*($J38/$H38)) -> 6.2623881
B39: =B38+1 -> 28 | C39: Mexico (2010) | D39: 2010 | E39: 2010 | F39: 112600583 | G39: 9.0388266e+12 | H39: 80.502825 | I39: 103.40738 | J39: 100 | K39: 7.6483314 | L39: 8.940212 | M39: 9.5138539e+11 | N39: 1.284595 | O39: 2.5691901 | P39: 4.1107041 | R39: 0.0204643 | S39: 0.0116648 | T39: 1.0513333e+09 | U39: 0.0011050551 | W39: 0.010403 | X39: 0.0050407 | Y39: 5.3444389e+08 | Z39: 0.00056175331 | AB39: 0.0104733 | AC39: 0.0052192 | AD39: 5.3805548e+08 | AE39: 0.00056554945 | AG39: 0.0522187 | AH39: 0.0309965 | AI39: 5.3653687e+09 | AJ39: 0.0056395323 | AL39: 0.0384584 | AM39: 0.0200624 | AN39: 3.9515249e+09 | AO39: 0.0041534429 | AQ39: 0.0383403 | AR39: 0.0200429 | AS39: 3.9393904e+09 | AT39: 0.0041406883 | AV39: 0.1018556 | AW39: 0.0596495 | AX39: 1.674474e+10 | AY39: 0.017600375 | BA39: 0.0869915 | BB39: 0.0465296 | BC39: 1.4301129e+10 | BD39: 0.015031899 | BF39: 0.0878435 | BG39: 0.0466517 | BH39: 1.4441195e+10 | BI39: 0.015179122
C40: Mexico (2012) | D40: 2012 | E40: 2012 | F40: 117284429 | G40: 4.8116053e+12 | H40: 80.502823 | I40: 103.40738 | J40: 107.65898 | K40: 7.6483312 | L40: 8.9402122 | M40: 4.7041824e+11 | N40: 1.3736285 | O40: 2.747257 | P40: 4.3956112 | R40: 0.018145542 | S40: 0.0092556084 | T40: 9.7098645e+08 | U40: 0.0020640918 | W40: 0.0050760976 | X40: 0.0018220879 | Y40: 2.7162716e+08 | Z40: 0.00057741631 | AB40: 0.0046072502 | AC40: 0.001652699 | AD40: 2.4653866e+08 | AE40: 0.00052408397 | AG40: 0.052728848 | AH40: 0.02985388 | AI40: 5.6431489e+09 | AJ40: 0.011996025 | AL40: 0.030576148 | AM40: 0.013650879 | AN40: 3.2723218e+09 | AO40: 0.0069561966 | AQ40: 0.029190539 | AR40: 0.01287875 | AS40: 3.1240311e+09 | AT40: 0.006640965 | AV40: 0.10671084 | AW40: 0.060953456 | AX40: 1.8272659e+10 | AY40: 0.038843431 | BA40: 0.082444608 | BB40: 0.040151671 | BC40: 1.4117424e+10 | BD40: 0.030010368 | BF40: 0.080736534 | BG40: 0.038885825 | BH40: 1.3824942e+10 | BI40: 0.029388618
C41: Mexico (2014) | D41: 2014 | E41: 2014 | F41: 119906312 | G41: 5.0501217e+12 | H41: 80.502824 | I41: 103.40738 | J41: 116.24798 | K41: 7.6483314 | L41: 8.9402122 | M41: 4.5725751e+11 | N41: 1.3736285 | O41: 2.7472571 | P41: 4.3956113 | R41: 0.019680172 | S41: 0.010798364 | T41: 1.0766482e+09 | U41: 0.0023545774 | W41: 0.0054830904 | X41: 0.0022364606 | Y41: 2.9996482e+08 | Z41: 0.00065600853 | AB41: 0.0053500584 | AC41: 0.0021214635 | AD41: 2.9268701e+08 | AE41: 0.0006400923 | AG41: 0.053462632 | AH41: 0.030976105 | AI41: 5.8495877e+09 | AJ41: 0.012792765 | AL41: 0.030586312 | AM41: 0.014088186 | AN41: 3.3465864e+09 | AO41: 0.0073188221 | AQ41: 0.031051937 | AR41: 0.01416278 | AS41: 3.3975324e+09 | AT41: 0.0074302387 | AV41: 0.10811236 | AW41: 0.061974588 | AX41: 1.8926498e+10 | AY41: 0.041391333 | BA41: 0.082973445 | BB41: 0.040118535 | BC41: 1.4525598e+10 | BD41: 0.031766779 | BF41: 0.085375575 | BG41: 0.04101027 | BH41: 1.4946123e+10 | BI41: 0.032686446
B42: =B39+1 -> 29 | C42: *,** Mongolia (2016) | D42: 2016 | E42: 2016 | F42: 3056359 | H42: 57.265934 | I42: 108.40917 | J42: 165.50894 | K42: 522.49286 | L42: 590.3299 | N42: =IF(E42>2011,1.25*$K42*($J42/$H42)/$L42*($I42/$J42), 1.25*$K42*($J42/$H42)/$K42*($J42/$H42)) -> 2.0944272 | O42: =IF(E42>2011,2.5*$K42*($J42/$H42)/$L42*($I42/$J42), 2.5*$K42*($J42/$H42)/$K42*($J42/$H42)) -> 4.1888543 | P42: =IF(E42>2011, 4*$K42*($J42/$H42)/$L42*($I42/$J42), 4*$K42*($J42/$H42)/$K42*($J42/$H42)) -> 6.7021669
B43: =B42+1 -> 30 | C43: *,** Namibia (2009) | D43: 2009 | E43: 2009 -10 | F43: 2118874 | H43: 71.405037 | I43: 105.00559 | J43: 100 | K43: 5.0639524 | L43: 5.130702 | N43: =IF(E43>2011,1.25*$K43*($J43/$H43)/$L43*($I43/$J43), 1.25*$K43*($J43/$H43)/$K43*($J43/$H43)) -> 1.8142888 | O43: =IF(E43>2011,2.5*$K43*($J43/$H43)/$L43*($I43/$J43), 2.5*$K43*($J43/$H43)/$K43*($J43/$H43)) -> 3.6285775 | P43: =IF(E43>2011, 4*$K43*($J43/$H43)/$L43*($I43/$J43), 4*$K43*($J43/$H43)/$K43*($J43/$H43)) -> 5.805724
B44: =B43+1 -> 31 | C44: Nicaragua (2009) | D44: 2009 | E44: 2009 | F44: 5765733 | G44: 1.3767678e+11 | H44: 62.929181 | I44: 108.08239 | J44: 94.827057 | K44: 7.297259 | L44: 9.1600754 | M44: 1.2520473e+10 | N44: 1.3165224 | O44: 2.6330448 | P44: 4.2128717 | R44: 0.017326605 | S44: 0.0073119599 | T44: 45579639 | U44: 0.0036404086 | W44: 0.017490502 | X44: 0.0074016086 | Y44: 46010788 | Z44: 0.0036748442 | AB44: 0.018569112 | AC44: 0.0080451589 | AD44: 48848196 | AE44: 0.0039014656 | AG44: 0.089323817 | AH44: 0.042035755 | AI44: 4.6995327e+08 | AJ44: 0.037534785 | AL44: 0.089078716 | AM44: 0.042023695 | AN44: 4.6866374e+08 | AO44: 0.037431791 | AQ44: 0.093020501 | AR44: 0.044001143 | AS44: 4.8940238e+08 | AT44: 0.03908817 | AV44: 0.20514757 | AW44: 0.10897331 | AX44: 1.7269261e+09 | AY44: 0.13792819 | BA44: 0.20615319 | BB44: 0.10914149 | BC44: 1.7353914e+09 | BD44: 0.1386043 | BF44: 0.21416527 | BG44: 0.11376484 | BH44: 1.8028368e+09 | BI44: 0.14399111
B45: =B44+1 -> 32 | C45: *,** Niger (2014) | D45: 2014 -15 | E45: 2014 | F45: 17114761 | H45: 88.526352 | I45: 102.94238 | J45: 104.80234 | K45: 267.33093 | L45: 228.75316 | N45: =IF(E45>2011,1.25*$K45*($J45/$H45)/$L45*($I45/$J45), 1.25*$K45*($J45/$H45)/$K45*($J45/$H45)) -> 1.6986885 | O45: =IF(E45>2011,2.5*$K45*($J45/$H45)/$L45*($I45/$J45), 2.5*$K45*($J45/$H45)/$K45*($J45/$H45)) -> 3.3973771 | P45: =IF(E45>2011, 4*$K45*($J45/$H45)/$L45*($I45/$J45), 4*$K45*($J45/$H45)/$K45*($J45/$H45)) -> 5.4358033
B46: =B45+1 -> 33 | C46: Panama (2016) | D46: 2016 | E46: 2015 | F46: 3941606 | G46: 2.0872384e+10 | H46: 81.28521 | I46: 105.8758 | J46: 120.52139 | K46: 0.61135751 | L46: 0.55340803 | M46: 2.3026303e+10 | N46: 1.798643 | O46: 3.5972861 | P46: 5.7556577 | R46: 0.024409555 | S46: 0.014957005 | T46: 43897111 | U46: 0.0019063899 | W46: 0.0088416655 | X46: 0.004501362 | Y46: 15900477 | Z46: 0.00069053541 | AB46: 0.0086143598 | AC46: 0.0042790092 | AD46: 15491701 | AE46: 0.00067278281 | AG46: 0.056602871 | AH46: 0.035244951 | AI46: 2.0358442e+08 | AJ46: 0.0088413856 | AL46: 0.033696913 | AM46: 0.017386548 | AN46: 1.2119821e+08 | AO46: 0.0052634679 | AQ46: 0.033198726 | AR46: 0.017093843 | AS46: 1.1940637e+08 | AT46: 0.005185651 | AV46: 0.095892609 | AW46: 0.061094338 | AX46: 5.5183749e+08 | AY46: 0.023965527 | BA46: 0.071184989 | BB46: 0.039430315 | BC46: 4.0965144e+08 | BD46: 0.017790587 | BF46: 0.070460798 | BG46: 0.038943723 | BH46: 4.0548391e+08 | BI46: 0.017609597
B47: =B46+1 -> 34 | C47: Paraguay (2014) | D47: 2014 | E47: 2014 | F47: 6780504 | G47: 1.4521466e+14 | H47: 71.354743 | I47: 108.25397 | J47: 121.04097 | K47: 2127.7958 | L47: 2309.43 | M47: 4.0231939e+10 | N47: 1.7472544 | O47: 3.4945088 | P47: 5.5912141 | R47: 0.0061887622 | S47: 0.0029091335 | T47: 19145585 | U47: 0.00047588025 | W47: 0.0026940283 | X47: 0.0011175248 | Y47: 8334259.2 | Z47: 0.00020715529 | AB47: 0.0025994993 | AC47: 0.0010488653 | AD47: 8041823.9 | AE47: 0.00019988656 | AG47: 0.025445986 | AH47: 0.012817344 | AI47: 1.5743966e+08 | AJ47: 0.0039133002 | AL47: 0.018178538 | AM47: 0.0082010526 | AN47: 1.1247443e+08 | AO47: 0.0027956503 | AQ47: 0.01830897 | AR47: 0.0081918209 | AS47: 1.1328144e+08 | AT47: 0.0028157091 | AV47: 0.060298406 | AW47: 0.031468596 | AX47: 5.9692623e+08 | AY47: 0.014837123 | BA47: 0.049099099 | BB47: 0.023854462 | BC47: 4.8605829e+08 | BD47: 0.012081404 | BF47: 0.049891048 | BG47: 0.024125838 | BH47: 4.9389822e+08 | BI47: 0.012276272
B48: =B47+1 -> 35 | C48: Peru (2009) | D48: 2009 | E48: 2009 | F48: 29553339 | G48: 306976162912 | H48: 87.125377 | I48: 103.36931 | J48: 98.494685 | K48: 1.6534499 | L48: 1.568639 | M48: 1.6422735e+11 | N48: 1.4192776 | O48: 2.8385552 | P48: 4.5416883 | AG48: 0.0551 | AH48: 0.02791 | AI48: 1.4859049e+09 | AJ48: 0.0090478531 | AL48: 0.0462 | AM48: 0.021681 | AN48: 1.2458949e+09 | AO48: 0.0075864031 | AQ48: 0.0482774 | AR48: 0.0229766 | AS48: 1.301917e+09 | AT48: 0.0079275285 | AV48: 0.116511 | AW48: 0.06438 | AX48: 5.0272021e+09 | AY48: 0.030611235 | BA48: 0.10767 | BB48: 0.05646 | BC48: 4.6457317e+09 | BD48: 0.028288416 | BF48: 0.1117492 | BG48: 0.0588422 | BH48: 4.8217405e+09 | BI48: 0.029360155
C49: Peru (2011) | D49: 2011 | E49: 2011 | F49: 29700727 | G49: 2.2047677e+11 | H49: 87.125374 | I49: 103.36931 | J49: 103.36931 | K49: 1.6534499 | L49: 1.568639 | M49: 1.1238927e+11 | N49: 1.5632377 | O49: 3.1264753 | P49: 5.0023605 | R49: 0.013416039 | S49: 0.0059537522 | T49: 1.8180016e+08 | U49: 0.0016175937 | W49: 0.0093132401 | X49: 0.0038369919 | Y49: 1.2620331e+08 | Z49: 0.0011229125 | AB49: 0.0095323074 | AC49: 0.0039437989 | AD49: 1.2917188e+08 | AE49: 0.0011493258 | AG49: 0.052578647 | AH49: 0.027180459 | AI49: 1.4249819e+09 | AJ49: 0.012678986 | AL49: 0.046167634 | AM49: 0.022320575 | AN49: 1.2512312e+09 | AO49: 0.011133013 | AQ49: 0.047177732 | AR49: 0.022831192 | AS49: 1.2786068e+09 | AT49: 0.011376592 | AV49: 0.1071704 | AW49: 0.060314487 | AX49: 4.6472367e+09 | AY49: 0.041349471 | BA49: 0.10132894 | BB49: 0.054641676 | BC49: 4.3939332e+09 | BD49: 0.039095666 | BF49: 0.10412412 | BG49: 0.056024871 | BH49: 4.5151407e+09 | BI49: 0.040174128
B50: =B48+1 -> 36 | C50: *,** Poland (2014) | D50: 2014 | E50: 2014 | F50: 38011735 | H50: 86.884388 | I50: 104.2394 | J50: 109.08024 | K50: 2.1335834 | L50: 1.920205 | N50: 1.6663345 | O50: 3.3326691 | P50: 5.3322705 | R50: 0.036805701 | S50: 0.032743932 | T50: =$F50*R50*$R$7*365 -> 6.383159e+08 | W50: 0.010605322 | X50: 0.0099268201 | Y50: =$F50*W50*$R$7*365 -> 1.8392654e+08 | AB50: 0.014502639 | AC50: 0.013900556 | AD50: =$F50*AB50*$R$7*365 -> 2.5151715e+08 | AG50: 0.046280711 | AH50: 0.039819555 | AI50: =$F50*AG50*$AG$7*365 -> 1.6052792e+09 | AL50: 0.012641933 | AM50: 0.011272992 | AN50: =$F50*AL50*$AG$7*365 -> 4.3849439e+08 | AQ50: 0.017322918 | AR50: 0.015368685 | AS50: =$F50*AQ50*$AG$7*365 -> 6.0085768e+08 | AV50: 0.057216872 | AW50: 0.047317095 | AX50: =$F50*AV50*$AV$7*365 -> 3.1753724e+09 | BA50: 0.016453284 | BB50: 0.01324353 | BC50: =$F50*BA50*$AV$7*365 -> 9.1311007e+08 | BF50: 0.023491623 | BG50: 0.018405102 | BH50: =$F50*BF50*$AV$7*365 -> 1.3037177e+09
B51: =B50+1 -> 37 | C51: *,** Romania (2016) | D51: 2016 | E51: 2016 | F51: 19702332 | H51: 74.093498 | I51: 105.78925 | J51: 112.44076 | K51: 1.7119983 | L51: 1.8589569 | N51: =IF(E51>2011,1.25*$K51*($J51/$H51)/$L51*($I51/$J51), 1.25*$K51*($J51/$H51)/$K51*($J51/$H51)) -> 1.6436353 | O51: =IF(E51>2011,2.5*$K51*($J51/$H51)/$L51*($I51/$J51), 2.5*$K51*($J51/$H51)/$K51*($J51/$H51)) -> 3.2872706 | P51: =IF(E51>2011, 4*$K51*($J51/$H51)/$L51*($I51/$J51), 4*$K51*($J51/$H51)/$K51*($J51/$H51)) -> 5.259633
